Workbook

Sheet API
A1: can_transact | B1: can_select | C1: chance_of_playing_next_round | D1: chance_of_playing_this_round | E1: code | F1: cost_change_event | G1: cost_change_event_fall | H1: cost_change_start | I1: cost_change_start_fall | J1: price_change_percent | K1: dreamteam_count | L1: element_type | M1: ep_next | N1: ep_this | O1: event_points | P1: first_name | Q1: form | R1: id | S1: in_dreamteam | T1: news | U1: news_added | V1: now_cost | W1: photo | X1: points_per_game | Y1: removed | Z1: second_name | AA1: selected_by_percent | AB1: special | AC1: squad_number | AD1: status | AE1: team | AF1: team_code | AG1: total_points | AH1: transfers_in | AI1: transfers_in_event | AJ1: transfers_out | AK1: transfers_out_event | AL1: value_form | AM1: value_season | AN1: web_name | AO1: known_name | AP1: region | AQ1: team_join_date | AR1: birth_date | AS1: has_temporary_code | AT1: opta_code | AU1: minutes | AV1: goals_scored | AW1: assists | AX1: clean_sheets | AY1: goals_conceded | AZ1: own_goals | BA1: penalties_saved | BB1: penalties_missed | BC1: yellow_cards | BD1: red_cards | BE1: saves | BF1: bonus | BG1: bps | BH1: influence | BI1: creativity | BJ1: threat | BK1: ict_index | BL1: clearances_blocks_interceptions | BM1: recoveries | BN1: tackles | BO1: defensive_contribution | BP1: starts | BQ1: expected_goals | BR1: expected_assists | BS1: expected_goal_involvements | BT1: expected_goals_conceded | BU1: corners_and_indirect_freekicks_order | BV1: corners_and_indirect_freekicks_text | BW1: direct_freekicks_order | BX1: direct_freekicks_text | BY1: penalties_order | BZ1: penalties_text | CA1: scout_risks | CB1: scout_news_link | CC1: influence_rank | CD1: influence_rank_type | CE1: creativity_rank | CF1: creativity_rank_type | CG1: threat_rank | CH1: threat_rank_type | CI1: ict_index_rank | CJ1: ict_index_rank_type | CK1: expected_goals_per_90 | CL1: saves_per_90 | CM1: expected_assists_per_90 | CN1: expected_goal_involvements_per_90 | CO1: expected_goals_conceded_per_90 | CP1: goals_conceded_per_90 | CQ1: now_cost_rank | CR1: now_cost_rank_type | CS1: form_rank | CT1: form_rank_type | CU1: points_per_game_rank | CV1: points_per_game_rank_type | CW1: selected_rank | CX1: selected_rank_type | CY1: starts_per_90 | CZ1: clean_sheets_per_90 | DA1: defensive_contribution_per_90
A2: TRUE | B2: TRUE | E2: 154561 | F2: 0 | G2: 0 | H2: 0 | I2: 0 | J2: 0 | K2: 0 | L2: 1 | M2: 4 | O2: 0 | P2: David | Q2: 0 | R2: 1 | S2: FALSE | V2: 60 | W2: 154561.jpg | X2: 4.4 | Y2: FALSE | Z2: Raya Martín | AA2: 29.3 | AB2: FALSE | AD2: a | AE2: 1 | AF2: 3 | AG2: 162 | AH2: 0 | AI2: 0 | AJ2: 0 | AK2: 0 | AL2: 0 | AM2: 27 | AN2: Raya | AS2: FALSE | AT2: p154561 | AU2: 3330 | AV2: 0 | AW2: 0 | AX2: 19 | AY2: 26 | AZ2: 0 | BA2: 0 | BB2: 0 | BC2: 1 | BD2: 0 | BE2: 60 | BF2: 11 | BG2: 633 | BH2: 541.6 | BI2: 33.5 | BJ2: 0 | BK2: 57.5 | BL2: 0 | BM2: 0 | BN2: 0 | BO2: 0 | BP2: 37 | BQ2: 0 | BR2: 0.07 | BS2: 0.07 | BT2: 27.56 | CC2: 96 | CD2: 16 | CE2: 304 | CF2: 3 | CG2: 549 | CH2: 60 | CI2: 229 | CJ2: 16 | CK2: 0 | CL2: 1.62 | CM2: 0 | CN2: 0 | CO2: 0.74 | CP2: 0.7 | CQ2: 60 | CR2: 1 | CS2: 454 | CT2: 60 | CU2: 32 | CV2: 3 | CW2: 6 | CX2: 1 | CY2: 1 | CZ2: 0.51 | DA2: 0
A3: TRUE | B3: TRUE | E3: 109745 | F3: 0 | G3: 0 | H3: 0 | I3: 0 | J3: 0 | K3: 0 | L3: 1 | M3: 2.6 | O3: 0 | P3: Kepa | Q3: 0 | R3: 2 | S3: FALSE | V3: 50 | W3: 109745.jpg | X3: 2 | Y3: FALSE | Z3: Arrizabalaga Revuelta | AA3: 0.3 | AB3: FALSE | AD3: a | AE3: 1 | AF3: 3 | AG3: 2 | AH3: 0 | AI3: 0 | AJ3: 0 | AK3: 0 | AL3: 0 | AM3: 0.4 | AN3: Arrizabalaga | AS3: FALSE | AT3: p109745 | AU3: 90 | AV3: 0 | AW3: 0 | AX3: 0 | AY3: 1 | AZ3: 0 | BA3: 0 | BB3: 0 | BC3: 0 | BD3: 0 | BE3: 2 | BF3: 0 | BG3: 11 | BH3: 19.8 | BI3: 0 | BJ3: 0 | BK3: 2 | BL3: 0 | BM3: 0 | BN3: 0 | BO3: 0 | BP3: 1 | BQ3: 0 | BR3: 0 | BS3: 0 | BT3: 0.98 | CC3: 357 | CD3: 30 | CE3: 486 | CF3: 54 | CG3: 480 | CH3: 49 | CI3: 373 | CJ3: 30 | CK3: 0 | CL3: 2 | CM3: 0 | CN3: 0 | CO3: 0.98 | CP3: 1 | CQ3: 222 | CR3: 8 | CS3: 200 | CT3: 46 | CU3: 285 | CV3: 28 | CW3: 315 | CX3: 37 | CY3: 1 | CZ3: 0 | DA3: 0
A4: TRUE | B4: TRUE | E4: 437495 | F4: 0 | G4: 0 | H4: 0 | I4: 0 | J4: 0 | K4: 0 | L4: 1 | M4: 2.6 | O4: 0 | P4: Illan | Q4: 0 | R4: 3 | S4: FALSE | V4: 50 | W4: 437495.jpg | X4: 0 | Y4: FALSE | Z4: Meslier | AA4: 0.1 | AB4: FALSE | AD4: a | AE4: 1 | AF4: 3 | AG4: 0 | AH4: 0 | AI4: 0 | AJ4: 0 | AK4: 0 | AL4: 0 | AM4: 0 | AN4: Meslier | AS4: FALSE | AT4: p437495 | AU4: 0 | AV4: 11 | AW4: 0 | AX4: 0 | AY4: 0 | AZ4: 0 | BA4: 0 | BB4: 0 | BC4: 0 | BD4: 0 | BE4: 0 | BF4: 0 | BG4: 11 | BH4: 0 | BI4: 0 | BJ4: 0 | BK4: 0 | BL4: 0 | BM4: 0 | BN4: 0 | BO4: 0 | BP4: 0 | BQ4: 0 | BR4: 0 | BS4: 0 | BT4: 0 | CC4: 508 | CD4: 60 | CE4: 505 | CF4: 57 | CG4: 502 | CH4: 55 | CI4: 508 | CJ4: 60 | CK4: 0 | CL4: 0 | CM4: 0 | CN4: 0 | CO4: 0 | CP4: 0 | CQ4: 285 | CR4: 14 | CS4: 263 | CT4: 52 | CU4: 508 | CV4: 60 | CW4: 431 | CX4: 52 | CY4: 0 | CZ4: 0 | DA4: 0
A5: TRUE | B5: TRUE | E5: 226597 | F5: 0 | G5: 0 | H5: 0 | I5: 0 | J5: 0 | K5: 0 | L5: 2 | M5: 4 | O5: 0 | P5: Gabriel | Q5: 0 | R5: 4 | S5: FALSE | V5: 80 | W5: 226597.jpg | X5: 6.5 | Y5: FALSE | Z5: dos Santos Magalhães | AA5: 24.2 | AB5: FALSE | AD5: a | AE5: 1 | AF5: 3 | AG5: 209 | AH5: 0 | AI5: 0 | AJ5: 0 | AK5: 0 | AL5: 0 | AM5: 26.1 | AN5: Gabriel | AS5: FALSE | AT5: p226597 | AU5: 2750 | AV5: 3 | AW5: 5 | AX5: 18 | AY5: 20 | AZ5: 0 | BA5: 0 | BB5: 0 | BC5: 4 | BD5: 0 | BE5: 0 | BF5: 30 | BG5: 724 | BH5: 824 | BI5: 128.5 | BJ5: 298 | BK5: 125 | BL5: 0 | BM5: 0 | BN5: 0 | BO5: 0 | BP5: 30 | BQ5: 2.94 | BR5: 1.75 | BS5: 4.69 | BT5: 22.01 | CC5: 25 | CD5: 9 | CE5: 219 | CF5: 61 | CG5: 101 | CH5: 15 | CI5: 80 | CJ5: 18 | CK5: 0.1 | CL5: 0 | CM5: 0.06 | CN5: 0.16 | CO5: 0.72 | CP5: 0.65 | CQ5: 9 | CR5: 1 | CS5: 549 | CT5: 184 | CU5: 4 | CV5: 1 | CW5: 9 | CX5: 3 | CY5: 0.98 | CZ5: 0.59 | DA5: 0
A6: TRUE | B6: TRUE | C6: 0 | E6: 445122 | F6: 0 | G6: 0 | H6: 0 | I6: 0 | J6: 0 | K6: 0 | L6: 2 | M6: 0 | O6: 0 | P6: Jurriën | Q6: 0 | R6: 5 | S6: FALSE | T6: Groin injury - Expected back 21 Aug | U6: 2026-07-23T12:01:23.272929Z | V6: 65 | W6: 445122.jpg | X6: 5 | Y6: FALSE | Z6: Timber | AA6: 0.9 | AB6: FALSE | AD6: i | AE6: 1 | AF6: 3 | AG6: 149 | AH6: 0 | AI6: 0 | AJ6: 0 | AK6: 0 | AL6: 0 | AM6: 22.9 | AN6: J.Timber | AS6: FALSE | AT6: p445122 | AU6: 2452 | AV6: 3 | AW6: 6 | AX6: 13 | AY6: 20 | AZ6: 0 | BA6: 0 | BB6: 0 | BC6: 5 | BD6: 0 | BE6: 0 | BF6: 9 | BG6: 532 | BH6: 499 | BI6: 402.6 | BJ6: 352 | BK6: 125.7 | BL6: 0 | BM6: 0 | BN6: 0 | BO6: 0 | BP6: 28 | BQ6: 4.71 | BR6: 1.53 | BS6: 6.24 | BT6: 17.45 | CB6: https://x.com/onsoranje/status/2064038072455495714?utm_source=premier-league-web&utm_medium=referral&utm_campaign=pl-referral-always-on&utm_term=injuries&utm_content=club-injury-article | CC6: 114 | CD6: 49 | CE6: 76 | CF6: 18 | CG6: 76 | CH6: 9 | CI6: 79 | CJ6: 17 | CK6: 0.17 | CL6: 0 | CM6: 0.06 | CN6: 0.23 | CO6: 0.64 | CP6: 0.73 | CQ6: 47 | CR6: 3 | CS6: 520 | CT6: 182 | CU6: 13 | CV6: 3 | CW6: 205 | CX6: 72 | CY6: 1.03 | CZ6: 0.48 | DA6: 0
A7: TRUE | B7: TRUE | C7: 0 | E7: 462424 | F7: 0 | G7: 0 | H7: 0 | I7: 0 | J7: 0 | K7: 0 | L7: 2 | M7: 0 | O7: 0 | P7: William | Q7: 0 | R7: 6 | S7: FALSE | T7: Back injury - Unknown return date | U7: 2026-07-23T12:01:23.289376Z | V7: 60 | W7: 462424.jpg | X7: 4.4 | Y7: FALSE | Z7: Saliba | AA7: 0.5 | AB7: FALSE | AD7: i | AE7: 1 | AF7: 3 | AG7: 137 | AH7: 0 | AI7: 0 | AJ7: 0 | AK7: 0 | AL7: 0 | AM7: 22.8 | AN7: Saliba | AS7: FALSE | AT7: p462424 | AU7: 2614 | AV7: 1 | AW7: 0 | AX7: 15 | AY7: 20 | AZ7: 0 | BA7: 0 | BB7: 0 | BC7: 2 | BD7: 0 | BE7: 0 | BF7: 12 | BG7: 581 | BH7: 552.6 | BI7: 201 | BJ7: 90 | BK7: 84.3 | BL7: 0 | BM7: 0 | BN7: 0 | BO7: 0 | BP7: 30 | BQ7: 0.88 | BR7: 1.21 | BS7: 2.09 | BT7: 20.41 | CB7: https://www.arsenal.com/news/medical-update-william-saliba-aVUca3q2han2 | CC7: 92 | CD7: 41 | CE7: 167 | CF7: 41 | CG7: 245 | CH7: 76 | CI7: 164 | CJ7: 57 | CK7: 0.03 | CL7: 0 | CM7: 0.04 | CN7: 0.07 | CO7: 0.7 | CP7: 0.69 | CQ7: 88 | CR7: 9 | CS7: 482 | CT7: 179 | CU7: 34 | CV7: 13 | CW7: 266 | CX7: 97 | CY7: 1.03 | CZ7: 0.52 | DA7: 0
A8: TRUE | B8: TRUE | E8: 499169 | F8: 0 | G8: 0 | H8: 0 | I8: 0 | J8: 0 | K8: 0 | L8: 3 | M8: 2 | O8: 0 | P8: Myles | Q8: 0 | R8: 7 | S8: FALSE | V8: 55 | W8: 499169.jpg | X8: 1.4 | Y8: FALSE | Z8: Lewis-Skelly | AA8: 0.3 | AB8: FALSE | AD8: a | AE8: 1 | AF8: 3 | AG8: 29 | AH8: 0 | AI8: 0 | AJ8: 0 | AK8: 0 | AL8: 0 | AM8: 5.3 | AN8: Lewis-Skelly | AS8: FALSE | AT8: p499169 | AU8: 697 | AV8: 0 | AW8: 0 | AX8: 2 | AY8: 8 | AZ8: 0 | BA8: 0 | BB8: 0 | BC8: 3 | BD8: 0 | BE8: 0 | BF8: 0 | BG8: 110 | BH8: 73.2 | BI8: 74.6 | BJ8: 29 | BK8: 17.6 | BL8: 0 | BM8: 0 | BN8: 0 | BO8: 0 | BP8: 5 | BQ8: 0.1 | BR8: 0.2 | BS8: 0.3 | BT8: 9.01 | CC8: 318 | CD8: 144 | CE8: 262 | CF8: 145 | CG8: 302 | CH8: 157 | CI8: 315 | CJ8: 150 | CK8: 0.01 | CL8: 0 | CM8: 0.03 | CN8: 0.04 | CO8: 1.16 | CP8: 1.03 | CQ8: 188 | CR8: 116 | CS8: 425 | CT8: 159 | CU8: 341 | CV8: 155 | CW8: 310 | CX8: 107 | CY8: 0.65 | CZ8: 0.26 | DA8: 0
A9: TRUE | B9: TRUE | E9: 466075 | F9: 0 | G9: 0 | H9: 0 | I9: 0 | J9: 0 | K9: 0 | L9: 2 | M9: 2.5 | O9: 0 | P9: Riccardo | Q9: 0 | R9: 8 | S9: FALSE | V9: 55 | W9: 466075.jpg | X9: 4.2 | Y9: FALSE | Z9: Calafiori | AA9: 11.5 | AB9: FALSE | AD9: a | AE9: 1 | AF9: 3 | AG9: 109 | AH9: 0 | AI9: 0 | AJ9: 0 | AK9: 0 | AL9: 0 | AM9: 19.8 | AN9: Calafiori | AS9: FALSE | AT9: p466075 | AU9: 1697 | AV9: 1 | AW9: 2 | AX9: 13 | AY9: 8 | AZ9: 0 | BA9: 0 | BB9: 0 | BC9: 5 | BD9: 0 | BE9: 0 | BF9: 6 | BG9: 389 | BH9: 283 | BI9: 182.3 | BJ9: 313 | BK9: 77.9 | BL9: 0 | BM9: 0 | BN9: 0 | BO9: 0 | BP9: 22 | BQ9: 3.36 | BR9: 0.76 | BS9: 4.12 | BT9: 9.72 | CC9: 211 | CD9: 80 | CE9: 182 | CF9: 46 | CG9: 93 | CH9: 12 | CI9: 178 | CJ9: 62 | CK9: 0.18 | CL9: 0 | CM9: 0.04 | CN9: 0.22 | CO9: 0.52 | CP9: 0.42 | CQ9: 173 | CR9: 24 | CS9: 410 | CT9: 166 | CU9: 41 | CV9: 16 | CW9: 41 | CX9: 15 | CY9: 1.17 | CZ9: 0.69 | DA9: 0
A10: TRUE | B10: TRUE | E10: 448104 | F10: 0 | G10: 0 | H10: 0 | I10: 0 | J10: 0 | K10: 0 | L10: 2 | M10: 2.5 | O10: 0 | P10: Piero | Q10: 0 | R10: 9 | S10: FALSE | V10: 55 | W10: 448104.jpg | X10: 3.5 | Y10: FALSE | Z10: Hincapié | AA10: 6.1 | AB10: FALSE | AD10: a | AE10: 1 | AF10: 3 | AG10: 87 | AH10: 0 | AI10: 0 | AJ10: 0 | AK10: 0 | AL10: 0 | AM10: 15.8 | AN10: Hincapie | AS10: FALSE | AT10: p448104 | AU10: 1787 | AV10: 1 | AW10: 2 | AX10: 5 | AY10: 19 | AZ10: 1 | BA10: 0 | BB10: 0 | BC10: 2 | BD10: 0 | BE10: 0 | BF10: 7 | BG10: 335 | BH10: 453.6 | BI10: 184.7 | BJ10: 72 | BK10: 70.9 | BL10: 0 | BM10: 0 | BN10: 0 | BO10: 0 | BP10: 20 | BQ10: 0.36 | BR10: 1.67 | BS10: 2.03 | BT10: 17.53 | CC10: 129 | CD10: 54 | CE10: 180 | CF10: 45 | CG10: 258 | CH10: 82 | CI10: 196 | CJ10: 65 | CK10: 0.02 | CL10: 0 | CM10: 0.08 | CN10: 0.1 | CO10: 0.88 | CP10: 0.96 | CQ10: 164 | CR10: 21 | CS10: 401 | CT10: 163 | CU10: 105 | CV10: 43 | CW10: 68 | CX10: 27 | CY10: 1.01 | CZ10: 0.25 | DA10: 0
A11: TRUE | B11: TRUE | C11: 0 | E11: 198869 | F11: 0 | G11: 0 | H11: 0 | I11: 0 | J11: 0 | K11: 0 | L11: 2 | M11: 0 | O11: 0 | P11: Benjamin | Q11: 0 | R11: 10 | S11: FALSE | T11: Knee injury - Expected back 21 Aug | U11: 2026-07-23T12:01:23.305229Z | V11: 55 | W11: 198869.jpg | X11: 3.8 | Y11: FALSE | Z11: White | AA11: 0 | AB11: FALSE | AD11: i | AE11: 1 | AF11: 3 | AG11: 45 | AH11: 0 | AI11: 0 | AJ11: 0 | AK11: 0 | AL11: 0 | AM11: 8.2 | AN11: White | AS11: FALSE | AT11: p198869 | AU11: 699 | AV11: 0 | AW11: 1 | AX11: 5 | AY11: 6 | AZ11: 0 | BA11: 0 | BB11: 0 | BC11: 0 | BD11: 0 | BE11: 0 | BF11: 3 | BG11: 181 | BH11: 154.8 | BI11: 133.4 | BJ11: 54 | BK11: 34.3 | BL11: 0 | BM11: 0 | BN11: 0 | BO11: 0 | BP11: 9 | BQ11: 0.45 | BR11: 0.69 | BS11: 1.14 | BT11: 8.68 | CC11: 272 | CD11: 101 | CE11: 213 | CF11: 58 | CG11: 275 | CH11: 89 | CI11: 280 | CJ11: 92 | CK11: 0.06 | CL11: 0 | CM11: 0.09 | CN11: 0.15 | CO11: 1.12 | CP11: 0.77 | CQ11: 127 | CR11: 13 | CS11: 364 | CT11: 155 | CU11: 71 | CV11: 27 | CW11: 527 | CX11: 179 | CY11: 1.16 | CZ11: 0.64 | DA11: 0
A12: TRUE | B12: TRUE | E12: 500040 | F12: 0 | G12: 0 | H12: 0 | I12: 0 | J12: 0 | K12: 0 | L12: 2 | M12: 2.5 | O12: 0 | P12: Cristhian | Q12: 0 | R12: 11 | S12: FALSE | V12: 55 | W12: 500040.jpg | X12: 2 | Y12: FALSE | Z12: Mosquera | AA12: 14.9 | AB12: FALSE | AD12: a | AE12: 1 | AF12: 3 | AG12: 40 | AH12: 0 | AI12: 0 | AJ12: 0 | AK12: 0 | AL12: 0 | AM12: 7.3 | AN12: Mosquera | AS12: FALSE | AT12: p500040 | AU12: 986 | AV12: 0 | AW12: 0 | AX12: 3 | AY12: 8 | AZ12: 0 | BA12: 0 | BB12: 0 | BC12: 4 | BD12: 0 | BE12: 0 | BF12: 1 | BG12: 195 | BH12: 219.2 | BI12: 88.7 | BJ12: 20 | BK12: 32.9 | BL12: 0 | BM12: 0 | BN12: 0 | BO12: 0 | BP12: 9 | BQ12: 0.1 | BR12: 0.63 | BS12: 0.73 | BT12: 9.04 | CC12: 239 | CD12: 90 | CE12: 243 | CF12: 79 | CG12: 310 | CH12: 108 | CI12: 282 | CJ12: 93 | CK12: 0.01 | CL12: 0 | CM12: 0.06 | CN12: 0.07 | CO12: 0.83 | CP12: 0.73 | CQ12: 190 | CR12: 28 | CS12: 427 | CT12: 170 | CU12: 288 | CV12: 110 | CW12: 27 | CX12: 10 | CY12: 0.82 | CZ12: 0.27 | DA12: 0
A13: TRUE | B13: TRUE | E13: 223340 | F13: 0 | G13: 0 | H13: 0 | I13: 0 | J13: 0 | K13: 0 | L13: 3 | M13: 3.2 | O13: 0 | P13: Bukayo | Q13: 0 | R13: 12 | S13: FALSE | V13: 95 | W13: 223340.jpg | X13: 5.1 | Y13: FALSE | Z13: Saka | AA13: 11.3 | AB13: FALSE | AD13: a | AE13: 1 | AF13: 3 | AG13: 157 | AH13: 0 | AI13: 0 | AJ13: 0 | AK13: 0 | AL13: 0 | AM13: 16.5 | AN13: Saka | AS13: FALSE | AT13: p223340 | AU13: 2218 | AV13: 7 | AW13: 10 | AX13: 12 | AY13: 16 | AZ13: 0 | BA13: 0 | BB13: 0 | BC13: 2 | BD13: 0 | BE13: 0 | BF13: 18 | BG13: 570 | BH13: 627 | BI13: 847.6 | BJ13: 828 | BK13: 230.6 | BL13: 0 | BM13: 0 | BN13: 0 | BO13: 0 | BP13: 25 | BQ13: 7.57 | BR13: 7.16 | BS13: 14.73 | BT13: 15.57 | BU13: 6 | BW13: 2 | BY13: 1 | CC13: 68 | CD13: 20 | CE13: 12 | CF13: 11 | CG13: 11 | CH13: 6 | CI13: 10 | CJ13: 8 | CK13: 0.31 | CL13: 0 | CM13: 0.29 | CN13: 0.6 | CO13: 0.63 | CP13: 0.65 | CQ13: 3 | CR13: 2 | CS13: 555 | CT13: 244 | CU13: 12 | CV13: 6 | CW13: 42 | CX13: 14 | CY13: 1.01 | CZ13: 0.49 | DA13: 0
A14: TRUE | B14: TRUE | E14: 204480 | F14: 0 | G14: 0 | H14: 0 | I14: 0 | J14: 0 | K14: 0 | L14: 3 | M14: 2.6 | O14: 0 | P14: Declan | Q14: 0 | R14: 13 | S14: FALSE | V14: 75 | W14: 204480.jpg | X14: 5.1 | Y14: FALSE | Z14: Rice | AA14: 23.1 | AB14: FALSE | AD14: a | AE14: 1 | AF14: 3 | AG14: 184 | AH14: 0 | AI14: 0 | AJ14: 0 | AK14: 0 | AL14: 0 | AM14: 24.5 | AN14: Rice | AS14: FALSE | AT14: p204480 | AU14: 3093 | AV14: 4 | AW14: 9 | AX14: 18 | AY14: 25 | AZ14: 0 | BA14: 0 | BB14: 0 | BC14: 3 | BD14: 0 | BE14: 0 | BF14: 23 | BG14: 790 | BH14: 827.2 | BI14: 1027.4 | BJ14: 298 | BK14: 215.4 | BL14: 0 | BM14: 0 | BN14: 0 | BO14: 0 | BP14: 35 | BQ14: 3.15 | BR14: 7.32 | BS14: 10.47 | BT14: 23.87 | BU14: 5 | BW14: 1 | CC14: 24 | CD14: 8 | CE14: 4 | CF14: 4 | CG14: 100 | CH14: 63 | CI14: 14 | CJ14: 11 | CK14: 0.09 | CL14: 0 | CM14: 0.21 | CN14: 0.3 | CO14: 0.69 | CP14: 0.73 | CQ14: 13 | CR14: 8 | CS14: 537 | CT14: 234 | CU14: 9 | CV14: 4 | CW14: 12 | CX14: 4 | CY14: 1.02 | CZ14: 0.52 | DA14: 0
A15: TRUE | B15: TRUE | E15: 232413 | F15: 0 | G15: 0 | H15: 0 | I15: 0 | J15: 0 | K15: 0 | L15: 3 | M15: 2.3 | O15: 0 | P15: Eberechi | Q15: 0 | R15: 14 | S15: FALSE | V15: 65 | W15: 232413.jpg | X15: 3.4 | Y15: FALSE | Z15: Eze | AA15: 3.1 | AB15: FALSE | AD15: a | AE15: 1 | AF15: 3 | AG15: 113 | AH15: 0 | AI15: 0 | AJ15: 0 | AK15: 0 | AL15: 0 | AM15: 17.4 | AN15: Eze | AS15: FALSE | AT15: p232413 | AU15: 1885 | AV15: 7 | AW15: 3 | AX15: 11 | AY15: 14 | AZ15: 0 | BA15: 0 | BB15: 0 | BC15: 1 | BD15: 0 | BE15: 0 | BF15: 8 | BG15: 439 | BH15: 393.4 | BI15: 305.7 | BJ15: 455 | BK15: 115.1 | BL15: 0 | BM15: 0 | BN15: 0 | BO15: 0 | BP15: 22 | BQ15: 5.18 | BR15: 2.66 | BS15: 7.84 | BT15: 14.21 | BW15: 3 | CC15: 156 | CD15: 61 | CE15: 123 | CF15: 85 | CG15: 47 | CH15: 28 | CI15: 95 | CJ15: 54 | CK15: 0.25 | CL15: 0 | CM15: 0.13 | CN15: 0.38 | CO15: 0.68 | CP15: 0.67 | CQ15: 41 | CR15: 28 | CS15: 514 | CT15: 216 | CU15: 122 | CV15: 50 | CW15: 102 | CX15: 33 | CY15: 1.05 | CZ15: 0.53 | DA15: 0
A16: TRUE | B16: TRUE | E16: 184029 | F16: 0 | G16: 0 | H16: 0 | I16: 0 | J16: 0 | K16: 0 | L16: 3 | M16: 2.3 | O16: 0 | P16: Martin | Q16: 0 | R16: 15 | S16: FALSE | V16: 65 | W16: 184029.jpg | X16: 3.1 | Y16: FALSE | Z16: Ødegaard | AA16: 2.7 | AB16: FALSE | AD16: a | AE16: 1 | AF16: 3 | AG16: 74 | AH16: 0 | AI16: 0 | AJ16: 0 | AK16: 0 | AL16: 0 | AM16: 11.4 | AN16: Ødegaard | AS16: FALSE | AT16: p184029 | AU16: 1363 | AV16: 1 | AW16: 7 | AX16: 6 | AY16: 13 | AZ16: 0 | BA16: 0 | BB16: 0 | BC16: 0 | BD16: 0 | BE16: 0 | BF16: 5 | BG16: 306 | BH16: 311.8 | BI16: 564.4 | BJ16: 168 | BK16: 104.4 | BL16: 0 | BM16: 0 | BN16: 0 | BO16: 0 | BP16: 16 | BQ16: 1.25 | BR16: 3.65 | BS16: 4.9 | BT16: 16.2 | BU16: 8 | BY16: 3 | CC16: 196 | CD16: 85 | CE16: 39 | CF16: 36 | CG16: 180 | CH16: 98 | CI16: 120 | CJ16: 68 | CK16: 0.08 | CL16: 0 | CM16: 0.24 | CN16: 0.32 | CO16: 1.07 | CP16: 0.86 | CQ16: 35 | CR16: 23 | CS16: 508 | CT16: 211 | CU16: 163 | CV16: 62 | CW16: 109 | CX16: 35 | CY16: 1.06 | CZ16: 0.4 | DA16: 0
A17: TRUE | B17: TRUE | E17: 248857 | F17: 0 | G17: 0 | H17: 0 | I17: 0 | J17: 0 | K17: 0 | L17: 3 | M17: 2.3 | O17: 0 | P17: Noni | Q17: 0 | R17: 16 | S17: FALSE | V17: 65 | W17: 248857.jpg | X17: 2.8 | Y17: FALSE | Z17: Madueke | AA17: 0.3 | AB17: FALSE | AD17: a | AE17: 1 | AF17: 3 | AG17: 72 | AH17: 0 | AI17: 0 | AJ17: 0 | AK17: 0 | AL17: 0 | AM17: 11.1 | AN17: Madueke | AS17: FALSE | AT17: p248857 | AU17: 1205 | AV17: 3 | AW17: 1 | AX17: 8 | AY17: 9 | AZ17: 0 | BA17: 0 | BB17: 0 | BC17: 0 | BD17: 0 | BE17: 0 | BF17: 9 | BG17: 254 | BH17: 257.4 | BI17: 352.8 | BJ17: 404 | BK17: 101.3 | BL17: 0 | BM17: 0 | BN17: 0 | BO17: 0 | BP17: 16 | BQ17: 1.23 | BR17: 2.86 | BS17: 4.09 | BT17: 12.77 | BU17: 7 | CC17: 221 | CD17: 98 | CE17: 98 | CF17: 71 | CG17: 64 | CH17: 38 | CI17: 126 | CJ17: 72 | CK17: 0.09 | CL17: 0 | CM17: 0.21 | CN17: 0.3 | CO17: 0.95 | CP17: 0.67 | CQ17: 43 | CR17: 30 | CS17: 516 | CT17: 218 | CU17: 201 | CV17: 77 | CW17: 307 | CX17: 105 | CY17: 1.2 | CZ17: 0.6 | DA17: 0
A18: TRUE | B18: TRUE | E18: 195384 | F18: 0 | G18: 0 | H18: 0 | I18: 0 | J18: 0 | K18: 0 | L18: 3 | M18: 2.1 | O18: 0 | P18: Mikel | Q18: 0 | R18: 17 | S18: FALSE | V18: 60 | W18: 195384.jpg | X18: 3 | Y18: FALSE | Z18: Merino Zazón | AA18: 1.1 | AB18: FALSE | AD18: a | AE18: 1 | AF18: 3 | AG18: 67 | AH18: 0 | AI18: 0 | AJ18: 0 | AK18: 0 | AL18: 0 | AM18: 11.2 | AN18: Merino | AS18: FALSE | AT18: p195384 | AU18: 1024 | AV18: 4 | AW18: 3 | AX18: 4 | AY18: 10 | AZ18: 0 | BA18: 0 | BB18: 0 | BC18: 1 | BD18: 0 | BE18: 0 | BF18: 5 | BG18: 236 | BH18: 304.4 | BI18: 191.8 | BJ18: 244 | BK18: 73.6 | BL18: 0 | BM18: 0 | BN18: 0 | BO18: 0 | BP18: 10 | BQ18: 3.36 | BR18: 1.45 | BS18: 4.81 | BT18: 7.36 | CC18: 199 | CD18: 88 | CE18: 176 | CF18: 118 | CG18: 119 | CH18: 69 | CI18: 189 | CJ18: 94 | CK18: 0.3 | CL18: 0 | CM18: 0.13 | CN18: 0.43 | CO18: 0.65 | CP18: 0.88 | CQ18: 64 | CR18: 42 | CS18: 458 | CT18: 177 | CU18: 175 | CV18: 68 | CW18: 185 | CX18: 61 | CY18: 0.88 | CZ18: 0.35 | DA18: 0
A19: TRUE | B19: TRUE | E19: 444145 | F19: 0 | G19: 0 | H19: 0 | I19: 0 | J19: 0 | K19: 0 | L19: 3 | M19: 2.3 | O19: 0 | P19: Gabriel | Q19: 0 | R19: 18 | S19: FALSE | V19: 65 | W19: 444145.jpg | X19: 1.9 | Y19: FALSE | Z19: Martinelli Silva | AA19: 0.3 | AB19: FALSE | AD19: a | AE19: 1 | AF19: 3 | AG19: 57 | AH19: 0 | AI19: 0 | AJ19: 0 | AK19: 0 | AL19: 0 | AM19: 8.8 | AN19: Martinelli | AS19: FALSE | AT19: p444145 | AU19: 1065 | AV19: 1 | AW19: 5 | AX19: 2 | AY19: 8 | AZ19: 0 | BA19: 0 | BB19: 0 | BC19: 3 | BD19: 0 | BE19: 0 | BF19: 3 | BG19: 195 | BH19: 204.6 | BI19: 202.2 | BJ19: 390 | BK19: 79 | BL19: 0 | BM19: 0 | BN19: 0 | BO19: 0 | BP19: 11 | BQ19: 4.12 | BR19: 1.27 | BS19: 5.39 | BT19: 10.51 | CC19: 249 | CD19: 112 | CE19: 166 | CF19: 111 | CG19: 69 | CH19: 42 | CI19: 177 | CJ19: 86 | CK19: 0.35 | CL19: 0 | CM19: 0.11 | CN19: 0.46 | CO19: 0.89 | CP19: 0.68 | CQ19: 45 | CR19: 32 | CS19: 518 | CT19: 220 | CU19: 298 | CV19: 130 | CW19: 317 | CX19: 112 | CY19: 0.93 | CZ19: 0.17 | DA19: 0
A20: TRUE | B20: TRUE | E20: 481655 | F20: 0 | G20: 0 | H20: 0 | I20: 0 | J20: 0 | K20: 0 | L20: 3 | M20: 2 | O20: 0 | P20: Martín | Q20: 0 | R20: 19 | S20: FALSE | V20: 55 | W20: 481655.jpg | X20: 3.5 | Y20: FALSE | Z20: Zubimendi Ibáñez | AA20: 1.3 | AB20: FALSE | AD20: a | AE20: 1 | AF20: 3 | AG20: 133 | AH20: 0 | AI20: 0 | AJ20: 0 | AK20: 0 | AL20: 0 | AM20: 24.2 | AN20: Zubimendi | AS20: FALSE | AT20: p481655 | AU20: 2991 | AV20: 5 | AW20: 1 | AX20: 16 | AY20: 25 | AZ20: 0 | BA20: 0 | BB20: 0 | BC20: 4 | BD20: 0 | BE20: 0 | BF20: 9 | BG20: 604 | BH20: 603.2 | BI20: 385.1 | BJ20: 271 | BK20: 126.2 | BL20: 0 | BM20: 0 | BN20: 0 | BO20: 0 | BP20: 34 | BQ20: 2.84 | BR20: 2.27 | BS20: 5.11 | BT20: 26.09 | CC20: 74 | CD20: 24 | CE20: 85 | CF20: 63 | CG20: 110 | CH20: 64 | CI20: 78 | CJ20: 49 | CK20: 0.09 | CL20: 0 | CM20: 0.07 | CN20: 0.16 | CO20: 0.79 | CP20: 0.75 | CQ20: 180 | CR20: 110 | CS20: 417 | CT20: 153 | CU20: 107 | CV20: 42 | CW20: 173 | CX20: 57 | CY20: 1.02 | CZ20: 0.48 | DA20: 0
A21: TRUE | B21: TRUE | E21: 616077 | F21: 0 | G21: 0 | H21: 0 | I21: 0 | J21: 0 | K21: 0 | L21: 3 | M21: 2 | O21: 0 | P21: Max | Q21: 0 | R21: 20 | S21: FALSE | V21: 55 | W21: 616077.jpg | X21: 2.7 | Y21: FALSE | Z21: Dowman | AA21: 0.2 | AB21: FALSE | AD21: a | AE21: 1 | AF21: 3 | AG21: 16 | AH21: 0 | AI21: 0 | AJ21: 0 | AK21: 0 | AL21: 0 | AM21: 2.9 | AN21: Dowman | AS21: FALSE | AT21: p616077 | AU21: 152 | AV21: 1 | AW21: 1 | AX21: 1 | AY21: 1 | AZ21: 0 | BA21: 0 | BB21: 0 | BC21: 0 | BD21: 0 | BE21: 0 | BF21: 0 | BG21: 51 | BH21: 45.2 | BI21: 55.5 | BJ21: 65 | BK21: 16.6 | BL21: 0 | BM21: 0 | BN21: 0 | BO21: 0 | BP21: 1 | BQ21: 1.19 | BR21: 0.3 | BS21: 1.49 | BT21: 0.88 | CC21: 338 | CD21: 154 | CE21: 279 | CF21: 153 | CG21: 264 | CH21: 140 | CI21: 318 | CJ21: 152 | CK21: 0.7 | CL21: 0 | CM21: 0.18 | CN21: 0.88 | CO21: 0.52 | CP21: 0.59 | CQ21: 210 | CR21: 131 | CS21: 447 | CT21: 174 | CU21: 212 | CV21: 83 | CW21: 383 | CX21: 143 | CY21: 0.59 | CZ21: 0.59 | DA21: 0
A22: TRUE | B22: TRUE | E22: 128295 | F22: 0 | G22: 0 | H22: 0 | I22: 0 | J22: 0 | K22: 0 | L22: 3 | M22: 1.5 | O22: 0 | P22: Christian | Q22: 0 | R22: 21 | S22: FALSE | V22: 50 | W22: 128295.jpg | X22: 1 | Y22: FALSE | Z22: Nørgaard | AA22: 0.1 | AB22: FALSE | AD22: a | AE22: 1 | AF22: 3 | AG22: 7 | AH22: 0 | AI22: 0 | AJ22: 0 | AK22: 0 | AL22: 0 | AM22: 1.4 | AN22: Nørgaard | AS22: FALSE | AT22: p128295 | AU22: 101 | AV22: 0 | AW22: 0 | AX22: 0 | AY22: 1 | AZ22: 0 | BA22: 0 | BB22: 0 | BC22: 0 | BD22: 0 | BE22: 0 | BF22: 0 | BG22: 28 | BH22: 23.4 | BI22: 5.5 | BJ22: 10 | BK22: 4 | BL22: 0 | BM22: 0 | BN22: 0 | BO22: 0 | BP22: 1 | BQ22: 0.08 | BR22: 0.04 | BS22: 0.12 | BT22: 2.28 | CC22: 354 | CD22: 164 | CE22: 353 | CF22: 174 | CG22: 327 | CH22: 167 | CI22: 363 | CJ22: 169 | CK22: 0.07 | CL22: 0 | CM22: 0.04 | CN22: 0.11 | CO22: 2.03 | CP22: 0.89 | CQ22: 225 | CR22: 136 | CS22: 203 | CT22: 30 | CU22: 377 | CV22: 173 | CW22: 446 | CX22: 174 | CY22: 0.89 | CZ22: 0 | DA22: 0
A23: TRUE | B23: TRUE | E23: 499175 | F23: 0 | G23: 0 | H23: 0 | I23: 0 | J23: 0 | K23: 0 | L23: 3 | M23: 2 | O23: 0 | P23: Ethan | Q23: 0 | R23: 22 | S23: FALSE | V23: 55 | W23: 499175.jpg | X23: 1.3 | Y23: FALSE | Z23: Nwaneri | AA23: 0 | AB23: FALSE | AD23: a | AE23: 1 | AF23: 3 | AG23: 8 | AH23: 0 | AI23: 0 | AJ23: 0 | AK23: 0 | AL23: 0 | AM23: 1.5 | AN23: Nwaneri | AS23: FALSE | AT23: p499175 | AU23: 165 | AV23: 0 | AW23: 0 | AX23: 1 | AY23: 0 | AZ23: 0 | BA23: 0 | BB23: 0 | BC23: 0 | BD23: 0 | BE23: 0 | BF23: 0 | BG23: 20 | BH23: 8.6 | BI23: 22.5 | BJ23: 24 | BK23: 5.4 | BL23: 0 | BM23: 0 | BN23: 0 | BO23: 0 | BP23: 0 | BQ23: 0.23 | BR23: 0.08 | BS23: 0.31 | BT23: 0.73 | CC23: 372 | CD23: 171 | CE23: 321 | CF23: 165 | CG23: 306 | CH23: 158 | CI23: 356 | CJ23: 166 | CK23: 0.13 | CL23: 0 | CM23: 0.04 | CN23: 0.17 | CO23: 0.4 | CP23: 0 | CQ23: 189 | CR23: 117 | CS23: 426 | CT23: 160 | CU23: 347 | CV23: 159 | CW23: 524 | CX23: 221 | CY23: 0 | CZ23: 0.55 | DA23: 0
A24: TRUE | B24: TRUE | E24: 438098 | F24: 0 | G24: 0 | H24: 0 | I24: 0 | J24: 0 | K24: 0 | L24: 3 | M24: 2 | O24: 0 | P24: Fábio | Q24: 0 | R24: 23 | S24: FALSE | V24: 55 | W24: 438098.jpg | X24: 0 | Y24: FALSE | Z24: Ferreira Vieira | AA24: 0 | AB24: FALSE | AD24: a | AE24: 1 | AF24: 3 | AG24: 0 | AH24: 0 | AI24: 0 | AJ24: 0 | AK24: 0 | AL24: 0 | AM24: 0 | AN24: Fábio Vieira | AS24: FALSE | AT24: p438098 | AU24: 0 | AV24: 0 | AW24: 0 | AX24: 0 | AY24: 0 | AZ24: 0 | BA24: 0 | BB24: 0 | BC24: 0 | BD24: 0 | BE24: 0 | BF24: 0 | BG24: 0 | BH24: 0 | BI24: 0 | BJ24: 0 | BK24: 0 | BL24: 0 | BM24: 0 | BN24: 0 | BO24: 0 | BP24: 0 | BQ24: 0 | BR24: 0 | BS24: 0 | BT24: 0 | CC24: 542 | CD24: 234 | CE24: 542 | CF24: 234 | CG24: 541 | CH24: 234 | CI24: 542 | CJ24: 234 | CK24: 0 | CL24: 0 | CM24: 0 | CN24: 0 | CO24: 0 | CP24: 0 | CQ24: 158 | CR24: 99 | CS24: 395 | CT24: 142 | CU24: 542 | CV24: 234 | CW24: 540 | CX24: 234 | CY24: 0 | CZ24: 0 | DA24: 0
A25: TRUE | B25: TRUE | E25: 200641 | F25: 0 | G25: 0 | H25: 0 | I25: 0 | J25: 0 | K25: 0 | L25: 3 | M25: 2 | O25: 0 | P25: Reiss | Q25: 0 | R25: 24 | S25: FALSE | V25: 55 | W25: 200641.jpg | X25: 1.3 | Y25: FALSE | Z25: Nelson | AA25: 0 | AB25: FALSE | AD25: a | AE25: 1 | AF25: 3 | AG25: 13 | AH25: 0 | AI25: 0 | AJ25: 0 | AK25: 0 | AL25: 0 | AM25: 2.4 | AN25: Nelson | AS25: FALSE | AT25: p200641 | AU25: 118 | AV25: 0 | AW25: 1 | AX25: 0 | AY25: 2 | AZ25: 0 | BA25: 0 | BB25: 0 | BC25: 0 | BD25: 0 | BE25: 0 | BF25: 0 | BG25: 39 | BH25: 42.6 | BI25: 32.6 | BJ25: 29 | BK25: 10 | BL25: 0 | BM25: 0 | BN25: 0 | BO25: 0 | BP25: 0 | BQ25: 0.71 | BR25: 0.11 | BS25: 0.82 | BT25: 3.02 | CC25: 340 | CD25: 156 | CE25: 306 | CF25: 161 | CG25: 301 | CH25: 156 | CI25: 337 | CJ25: 157 | CK25: 0.54 | CL25: 0 | CM25: 0.08 | CN25: 0.62 | CO25: 2.3 | CP25: 1.53 | CQ25: 129 | CR25: 81 | CS25: 366 | CT25: 124 | CU25: 345 | CV25: 157 | CW25: 539 | CX25: 233 | CY25: 0 | CZ25: 0 | DA25: 0
A26: TRUE | B26: TRUE | E26: 224117 | F26: 0 | G26: 0 | H26: 0 | I26: 0 | J26: 0 | K26: 0 | L26: 4 | M26: 2.3 | O26: 0 | P26: Viktor | Q26: 0 | R26: 25 | S26: FALSE | V26: 75 | W26: 224117.jpg | X26: 3.6 | Y26: FALSE | Z26: Gyökeres | AA26: 15.7 | AB26: FALSE | AD26: a | AE26: 1 | AF26: 3 | AG26: 128 | AH26: 0 | AI26: 0 | AJ26: 0 | AK26: 0 | AL26: 0 | AM26: 17.1 | AN26: Gyökeres | AS26: FALSE | AT26: p224117 | AU26: 2217 | AV26: 14 | AW26: 1 | AX26: 12 | AY26: 14 | AZ26: 0 | BA26: 0 | BB26: 0 | BC26: 5 | BD26: 0 | BE26: 0 | BF26: 16 | BG26: 474 | BH26: 539.6 | BI26: 271.7 | BJ26: 772 | BK26: 157.5 | BL26: 0 | BM26: 0 | BN26: 0 | BO26: 0 | BP26: 26 | BQ26: 12.26 | BR26: 1.94 | BS26: 14.19 | BT26: 17.81 | BY26: 2 | CC26: 99 | CD26: 9 | CE26: 133 | CF26: 11 | CG26: 19 | CH26: 11 | CI26: 46 | CJ26: 8 | CK26: 0.5 | CL26: 0 | CM26: 0.08 | CN26: 0.58 | CO26: 0.72 | CP26: 0.57 | CQ26: 15 | CR26: 6 | CS26: 539 | CT26: 62 | CU26: 97 | CV26: 10 | CW26: 24 | CX26: 6 | CY26: 1.06 | CZ26: 0.49 | DA26: 0
A27: TRUE | B27: TRUE | E27: 219847 | F27: 0 | G27: 0 | H27: 0 | I27: 0 | J27: 0 | K27: 0 | L27: 4 | M27: 2.3 | O27: 0 | P27: Kai | Q27: 0 | R27: 26 | S27: FALSE | V27: 75 | W27: 219847.jpg | X27: 3 | Y27: FALSE | Z27: Havertz | AA27: 5.2 | AB27: FALSE | AD27: a | AE27: 1 | AF27: 3 | AG27: 36 | AH27: 0 | AI27: 0 | AJ27: 0 | AK27: 0 | AL27: 0 | AM27: 4.8 | AN27: Havertz | AS27: FALSE | AT27: p219847 | AU27: 577 | AV27: 2 | AW27: 3 | AX27: 4 | AY27: 4 | AZ27: 0 | BA27: 0 | BB27: 0 | BC27: 1 | BD27: 0 | BE27: 0 | BF27: 3 | BG27: 143 | BH27: 152.6 | BI27: 134.6 | BJ27: 210 | BK27: 49.9 | BL27: 0 | BM27: 0 | BN27: 0 | BO27: 0 | BP27: 7 | BQ27: 3.31 | BR27: 0.64 | BS27: 3.95 | BT27: 6.68 | CC27: 274 | CD27: 27 | CE27: 211 | CF27: 23 | CG27: 145 | CH27: 32 | CI27: 245 | CJ27: 27 | CK27: 0.52 | CL27: 0 | CM27: 0.1 | CN27: 0.62 | CO27: 1.04 | CP27: 0.62 | CQ27: 14 | CR27: 5 | CS27: 538 | CT27: 61 | CU27: 177 | CV27: 17 | CW27: 76 | CX27: 11 | CY27: 1.09 | CZ27: 0.62 | DA27: 0
A28: TRUE | B28: TRUE | E28: 205651 | F28: 0 | G28: 0 | H28: 0 | I28: 0 | J28: 0 | K28: 0 | L28: 4 | M28: 2 | O28: 0 | P28: Gabriel | Q28: 0 | R28: 27 | S28: FALSE | V28: 60 | W28: 205651.jpg | X28: 1.7 | Y28: FALSE | Z28: Fernando de Jesus | AA28: 0.3 | AB28: FALSE | AD28: a | AE28: 1 | AF28: 3 | AG28: 24 | AH28: 0 | AI28: 0 | AJ28: 0 | AK28: 0 | AL28: 0 | AM28: 4 | AN28: G.Jesus | AS28: FALSE | AT28: p205651 | AU28: 418 | AV28: 3 | AW28: 0 | AX28: 1 | AY28: 6 | AZ28: 0 | BA28: 0 | BB28: 0 | BC28: 3 | BD28: 0 | BE28: 0 | BF28: 0 | BG28: 92 | BH28: 141.8 | BI28: 54.3 | BJ28: 281 | BK28: 47.5 | BL28: 0 | BM28: 0 | BN28: 0 | BO28: 0 | BP28: 3 | BQ28: 2.71 | BR28: 0.26 | BS28: 2.97 | BT28: 3.97 | CC28: 280 | CD28: 30 | CE28: 281 | CF28: 33 | CG28: 107 | CH28: 27 | CI28: 252 | CJ28: 30 | CK28: 0.58 | CL28: 0 | CM28: 0.06 | CN28: 0.64 | CO28: 0.85 | CP28: 1.29 | CQ28: 68 | CR28: 17 | CS28: 462 | CT28: 47 | CU28: 319 | CV28: 35 | CW28: 322 | CX28: 57 | CY28: 0.65 | CZ28: 0.22 | DA28: 0
A29: TRUE | B29: TRUE | E29: 439509 | F29: 0 | G29: 0 | H29: 0 | I29: 0 | J29: 0 | K29: 0 | L29: 3 | M29: 2.3 | O29: 0 | P29: Christos | Q29: 0 | R29: 557 | S29: FALSE | V29: 65 | W29: 439509.jpg | X29: 0 | Y29: FALSE | Z29: Tzolis | AA29: 0.3 | AB29: FALSE | AD29: a | AE29: 1 | AF29: 3 | AG29: 0 | AH29: 0 | AI29: 0 | AJ29: 0 | AK29: 0 | AL29: 0 | AM29: 0 | AN29: Tzolis | AP29: 83 | AQ29: 46226 | AR29: 37286 | AS29: FALSE | AT29: p439509 | AU29: 0 | AV29: 0 | AW29: 0 | AX29: 0 | AY29: 0 | AZ29: 0 | BA29: 0 | BB29: 0 | BC29: 0 | BD29: 0 | BE29: 0 | BF29: 0 | BG29: 0 | BH29: 0 | BI29: 0 | BJ29: 0 | BK29: 0 | BL29: 0 | BM29: 0 | BN29: 0 | BO29: 0 | BP29: 0 | BQ29: 0 | BR29: 0 | BS29: 0 | BT29: 0 | CC29: 554 | CD29: 243 | CE29: 554 | CF29: 243 | CG29: 554 | CH29: 243 | CI29: 554 | CJ29: 243 | CK29: 0 | CL29: 0 | CM29: 0 | CN29: 0 | CO29: 0 | CP29: 0 | CQ29: 44 | CR29: 31 | CS29: 517 | CT29: 219 | CU29: 554 | CV29: 243 | CW29: 324 | CX29: 116 | CY29: 0 | CZ29: 0 | DA29: 0
A30: TRUE | B30: TRUE | E30: 98980 | F30: 0 | G30: 0 | H30: 0 | I30: 0 | J30: 0 | K30: 0 | L30: 1 | M30: 2.6 | O30: 0 | P30: Emiliano | Q30: 0 | R30: 28 | S30: FALSE | V30: 50 | W30: 98980.jpg | X30: 3.8 | Y30: FALSE | Z30: Martínez Romero | AA30: 3.9 | AB30: FALSE | AD30: a | AE30: 2 | AF30: 7 | AG30: 120 | AH30: 0 | AI30: 0 | AJ30: 0 | AK30: 0 | AL30: 0 | AM30: 24 | AN30: Martinez | AS30: FALSE | AT30: p98980 | AU30: 2835 | AV30: 0 | AW30: 1 | AX30: 7 | AY30: 39 | AZ30: 0 | BA30: 1 | BB30: 0 | BC30: 2 | BD30: 0 | BE30: 95 | BF30: 11 | BG30: 530 | BH30: 769.8 | BI30: 23.2 | BJ30: 0 | BK30: 79.2 | BL30: 0 | BM30: 0 | BN30: 0 | BO30: 0 | BP30: 32 | BQ30: 0 | BR30: 0.08 | BS30: 0.08 | BT30: 42.92 | CC30: 34 | CD30: 10 | CE30: 319 | CF30: 4 | CG30: 479 | CH30: 48 | CI30: 175 | CJ30: 10 | CK30: 0 | CL30: 3.02 | CM30: 0 | CN30: 0 | CO30: 1.36 | CP30: 1.24 | CQ30: 220 | CR30: 7 | CS30: 198 | CT30: 45 | CU30: 69 | CV30: 7 | CW30: 88 | CX30: 14 | CY30: 1.02 | CZ30: 0.22 | DA30: 0
A31: TRUE | B31: TRUE | E31: 72147 | F31: 0 | G31: 0 | H31: 0 | I31: 0 | J31: 0 | K31: 0 | L31: 1 | M31: 2 | O31: 0 | P31: Marco | Q31: 0 | R31: 29 | S31: FALSE | V31: 45 | W31: 72147.jpg | X31: 2.3 | Y31: FALSE | Z31: Bizot | AA31: 0.1 | AB31: FALSE | AD31: a | AE31: 2 | AF31: 7 | AG31: 16 | AH31: 0 | AI31: 0 | AJ31: 0 | AK31: 0 | AL31: 0 | AM31: 3.6 | AN31: M.Bizot | AS31: FALSE | AT31: p72147 | AU31: 585 | AV31: 0 | AW31: 0 | AX31: 1 | AY31: 10 | AZ31: 0 | BA31: 0 | BB31: 0 | BC31: 2 | BD31: 0 | BE31: 19 | BF31: 0 | BG31: 75 | BH31: 139.2 | BI31: 0 | BJ31: 0 | BK31: 13.9 | BL31: 0 | BM31: 0 | BN31: 0 | BO31: 0 | BP31: 6 | BQ31: 0 | BR31: 0 | BS31: 0 | BT31: 11.02 | CC31: 283 | CD31: 21 | CE31: 436 | CF31: 35 | CG31: 419 | CH31: 26 | CI31: 323 | CJ31: 21 | CK31: 0 | CL31: 2.92 | CM31: 0 | CN31: 0 | CO31: 1.7 | CP31: 1.54 | CQ31: 371 | CR31: 20 | CS31: 70 | CT31: 22 | CU31: 253 | CV31: 25 | CW31: 411 | CX31: 48 | CY31: 0.92 | CZ31: 0.15 | DA31: 0
A32: TRUE | B32: TRUE | E32: 101188 | F32: 0 | G32: 0 | H32: 0 | I32: 0 | J32: 0 | K32: 0 | L32: 2 | M32: 1.7 | O32: 0 | P32: Lucas | Q32: 0 | R32: 30 | S32: FALSE | V32: 45 | W32: 101188.jpg | X32: 3.1 | Y32: FALSE | Z32: Digne | AA32: 1.4 | AB32: FALSE | AD32: a | AE32: 2 | AF32: 7 | AG32: 97 | AH32: 0 | AI32: 0 | AJ32: 0 | AK32: 0 | AL32: 0 | AM32: 21.6 | AN32: Digne | AS32: FALSE | AT32: p101188 | AU32: 1842 | AV32: 0 | AW32: 7 | AX32: 7 | AY32: 23 | AZ32: 0 | BA32: 0 | BB32: 0 | BC32: 3 | BD32: 0 | BE32: 0 | BF32: 5 | BG32: 381 | BH32: 400.2 | BI32: 455.5 | BJ32: 130 | BK32: 98.5 | BL32: 0 | BM32: 0 | BN32: 0 | BO32: 0 | BP32: 21 | BQ32: 0.67 | BR32: 3.28 | BS32: 3.95 | BT32: 27.79 | BU32: 4 | CC32: 153 | CD32: 63 | CE32: 60 | CF32: 11 | CG32: 206 | CH32: 56 | CI32: 134 | CJ32: 43 | CK32: 0.03 | CL32: 0 | CM32: 0.16 | CN32: 0.19 | CO32: 1.36 | CP32: 1.12 | CQ32: 376 | CR32: 77 | CS32: 75 | CT32: 51 | CU32: 154 | CV32: 61 | CW32: 168 | CX32: 63 | CY32: 1.03 | CZ32: 0.34 | DA32: 0
A33: TRUE | B33: TRUE | E33: 199798 | F33: 0 | G33: 0 | H33: 0 | I33: 0 | J33: 0 | K33: 0 | L33: 2 | M33: 1.7 | O33: 0 | P33: Ezri | Q33: 0 | R33: 31 | S33: FALSE | V33: 45 | W33: 199798.jpg | X33: 2.9 | Y33: FALSE | Z33: Konsa Ngoyo | AA33: 17.3 | AB33: FALSE | AD33: a | AE33: 2 | AF33: 7 | AG33: 100 | AH33: 0 | AI33: 0 | AJ33: 0 | AK33: 0 | AL33: 0 | AM33: 22.2 | AN33: Konsa | AS33: FALSE | AT33: p199798 | AU33: 3035 | AV33: 0 | AW33: 1 | AX33: 9 | AY33: 44 | AZ33: 0 | BA33: 0 | BB33: 0 | BC33: 0 | BD33: 1 | BE33: 0 | BF33: 3 | BG33: 497 | BH33: 601.4 | BI33: 108.3 | BJ33: 124 | BK33: 84 | BL33: 0 | BM33: 0 | BN33: 0 | BO33: 0 | BP33: 34 | BQ33: 1.27 | BR33: 0.59 | BS33: 1.86 | BT33: 48.93 | CC33: 76 | CD33: 31 | CE33: 233 | CF33: 72 | CG33: 210 | CH33: 58 | CI33: 165 | CJ33: 58 | CK33: 0.04 | CL33: 0 | CM33: 0.02 | CN33: 0.06 | CO33: 1.45 | CP33: 1.3 | CQ33: 401 | CR33: 91 | CS33: 100 | CT33: 65 | CU33: 180 | CV33: 74 | CW33: 19 | CX33: 6 | CY33: 1.01 | CZ33: 0.27 | DA33: 0
A34: TRUE | B34: TRUE | E34: 199796 | F34: 0 | G34: 0 | H34: 0 | I34: 0 | J34: 0 | K34: 0 | L34: 2 | M34: 1.7 | O34: 0 | P34: Matty | Q34: 0 | R34: 32 | S34: FALSE | V34: 45 | W34: 199796.jpg | X34: 3.3 | Y34: FALSE | Z34: Cash | AA34: 8.8 | AB34: FALSE | AD34: a | AE34: 2 | AF34: 7 | AG34: 117 | AH34: 0 | AI34: 0 | AJ34: 0 | AK34: 0 | AL34: 0 | AM34: 26 | AN34: Cash | AS34: FALSE | AT34: p199796 | AU34: 3016 | AV34: 3 | AW34: 3 | AX34: 8 | AY34: 38 | AZ34: 0 | BA34: 0 | BB34: 0 | BC34: 9 | BD34: 0 | BE34: 0 | BF34: 7 | BG34: 450 | BH34: 643 | BI34: 510.7 | BJ34: 221 | BK34: 137.5 | BL34: 0 | BM34: 0 | BN34: 0 | BO34: 0 | BP34: 34 | BQ34: 1.14 | BR34: 2.94 | BS34: 4.08 | BT34: 45.45 | BU34: 5 | CC34: 65 | CD34: 29 | CE34: 49 | CF34: 6 | CG34: 136 | CH34: 28 | CI34: 67 | CJ34: 13 | CK34: 0.03 | CL34: 0 | CM34: 0.09 | CN34: 0.12 | CO34: 1.36 | CP34: 1.13 | CQ34: 400 | CR34: 90 | CS34: 99 | CT34: 64 | CU34: 125 | CV34: 48 | CW34: 53 | CX34: 19 | CY34: 1.01 | CZ34: 0.24 | DA34: 0
A35: TRUE | B35: TRUE | E35: 149484 | F35: 0 | G35: 0 | H35: 0 | I35: 0 | J35: 0 | K35: 0 | L35: 2 | M35: 1.7 | O35: 0 | P35: Tyrone | Q35: 0 | R35: 33 | S35: FALSE | V35: 45 | W35: 149484.jpg | X35: 2.9 | Y35: FALSE | Z35: Mings | AA35: 0.2 | AB35: FALSE | AD35: a | AE35: 2 | AF35: 7 | AG35: 50 | AH35: 0 | AI35: 0 | AJ35: 0 | AK35: 0 | AL35: 0 | AM35: 11.1 | AN35: Mings | AS35: FALSE | AT35: p149484 | AU35: 1322 | AV35: 0 | AW35: 1 | AX35: 3 | AY35: 23 | AZ35: 0 | BA35: 0 | BB35: 0 | BC35: 1 | BD35: 0 | BE35: 0 | BF35: 4 | BG35: 169 | BH35: 282.6 | BI35: 80.5 | BJ35: 105 | BK35: 46.8 | BL35: 0 | BM35: 0 | BN35: 0 | BO35: 0 | BP35: 15 | BQ35: 1.3 | BR35: 0.42 | BS35: 1.72 | BT35: 23.37 | CC35: 212 | CD35: 81 | CE35: 256 | CF35: 85 | CG35: 226 | CH35: 68 | CI35: 255 | CJ35: 81 | CK35: 0.09 | CL35: 0 | CM35: 0.03 | CN35: 0.12 | CO35: 1.59 | CP35: 1.57 | CQ35: 388 | CR35: 81 | CS35: 87 | CT35: 55 | CU35: 178 | CV35: 73 | CW35: 369 | CX35: 131 | CY35: 1.02 | CZ35: 0.2 | DA35: 0
A36: TRUE | B36: TRUE | E36: 244954 | F36: 0 | G36: 0 | H36: 0 | I36: 0 | J36: 0 | K36: 0 | L36: 2 | M36: 1.7 | O36: 0 | P36: Pau | Q36: 0 | R36: 34 | S36: FALSE | V36: 45 | W36: 244954.jpg | X36: 3 | Y36: FALSE | Z36: Torres | AA36: 0.3 | AB36: FALSE | AD36: a | AE36: 2 | AF36: 7 | AG36: 64 | AH36: 0 | AI36: 0 | AJ36: 0 | AK36: 0 | AL36: 0 | AM36: 14.2 | AN36: Pau | AS36: FALSE | AT36: p244954 | AU36: 1673 | AV36: 0 | AW36: 2 | AX36: 5 | AY36: 19 | AZ36: 1 | BA36: 0 | BB36: 0 | BC36: 1 | BD36: 0 | BE36: 0 | BF36: 2 | BG36: 280 | BH36: 321.8 | BI36: 47.1 | BJ36: 79 | BK36: 45.1 | BL36: 0 | BM36: 0 | BN36: 0 | BO36: 0 | BP36: 18 | BQ36: 1.33 | BR36: 0.39 | BS36: 1.72 | BT36: 22.81 | CC36: 193 | CD36: 74 | CE36: 290 | CF36: 99 | CG36: 251 | CH36: 79 | CI36: 260 | CJ36: 85 | CK36: 0.07 | CL36: 0 | CM36: 0.02 | CN36: 0.09 | CO36: 1.23 | CP36: 1.02 | CQ36: 425 | CR36: 110 | CS36: 124 | CT36: 84 | CU36: 167 | CV36: 70 | CW36: 330 | CX36: 115 | CY36: 0.97 | CZ36: 0.27 | DA36: 0
A37: TRUE | B37: TRUE | E37: 515597 | F37: 0 | G37: 0 | H37: 0 | I37: 0 | J37: 0 | K37: 0 | L37: 3 | M37: 1.5 | O37: 0 | P37: Lamare | Q37: 0 | R37: 35 | S37: FALSE | V37: 50 | W37: 515597.jpg | X37: 1.4 | Y37: FALSE | Z37: Bogarde | AA37: 0.1 | AB37: FALSE | AD37: a | AE37: 2 | AF37: 7 | AG37: 40 | AH37: 0 | AI37: 0 | AJ37: 0 | AK37: 0 | AL37: 0 | AM37: 8 | AN37: Bogarde | AS37: FALSE | AT37: p515597 | AU37: 1042 | AV37: 0 | AW37: 0 | AX37: 2 | AY37: 17 | AZ37: 0 | BA37: 0 | BB37: 0 | BC37: 5 | BD37: 0 | BE37: 0 | BF37: 4 | BG37: 121 | BH37: 133 | BI37: 59.4 | BJ37: 14 | BK37: 20.6 | BL37: 0 | BM37: 0 | BN37: 0 | BO37: 0 | BP37: 11 | BQ37: 0 | BR37: 0.2 | BS37: 0.2 | BT37: 15.38 | CC37: 288 | CD37: 133 | CE37: 277 | CF37: 152 | CG37: 322 | CH37: 164 | CI37: 309 | CJ37: 147 | CK37: 0 | CL37: 0 | CM37: 0.02 | CN37: 0.02 | CO37: 1.33 | CP37: 1.47 | CQ37: 335 | CR37: 196 | CS37: 313 | CT37: 90 | CU37: 339 | CV37: 153 | CW37: 444 | CX37: 172 | CY37: 0.95 | CZ37: 0.17 | DA37: 0
A38: TRUE | B38: TRUE | E38: 441302 | F38: 0 | G38: 0 | H38: 0 | I38: 0 | J38: 0 | K38: 0 | L38: 2 | M38: 1.7 | O38: 0 | P38: Ian | Q38: 0 | R38: 36 | S38: FALSE | V38: 45 | W38: 441302.jpg | X38: 1.8 | Y38: FALSE | Z38: Maatsen | AA38: 0.7 | AB38: FALSE | AD38: a | AE38: 2 | AF38: 7 | AG38: 54 | AH38: 0 | AI38: 0 | AJ38: 0 | AK38: 0 | AL38: 0 | AM38: 12 | AN38: Maatsen | AS38: FALSE | AT38: p441302 | AU38: 1590 | AV38: 0 | AW38: 1 | AX38: 2 | AY38: 27 | AZ38: 0 | BA38: 0 | BB38: 0 | BC38: 2 | BD38: 0 | BE38: 0 | BF38: 1 | BG38: 242 | BH38: 336.6 | BI38: 373.4 | BJ38: 231 | BK38: 94.3 | BL38: 0 | BM38: 0 | BN38: 0 | BO38: 0 | BP38: 17 | BQ38: 1.26 | BR38: 2.39 | BS38: 3.65 | BT38: 26.64 | CC38: 180 | CD38: 71 | CE38: 90 | CF38: 21 | CG38: 130 | CH38: 25 | CI38: 142 | CJ38: 47 | CK38: 0.07 | CL38: 0 | CM38: 0.14 | CN38: 0.21 | CO38: 1.51 | CP38: 1.53 | CQ38: 430 | CR38: 115 | CS38: 129 | CT38: 89 | CU38: 299 | CV38: 111 | CW38: 239 | CX38: 86 | CY38: 0.96 | CZ38: 0.11 | DA38: 0
A39: TRUE | B39: TRUE | E39: 184667 | F39: 0 | G39: 0 | H39: 0 | I39: 0 | J39: 0 | K39: 0 | L39: 2 | M39: 1.7 | O39: 0 | P39: Victor | Q39: 0 | R39: 37 | S39: FALSE | V39: 45 | W39: 184667.jpg | X39: 1.7 | Y39: FALSE | Z39: Lindelöf | AA39: 0.2 | AB39: FALSE | AD39: a | AE39: 2 | AF39: 7 | AG39: 29 | AH39: 0 | AI39: 0 | AJ39: 0 | AK39: 0 | AL39: 0 | AM39: 6.4 | AN39: Lindelöf | AS39: FALSE | AT39: p184667 | AU39: 942 | AV39: 0 | AW39: 1 | AX39: 1 | AY39: 15 | AZ39: 0 | BA39: 0 | BB39: 0 | BC39: 0 | BD39: 0 | BE39: 0 | BF39: 0 | BG39: 124 | BH39: 167.8 | BI39: 36.6 | BJ39: 22 | BK39: 22.7 | BL39: 0 | BM39: 0 | BN39: 0 | BO39: 0 | BP39: 11 | BQ39: 0.28 | BR39: 0.1 | BS39: 0.38 | BT39: 15.93 | CC39: 262 | CD39: 99 | CE39: 302 | CF39: 103 | CG39: 307 | CH39: 106 | CI39: 307 | CJ39: 106 | CK39: 0.03 | CL39: 0 | CM39: 0.01 | CN39: 0.04 | CO39: 1.52 | CP39: 1.43 | CQ39: 397 | CR39: 87 | CS39: 96 | CT39: 61 | CU39: 311 | CV39: 114 | CW39: 380 | CX39: 134 | CY39: 1.05 | CZ39: 0.1 | DA39: 0
A40: TRUE | B40: TRUE | E40: 606798 | F40: 0 | G40: 0 | H40: 0 | I40: 0 | J40: 0 | K40: 0 | L40: 2 | M40: 1 | O40: 0 | P40: Andrés | Q40: 0 | R40: 38 | S40: FALSE | V40: 40 | W40: 606798.jpg | X40: 0.8 | Y40: FALSE | Z40: García | AA40: 1.5 | AB40: FALSE | AD40: a | AE40: 2 | AF40: 7 | AG40: 5 | AH40: 0 | AI40: 0 | AJ40: 0 | AK40: 0 | AL40: 0 | AM40: 1.2 | AN40: A.García | AS40: FALSE | AT40: p606798 | AU40: 83 | AV40: 0 | AW40: 0 | AX40: 0 | AY40: 3 | AZ40: 0 | BA40: 0 | BB40: 0 | BC40: 0 | BD40: 0 | BE40: 0 | BF40: 0 | BG40: 12 | BH40: 17.8 | BI40: 3.2 | BJ40: 2 | BK40: 2.3 | BL40: 0 | BM40: 0 | BN40: 0 | BO40: 0 | BP40: 1 | BQ40: 0 | BR40: 0.01 | BS40: 0.01 | BT40: 2.74 | CC40: 360 | CD40: 125 | CE40: 359 | CF40: 126 | CG40: 348 | CH40: 126 | CI40: 369 | CJ40: 128 | CK40: 0 | CL40: 0 | CM40: 0.01 | CN40: 0.01 | CO40: 2.97 | CP40: 3.25 | CQ40: 554 | CR40: 180 | CS40: 63 | CT40: 43 | CU40: 395 | CV40: 132 | CW40: 161 | CX40: 61 | CY40: 1.08 | CZ40: 0 | DA40: 0
A41: TRUE | B41: TRUE | E41: 578545 | F41: 0 | G41: 0 | H41: 0 | I41: 0 | J41: 0 | K41: 0 | L41: 2 | M41: 1 | O41: 0 | P41: Kosta | Q41: 0 | R41: 39 | S41: FALSE | V41: 40 | W41: 578545.jpg | X41: 0 | Y41: FALSE | Z41: Nedeljkovic | AA41: 0.5 | AB41: FALSE | AD41: a | AE41: 2 | AF41: 7 | AG41: 0 | AH41: 0 | AI41: 0 | AJ41: 0 | AK41: 0 | AL41: 0 | AM41: 0 | AN41: Nedeljkovic | AS41: FALSE | AT41: p578545 | AU41: 0 | AV41: 0 | AW41: 0 | AX41: 0 | AY41: 0 | AZ41: 0 | BA41: 0 | BB41: 0 | BC41: 0 | BD41: 0 | BE41: 0 | BF41: 0 | BG41: 0 | BH41: 0 | BI41: 0 | BJ41: 0 | BK41: 0 | BL41: 0 | BM41: 0 | BN41: 0 | BO41: 0 | BP41: 0 | BQ41: 0 | BR41: 0 | BS41: 0 | BT41: 0 | CC41: 445 | CD41: 167 | CE41: 431 | CF41: 167 | CG41: 413 | CH41: 164 | CI41: 447 | CJ41: 167 | CK41: 0 | CL41: 0 | CM41: 0 | CN41: 0 | CO41: 0 | CP41: 0 | CQ41: 552 | CR41: 179 | CS41: 61 | CT41: 42 | CU41: 450 | CV41: 167 | CW41: 269 | CX41: 99 | CY41: 0 | CZ41: 0 | DA41: 0
A42: TRUE | B42: TRUE | E42: 195546 | F42: 0 | G42: 0 | H42: 0 | I42: 0 | J42: 0 | K42: 0 | L42: 3 | M42: 2.1 | O42: 0 | P42: Emiliano | Q42: 0 | R42: 41 | S42: FALSE | V42: 60 | W42: 195546.jpg | X42: 2.8 | Y42: FALSE | Z42: Buendía Stati | AA42: 0.8 | AB42: FALSE | AD42: a | AE42: 2 | AF42: 7 | AG42: 102 | AH42: 0 | AI42: 0 | AJ42: 0 | AK42: 0 | AL42: 0 | AM42: 17 | AN42: Buendía | AS42: FALSE | AT42: p195546 | AU42: 1753 | AV42: 6 | AW42: 2 | AX42: 3 | AY42: 24 | AZ42: 0 | BA42: 0 | BB42: 0 | BC42: 6 | BD42: 0 | BE42: 0 | BF42: 10 | BG42: 382 | BH42: 427 | BI42: 402.1 | BJ42: 398 | BK42: 121.4 | BL42: 0 | BM42: 0 | BN42: 0 | BO42: 0 | BP42: 21 | BQ42: 3.38 | BR42: 2.23 | BS42: 5.61 | BT42: 28.03 | BW42: 1 | BY42: 1 | CC42: 144 | CD42: 55 | CE42: 77 | CF42: 58 | CG42: 67 | CH42: 40 | CI42: 87 | CJ42: 51 | CK42: 0.17 | CL42: 0 | CM42: 0.11 | CN42: 0.28 | CO42: 1.44 | CP42: 1.23 | CQ42: 65 | CR42: 43 | CS42: 459 | CT42: 178 | CU42: 199 | CV42: 75 | CW42: 213 | CX42: 69 | CY42: 1.08 | CZ42: 0.15 | DA42: 0
A43: TRUE | B43: TRUE | E43: 485337 | F43: 0 | G43: 0 | H43: 0 | I43: 0 | J43: 0 | K43: 0 | L43: 3 | M43: 2 | O43: 0 | P43: Evann | Q43: 0 | R43: 42 | S43: FALSE | V43: 55 | W43: 485337.jpg | X43: 2.1 | Y43: FALSE | Z43: Guessand | AA43: 0.1 | AB43: FALSE | AD43: a | AE43: 2 | AF43: 7 | AG43: 44 | AH43: 0 | AI43: 0 | AJ43: 0 | AK43: 0 | AL43: 0 | AM43: 8 | AN43: Guessand | AS43: FALSE | AT43: p485337 | AU43: 909 | AV43: 1 | AW43: 3 | AX43: 2 | AY43: 15 | AZ43: 0 | BA43: 0 | BB43: 0 | BC43: 0 | BD43: 0 | BE43: 0 | BF43: 0 | BG43: 143 | BH43: 159.4 | BI43: 76.6 | BJ43: 187 | BK43: 42 | BL43: 0 | BM43: 0 | BN43: 0 | BO43: 0 | BP43: 9 | BQ43: 1.56 | BR43: 0.85 | BS43: 2.41 | BT43: 14.48 | CC43: 269 | CD43: 124 | CE43: 261 | CF43: 144 | CG43: 164 | CH43: 87 | CI43: 265 | CJ43: 127 | CK43: 0.15 | CL43: 0 | CM43: 0.08 | CN43: 0.23 | CO43: 1.43 | CP43: 1.49 | CQ43: 181 | CR43: 111 | CS43: 418 | CT43: 154 | CU43: 278 | CV43: 119 | CW43: 502 | CX43: 206 | CY43: 0.89 | CZ43: 0.2 | DA43: 0
A44: TRUE | B44: TRUE | E44: 215711 | F44: 0 | G44: 0 | H44: 0 | I44: 0 | J44: 0 | K44: 0 | L44: 3 | M44: 2 | O44: 0 | P44: Leon | Q44: 0 | R44: 44 | S44: FALSE | V44: 55 | W44: 215711.jpg | X44: 1.6 | Y44: FALSE | Z44: Bailey | AA44: 0.1 | AB44: FALSE | AD44: a | AE44: 2 | AF44: 7 | AG44: 21 | AH44: 0 | AI44: 0 | AJ44: 0 | AK44: 0 | AL44: 0 | AM44: 3.8 | AN44: Bailey | AS44: FALSE | AT44: p215711 | AU44: 450 | AV44: 0 | AW44: 2 | AX44: 0 | AY44: 9 | AZ44: 0 | BA44: 0 | BB44: 0 | BC44: 1 | BD44: 0 | BE44: 0 | BF44: 0 | BG44: 69 | BH44: 71.2 | BI44: 160.4 | BJ44: 69 | BK44: 30.1 | BL44: 0 | BM44: 0 | BN44: 0 | BO44: 0 | BP44: 3 | BQ44: 0.5 | BR44: 1.46 | BS44: 1.96 | BT44: 7.03 | CC44: 319 | CD44: 145 | CE44: 192 | CF44: 125 | CG44: 263 | CH44: 139 | CI44: 288 | CJ44: 139 | CK44: 0.1 | CL44: 0 | CM44: 0.29 | CN44: 0.39 | CO44: 1.41 | CP44: 1.8 | CQ44: 138 | CR44: 86 | CS44: 375 | CT44: 129 | CU44: 325 | CV44: 143 | CW44: 412 | CX44: 155 | CY44: 0.6 | CZ44: 0 | DA44: 0
A45: TRUE | B45: TRUE | E45: 122806 | F45: 0 | G45: 0 | H45: 0 | I45: 0 | J45: 0 | K45: 0 | L45: 3 | M45: 2 | O45: 0 | P45: John | Q45: 0 | R45: 45 | S45: FALSE | V45: 55 | W45: 122806.jpg | X45: 3.4 | Y45: FALSE | Z45: McGinn | AA45: 2.7 | AB45: FALSE | AD45: a | AE45: 2 | AF45: 7 | AG45: 103 | AH45: 0 | AI45: 0 | AJ45: 0 | AK45: 0 | AL45: 0 | AM45: 18.7 | AN45: McGinn | AS45: FALSE | AT45: p122806 | AU45: 2136 | AV45: 5 | AW45: 4 | AX45: 8 | AY45: 28 | AZ45: 0 | BA45: 0 | BB45: 0 | BC45: 5 | BD45: 0 | BE45: 0 | BF45: 6 | BG45: 443 | BH45: 459.8 | BI45: 605.3 | BJ45: 309 | BK45: 137.3 | BL45: 0 | BM45: 0 | BN45: 0 | BO45: 0 | BP45: 28 | BQ45: 3 | BR45: 4.11 | BS45: 7.11 | BT45: 33.08 | BU45: 6 | CC45: 127 | CD45: 46 | CE45: 33 | CF45: 32 | CG45: 96 | CH45: 61 | CI45: 68 | CJ45: 43 | CK45: 0.13 | CL45: 0 | CM45: 0.17 | CN45: 0.3 | CO45: 1.39 | CP45: 1.18 | CQ45: 116 | CR45: 76 | CS45: 353 | CT45: 119 | CU45: 114 | CV45: 44 | CW45: 112 | CX45: 37 | CY45: 1.18 | CZ45: 0.34 | DA45: 0
A46: TRUE | B46: TRUE | E46: 88894 | F46: 0 | G46: 0 | H46: 0 | I46: 0 | J46: 0 | K46: 0 | L46: 3 | M46: 1.5 | O46: 0 | P46: Ross | Q46: 0 | R46: 46 | S46: FALSE | V46: 50 | W46: 88894.jpg | X46: 2.7 | Y46: FALSE | Z46: Barkley | AA46: 0.2 | AB46: FALSE | AD46: a | AE46: 2 | AF46: 7 | AG46: 56 | AH46: 0 | AI46: 0 | AJ46: 0 | AK46: 0 | AL46: 0 | AM46: 11.2 | AN46: Barkley | AS46: FALSE | AT46: p88894 | AU46: 844 | AV46: 3 | AW46: 2 | AX46: 1 | AY46: 15 | AZ46: 0 | BA46: 0 | BB46: 0 | BC46: 1 | BD46: 0 | BE46: 0 | BF46: 5 | BG46: 221 | BH46: 227.8 | BI46: 162.3 | BJ46: 191 | BK46: 58.1 | BL46: 0 | BM46: 0 | BN46: 0 | BO46: 0 | BP46: 7 | BQ46: 1.58 | BR46: 1.26 | BS46: 2.84 | BT46: 13.2 | CC46: 234 | CD46: 104 | CE46: 187 | CF46: 123 | CG46: 161 | CH46: 86 | CI46: 226 | CJ46: 115 | CK46: 0.17 | CL46: 0 | CM46: 0.13 | CN46: 0.3 | CO46: 1.41 | CP46: 1.6 | CQ46: 217 | CR46: 134 | CS46: 195 | CT46: 28 | CU46: 204 | CV46: 78 | CW46: 390 | CX46: 145 | CY46: 0.75 | CZ46: 0.11 | DA46: 0
A47: TRUE | B47: TRUE | C47: 75 | E47: 226944 | F47: 0 | G47: 0 | H47: 0 | I47: 0 | J47: 0 | K47: 0 | L47: 3 | M47: 1.1 | O47: 0 | P47: Boubacar | Q47: 0 | R47: 47 | S47: FALSE | T47: Knee injury - 75% chance of playing | U47: 2026-07-23T12:01:23.337269Z | V47: 50 | W47: 226944.jpg | X47: 3.4 | Y47: FALSE | Z47: Kamara | AA47: 0.1 | AB47: FALSE | AD47: d | AE47: 2 | AF47: 7 | AG47: 61 | AH47: 0 | AI47: 0 | AJ47: 0 | AK47: 0 | AL47: 0 | AM47: 12.2 | AN47: Kamara | AS47: FALSE | AT47: p226944 | AU47: 1410 | AV47: 1 | AW47: 3 | AX47: 5 | AY47: 15 | AZ47: 0 | BA47: 0 | BB47: 0 | BC47: 5 | BD47: 0 | BE47: 0 | BF47: 7 | BG47: 282 | BH47: 325 | BI47: 241.3 | BJ47: 75 | BK47: 64.2 | BL47: 0 | BM47: 0 | BN47: 0 | BO47: 0 | BP47: 17 | BQ47: 0.53 | BR47: 0.84 | BS47: 1.36 | BT47: 20.8 | CB47: https://www.avfc.co.uk/news/2026/may/14/prematch-team-news-for-liverpool-clash/?utm_source=premier-league-web&utm_medium=referral&utm_campaign=pl-referral-always-on&utm_term=injuries&utm_content=club-injury-article | CC47: 190 | CD47: 81 | CE47: 141 | CF47: 97 | CG47: 253 | CH47: 135 | CI47: 212 | CJ47: 108 | CK47: 0.03 | CL47: 0 | CM47: 0.05 | CN47: 0.08 | CO47: 1.33 | CP47: 0.96 | CQ47: 267 | CR47: 159 | CS47: 245 | CT47: 53 | CU47: 111 | CV47: 43 | CW47: 478 | CX47: 192 | CY47: 1.09 | CZ47: 0.32 | DA47: 0
A48: TRUE | B48: TRUE | C48: 0 | E48: 449871 | F48: 0 | G48: 0 | H48: 0 | I48: 0 | J48: 0 | K48: 0 | L48: 3 | M48: 0 | O48: 0 | P48: Amadou | Q48: 0 | R48: 48 | S48: FALSE | T48: Knee injury - Unknown return date | U48: 2026-07-23T12:01:23.352497Z | V48: 50 | W48: 449871.jpg | X48: 3 | Y48: FALSE | Z48: Onana | AA48: 0 | AB48: FALSE | AD48: i | AE48: 2 | AF48: 7 | AG48: 76 | AH48: 0 | AI48: 0 | AJ48: 0 | AK48: 0 | AL48: 0 | AM48: 15.2 | AN48: Onana | AS48: FALSE | AT48: p449871 | AU48: 1755 | AV48: 2 | AW48: 0 | AX48: 6 | AY48: 26 | AZ48: 0 | BA48: 0 | BB48: 0 | BC48: 3 | BD48: 0 | BE48: 0 | BF48: 4 | BG48: 353 | BH48: 413.2 | BI48: 152.6 | BJ48: 178 | BK48: 74.4 | BL48: 0 | BM48: 0 | BN48: 0 | BO48: 0 | BP48: 21 | BQ48: 1.68 | BR48: 0.69 | BS48: 2.37 | BT48: 28.53 | CC48: 148 | CD48: 56 | CE48: 203 | CF48: 130 | CG48: 175 | CH48: 94 | CI48: 185 | CJ48: 93 | CK48: 0.09 | CL48: 0 | CM48: 0.04 | CN48: 0.13 | CO48: 1.46 | CP48: 1.33 | CQ48: 292 | CR48: 172 | CS48: 270 | CT48: 66 | CU48: 170 | CV48: 64 | CW48: 537 | CX48: 231 | CY48: 1.08 | CZ48: 0.31 | DA48: 0
A49: TRUE | B49: TRUE | E49: 469247 | F49: 0 | G49: 0 | H49: 0 | I49: 0 | J49: 0 | K49: 0 | L49: 3 | M49: 1.5 | O49: 0 | P49: Samuel | Q49: 0 | R49: 49 | S49: FALSE | V49: 50 | W49: 469247.jpg | X49: 0 | Y49: FALSE | Z49: Iling-Junior | AA49: 0 | AB49: FALSE | AD49: a | AE49: 2 | AF49: 7 | AG49: 0 | AH49: 0 | AI49: 0 | AJ49: 0 | AK49: 0 | AL49: 0 | AM49: 0 | AN49: Iling Jr | AS49: FALSE | AT49: p469247 | AU49: 0 | AV49: 0 | AW49: 0 | AX49: 0 | AY49: 0 | AZ49: 0 | BA49: 0 | BB49: 0 | BC49: 0 | BD49: 0 | BE49: 0 | BF49: 0 | BG49: 0 | BH49: 0 | BI49: 0 | BJ49: 0 | BK49: 0 | BL49: 0 | BM49: 0 | BN49: 0 | BO49: 0 | BP49: 0 | BQ49: 0 | BR49: 0 | BS49: 0 | BT49: 0 | CC49: 515 | CD49: 216 | CE49: 514 | CF49: 216 | CG49: 510 | CH49: 215 | CI49: 515 | CJ49: 216 | CK49: 0 | CL49: 0 | CM49: 0 | CN49: 0 | CO49: 0 | CP49: 0 | CQ49: 303 | CR49: 176 | CS49: 281 | CT49: 70 | CU49: 515 | CV49: 216 | CW49: 523 | CX49: 220 | CY49: 0 | CZ49: 0 | DA49: 0
A50: TRUE | B50: TRUE | E50: 645618 | F50: 0 | G50: 0 | H50: 0 | I50: 0 | J50: 0 | K50: 0 | L50: 3 | M50: 1 | O50: 0 | P50: Bradley | Q50: 0 | R50: 50 | S50: FALSE | V50: 45 | W50: 645618.jpg | X50: 1 | Y50: FALSE | Z50: Burrowes | AA50: 1.2 | AB50: FALSE | AD50: a | AE50: 2 | AF50: 7 | AG50: 1 | AH50: 0 | AI50: 0 | AJ50: 0 | AK50: 0 | AL50: 0 | AM50: 0.2 | AN50: Burrowes | AS50: FALSE | AT50: p645618 | AU50: 16 | AV50: 0 | AW50: 0 | AX50: 0 | AY50: 1 | AZ50: 0 | BA50: 0 | BB50: 0 | BC50: 0 | BD50: 0 | BE50: 0 | BF50: 0 | BG50: 3 | BH50: 0 | BI50: 0.3 | BJ50: 0 | BK50: 0 | BL50: 0 | BM50: 0 | BN50: 0 | BO50: 0 | BP50: 0 | BQ50: 0 | BR50: 0 | BS50: 0 | BT50: 0.9 | CC50: 489 | CD50: 199 | CE50: 375 | CF50: 187 | CG50: 475 | CH50: 197 | CI50: 489 | CJ50: 199 | CK50: 0 | CL50: 0 | CM50: 0 | CN50: 0 | CO50: 5.06 | CP50: 5.62 | CQ50: 489 | CR50: 244 | CS50: 188 | CT50: 23 | CU50: 375 | CV50: 171 | CW50: 180 | CX50: 58 | CY50: 0 | CZ50: 0 | DA50: 0
A51: TRUE | B51: TRUE | E51: 577285 | F51: 0 | G51: 0 | H51: 0 | I51: 0 | J51: 0 | K51: 0 | L51: 3 | M51: 1 | O51: 0 | P51: George | Q51: 0 | R51: 51 | S51: FALSE | V51: 45 | W51: 577285.jpg | X51: 1 | Y51: FALSE | Z51: Hemmings | AA51: 0.2 | AB51: FALSE | AD51: a | AE51: 2 | AF51: 7 | AG51: 2 | AH51: 0 | AI51: 0 | AJ51: 0 | AK51: 0 | AL51: 0 | AM51: 0.4 | AN51: George Hemmings | AS51: FALSE | AT51: p577285 | AU51: 25 | AV51: 0 | AW51: 0 | AX51: 0 | AY51: 0 | AZ51: 0 | BA51: 0 | BB51: 0 | BC51: 0 | BD51: 0 | BE51: 0 | BF51: 0 | BG51: 5 | BH51: 0 | BI51: 1.7 | BJ51: 2 | BK51: 0.3 | BL51: 0 | BM51: 0 | BN51: 0 | BO51: 0 | BP51: 0 | BQ51: 0.04 | BR51: 0.01 | BS51: 0.05 | BT51: 0.61 | CC51: 483 | CD51: 197 | CE51: 369 | CF51: 185 | CG51: 353 | CH51: 179 | CI51: 392 | CJ51: 184 | CK51: 0.14 | CL51: 0 | CM51: 0.04 | CN51: 0.18 | CO51: 2.2 | CP51: 0 | CQ51: 477 | CR51: 240 | CS51: 176 | CT51: 19 | CU51: 371 | CV51: 169 | CW51: 352 | CX51: 131 | CY51: 0 | CZ51: 0 | DA51: 0
A52: TRUE | B52: TRUE | E52: 653481 | F52: 0 | G52: 0 | H52: 0 | I52: 0 | J52: 0 | K52: 0 | L52: 3 | M52: 1.5 | O52: 0 | P52: Alysson Edward Franco | Q52: 0 | R52: 52 | S52: FALSE | V52: 50 | W52: 653481.jpg | X52: 1 | Y52: FALSE | Z52: da Rocha dos Santos | AA52: 0.1 | AB52: FALSE | AD52: a | AE52: 2 | AF52: 7 | AG52: 3 | AH52: 0 | AI52: 0 | AJ52: 0 | AK52: 0 | AL52: 0 | AM52: 0.6 | AN52: Alysson | AS52: FALSE | AT52: p653481 | AU52: 47 | AV52: 0 | AW52: 0 | AX52: 0 | AY52: 2 | AZ52: 0 | BA52: 0 | BB52: 0 | BC52: 0 | BD52: 0 | BE52: 0 | BF52: 0 | BG52: 11 | BH52: 3.2 | BI52: 3.5 | BJ52: 10 | BK52: 1.5 | BL52: 0 | BM52: 0 | BN52: 0 | BO52: 0 | BP52: 0 | BQ52: 0.05 | BR52: 0.05 | BS52: 0.1 | BT52: 1.87 | CC52: 384 | CD52: 179 | CE52: 358 | CF52: 177 | CG52: 329 | CH52: 168 | CI52: 380 | CJ52: 179 | CK52: 0.1 | CL52: 0 | CM52: 0.1 | CN52: 0.2 | CO52: 3.58 | CP52: 3.83 | CQ52: 365 | CR52: 219 | CS52: 343 | CT52: 113 | CU52: 385 | CV52: 181 | CW52: 495 | CX52: 203 | CY52: 0 | CZ52: 0 | DA52: 0
A53: TRUE | B53: TRUE | E53: 614071 | F53: 0 | G53: 0 | H53: 0 | I53: 0 | J53: 0 | K53: 0 | L53: 3 | M53: 2.1 | O53: 0 | P53: Johan | Q53: 0 | R53: 53 | S53: FALSE | V53: 60 | W53: 614071.jpg | X53: 0 | Y53: FALSE | Z53: Manzambi | AA53: 3.9 | AB53: FALSE | AD53: a | AE53: 2 | AF53: 7 | AG53: 0 | AH53: 0 | AI53: 0 | AJ53: 0 | AK53: 0 | AL53: 0 | AM53: 0 | AN53: Manzambi | AS53: FALSE | AT53: p614071 | AU53: 0 | AV53: 0 | AW53: 0 | AX53: 0 | AY53: 0 | AZ53: 0 | BA53: 0 | BB53: 0 | BC53: 0 | BD53: 0 | BE53: 0 | BF53: 0 | BG53: 0 | BH53: 0 | BI53: 0 | BJ53: 0 | BK53: 0 | BL53: 0 | BM53: 0 | BN53: 0 | BO53: 0 | BP53: 0 | BQ53: 0 | BR53: 0 | BS53: 0 | BT53: 0 | CC53: 553 | CD53: 242 | CE53: 553 | CF53: 242 | CG53: 553 | CH53: 242 | CI53: 553 | CJ53: 242 | CK53: 0 | CL53: 0 | CM53: 0 | CN53: 0 | CO53: 0 | CP53: 0 | CQ53: 109 | CR53: 72 | CS53: 503 | CT53: 207 | CU53: 553 | CV53: 242 | CW53: 89 | CX53: 30 | CY53: 0 | CZ53: 0 | DA53: 0
A54: TRUE | B54: TRUE | E54: 448089 | F54: 0 | G54: 0 | H54: 0 | I54: 0 | J54: 0 | K54: 0 | L54: 3 | M54: 2 | O54: 0 | P54: Joao | Q54: 0 | R54: 54 | S54: FALSE | V54: 55 | W54: 448089.jpg | X54: 3 | Y54: FALSE | Z54: Gomes | AA54: 0.3 | AB54: FALSE | AD54: a | AE54: 2 | AF54: 7 | AG54: 85 | AH54: 0 | AI54: 0 | AJ54: 0 | AK54: 0 | AL54: 0 | AM54: 15.5 | AN54: Gomes | AS54: FALSE | AT54: p448089 | AU54: 2207 | AV54: 1 | AW54: 1 | AX54: 4 | AY54: 41 | AZ54: 0 | BA54: 0 | BB54: 0 | BC54: 9 | BD54: 0 | BE54: 0 | BF54: 4 | BG54: 421 | BH54: 486.6 | BI54: 353.4 | BJ54: 176 | BK54: 102 | BL54: 0 | BM54: 0 | BN54: 0 | BO54: 0 | BP54: 25 | BQ54: 1.15 | BR54: 1.34 | BS54: 2.49 | BT54: 48.6 | CC54: 117 | CD54: 41 | CE54: 96 | CF54: 70 | CG54: 177 | CH54: 96 | CI54: 125 | CJ54: 71 | CK54: 0.05 | CL54: 0 | CM54: 0.05 | CN54: 0.1 | CO54: 1.98 | CP54: 1.67 | CQ54: 163 | CR54: 103 | CS54: 400 | CT54: 146 | CU54: 173 | CV54: 66 | CW54: 306 | CX54: 104 | CY54: 1.02 | CZ54: 0.16 | DA54: 0
A55: TRUE | B55: TRUE | E55: 178301 | F55: 0 | G55: 0 | H55: 0 | I55: 0 | J55: 0 | K55: 0 | L55: 4 | M55: 2.5 | O55: 0 | P55: Ollie | Q55: 0 | R55: 55 | S55: FALSE | V55: 80 | W55: 178301.jpg | X55: 4.5 | Y55: FALSE | Z55: Watkins | AA55: 14.1 | AB55: FALSE | AD55: a | AE55: 2 | AF55: 7 | AG55: 167 | AH55: 0 | AI55: 0 | AJ55: 0 | AK55: 0 | AL55: 0 | AM55: 20.9 | AN55: Watkins | AS55: FALSE | AT55: p178301 | AU55: 2833 | AV55: 16 | AW55: 4 | AX55: 9 | AY55: 38 | AZ55: 0 | BA55: 0 | BB55: 0 | BC55: 4 | BD55: 0 | BE55: 0 | BF55: 26 | BG55: 623 | BH55: 720.2 | BI55: 330.9 | BJ55: 1206 | BK55: 225.2 | BL55: 0 | BM55: 0 | BN55: 0 | BO55: 0 | BP55: 33 | BQ55: 15.4 | BR55: 1.18 | BS55: 16.58 | BT55: 43.39 | BY55: 2 | CC55: 42 | CD55: 4 | CE55: 107 | CF55: 5 | CG55: 2 | CH55: 2 | CI55: 11 | CJ55: 3 | CK55: 0.49 | CL55: 0 | CM55: 0.04 | CN55: 0.53 | CO55: 1.38 | CP55: 1.21 | CQ55: 7 | CR55: 3 | CS55: 547 | CT55: 65 | CU55: 29 | CV55: 5 | CW55: 29 | CX55: 7 | CY55: 1.05 | CZ55: 0.29 | DA55: 0
A56: TRUE | B56: TRUE | C56: 0 | E56: 173879 | F56: 0 | G56: 0 | H56: 0 | I56: 0 | J56: 0 | K56: 0 | L56: 4 | M56: 0 | O56: 0 | P56: Tammy | Q56: 0 | R56: 56 | S56: FALSE | T56: Shoulder injury - Expected back 23 Aug | U56: 2026-07-23T12:01:23.368701Z | V56: 55 | W56: 173879.jpg | X56: 1.9 | Y56: FALSE | Z56: Abraham | AA56: 0 | AB56: FALSE | AD56: i | AE56: 2 | AF56: 7 | AG56: 23 | AH56: 0 | AI56: 0 | AJ56: 0 | AK56: 0 | AL56: 0 | AM56: 4.2 | AN56: Abraham | AS56: FALSE | AT56: p173879 | AU56: 278 | AV56: 2 | AW56: 0 | AX56: 0 | AY56: 8 | AZ56: 0 | BA56: 0 | BB56: 0 | BC56: 0 | BD56: 0 | BE56: 0 | BF56: 2 | BG56: 93 | BH56: 87.2 | BI56: 49.2 | BJ56: 136 | BK56: 27.1 | BL56: 0 | BM56: 0 | BN56: 0 | BO56: 0 | BP56: 2 | BQ56: 2.05 | BR56: 0.36 | BS56: 2.41 | BT56: 5.12 | CC56: 311 | CD56: 34 | CE56: 286 | CF56: 34 | CG56: 200 | CH56: 36 | CI56: 297 | CJ56: 35 | CK56: 0.66 | CL56: 0 | CM56: 0.12 | CN56: 0.78 | CO56: 1.66 | CP56: 2.59 | CQ56: 121 | CR56: 30 | CS56: 358 | CT56: 27 | CU56: 292 | CV56: 29 | CW56: 531 | CX56: 67 | CY56: 0.65 | CZ56: 0 | DA56: 0
A57: TRUE | B57: TRUE | E57: 493105 | F57: 0 | G57: 0 | H57: 0 | I57: 0 | J57: 0 | K57: 0 | L57: 3 | M57: 2.1 | O57: 0 | P57: Alejandro | Q57: 0 | R57: 160 | S57: FALSE | V57: 60 | W57: 493105.jpg | X57: 2.3 | Y57: FALSE | Z57: Garnacho Ferreyra | AA57: 0.9 | AB57: FALSE | AD57: a | AE57: 2 | AF57: 7 | AG57: 56 | AH57: 0 | AI57: 0 | AJ57: 0 | AK57: 0 | AL57: 0 | AM57: 9.3 | AN57: Garnacho | AQ57: 46226 | AS57: FALSE | AT57: p493105 | AU57: 1261 | AV57: 1 | AW57: 4 | AX57: 4 | AY57: 20 | AZ57: 0 | BA57: 0 | BB57: 0 | BC57: 2 | BD57: 0 | BE57: 0 | BF57: 3 | BG57: 222 | BH57: 211.4 | BI57: 405.3 | BJ57: 399 | BK57: 100.5 | BL57: 0 | BM57: 0 | BN57: 0 | BO57: 0 | BP57: 14 | BQ57: 3.44 | BR57: 3.68 | BS57: 7.12 | BT57: 20.52 | CC57: 243 | CD57: 109 | CE57: 73 | CF57: 55 | CG57: 66 | CH57: 39 | CI57: 127 | CJ57: 73 | CK57: 0.25 | CL57: 0 | CM57: 0.26 | CN57: 0.51 | CO57: 1.46 | CP57: 1.43 | CQ57: 95 | CR57: 60 | CS57: 489 | CT57: 195 | CU57: 260 | CV57: 108 | CW57: 204 | CX57: 67 | CY57: 1 | CZ57: 0.29 | DA57: 0
A58: TRUE | B58: TRUE | E58: 457569 | F58: 0 | G58: 0 | H58: 0 | I58: 0 | J58: 0 | K58: 0 | L58: 1 | M58: 2 | O58: 0 | P58: Đorđe | Q58: 0 | R58: 57 | S58: FALSE | V58: 45 | W58: 457569.jpg | X58: 3.3 | Y58: FALSE | Z58: Petrović | AA58: 3.9 | AB58: FALSE | AD58: a | AE58: 3 | AF58: 91 | AG58: 124 | AH58: 0 | AI58: 0 | AJ58: 0 | AK58: 0 | AL58: 0 | AM58: 27.6 | AN58: Petrović | AS58: FALSE | AT58: p457569 | AU58: 3420 | AV58: 0 | AW58: 0 | AX58: 11 | AY58: 54 | AZ58: 1 | BA58: 0 | BB58: 0 | BC58: 3 | BD58: 0 | BE58: 109 | BF58: 5 | BG58: 512 | BH58: 822.6 | BI58: 0 | BJ58: 0 | BK58: 82.4 | BL58: 0 | BM58: 0 | BN58: 0 | BO58: 0 | BP58: 38 | BQ58: 0 | BR58: 0 | BS58: 0 | BT58: 56.72 | CC58: 26 | CD58: 7 | CE58: 456 | CF58: 46 | CG58: 442 | CH58: 39 | CI58: 167 | CJ58: 8 | CK58: 0 | CL58: 2.87 | CM58: 0 | CN58: 0 | CO58: 1.49 | CP58: 1.42 | CQ58: 433 | CR58: 33 | CS58: 132 | CT58: 35 | CU58: 126 | CV58: 16 | CW58: 90 | CX58: 15 | CY58: 1 | CZ58: 0.29 | DA58: 0
A59: TRUE | B59: TRUE | E59: 40383 | F59: 0 | G59: 0 | H59: 0 | I59: 0 | J59: 0 | K59: 0 | L59: 1 | M59: 1 | O59: 0 | P59: Fraser | Q59: 0 | R59: 58 | S59: FALSE | V59: 40 | W59: 40383.jpg | X59: 0 | Y59: FALSE | Z59: Forster | AA59: 3.4 | AB59: FALSE | AD59: a | AE59: 3 | AF59: 91 | AG59: 0 | AH59: 0 | AI59: 0 | AJ59: 0 | AK59: 0 | AL59: 0 | AM59: 0 | AN59: Forster | AS59: FALSE | AT59: p40383 | AU59: 0 | AV59: 0 | AW59: 0 | AX59: 0 | AY59: 0 | AZ59: 0 | BA59: 0 | BB59: 0 | BC59: 0 | BD59: 0 | BE59: 0 | BF59: 0 | BG59: 0 | BH59: 0 | BI59: 0 | BJ59: 0 | BK59: 0 | BL59: 0 | BM59: 0 | BN59: 0 | BO59: 0 | BP59: 0 | BQ59: 0 | BR59: 0 | BS59: 0 | BT59: 0 | CC59: 396 | CD59: 33 | CE59: 379 | CF59: 15 | CG59: 360 | CH59: 6 | CI59: 398 | CJ59: 33 | CK59: 0 | CL59: 0 | CM59: 0 | CN59: 0 | CO59: 0 | CP59: 0 | CQ59: 493 | CR59: 42 | CS59: 2 | CT59: 2 | CU59: 402 | CV59: 33 | CW59: 97 | CX59: 16 | CY59: 0 | CZ59: 0 | DA59: 0
A60: TRUE | B60: TRUE | E60: 444172 | F60: 0 | G60: 0 | H60: 0 | I60: 0 | J60: 0 | K60: 0 | L60: 1 | M60: 1 | O60: 0 | P60: Will | Q60: 0 | R60: 59 | S60: FALSE | V60: 40 | W60: 444172.jpg | X60: 0 | Y60: FALSE | Z60: Dennis | AA60: 0.2 | AB60: FALSE | AD60: a | AE60: 3 | AF60: 91 | AG60: 0 | AH60: 0 | AI60: 0 | AJ60: 0 | AK60: 0 | AL60: 0 | AM60: 0 | AN60: Dennis | AS60: FALSE | AT60: p444172 | AU60: 0 | AV60: 0 | AW60: 0 | AX60: 0 | AY60: 0 | AZ60: 0 | BA60: 0 | BB60: 0 | BC60: 0 | BD60: 0 | BE60: 0 | BF60: 0 | BG60: 0 | BH60: 0 | BI60: 0 | BJ60: 0 | BK60: 0 | BL60: 0 | BM60: 0 | BN60: 0 | BO60: 0 | BP60: 0 | BQ60: 0 | BR60: 0 | BS60: 0 | BT60: 0 | CC60: 423 | CD60: 43 | CE60: 408 | CF60: 27 | CG60: 389 | CH60: 18 | CI60: 425 | CJ60: 43 | CK60: 0 | CL60: 0 | CM60: 0 | CN60: 0 | CO60: 0 | CP60: 0 | CQ60: 526 | CR60: 54 | CS60: 35 | CT60: 14 | CU60: 429 | CV60: 43 | CW60: 343 | CX60: 40 | CY60: 0 | CZ60: 0 | DA60: 0
A61: TRUE | B61: TRUE | E61: 463981 | F61: 0 | G61: 0 | H61: 0 | I61: 0 | J61: 0 | K61: 0 | L61: 2 | M61: 2.5 | O61: 0 | P61: James | Q61: 0 | R61: 60 | S61: FALSE | V61: 55 | W61: 463981.jpg | X61: 3.8 | Y61: FALSE | Z61: Hill | AA61: 1.7 | AB61: FALSE | AD61: a | AE61: 3 | AF61: 91 | AG61: 110 | AH61: 0 | AI61: 0 | AJ61: 0 | AK61: 0 | AL61: 0 | AM61: 20 | AN61: Hill | AS61: FALSE | AT61: p463981 | AU61: 2102 | AV61: 0 | AW61: 3 | AX61: 8 | AY61: 24 | AZ61: 2 | BA61: 0 | BB61: 0 | BC61: 5 | BD61: 0 | BE61: 0 | BF61: 4 | BG61: 386 | BH61: 579.4 | BI61: 161.7 | BJ61: 119 | BK61: 86.3 | BL61: 0 | BM61: 0 | BN61: 0 | BO61: 0 | BP61: 22 | BQ61: 0.89 | BR61: 1.16 | BS61: 2.04 | BT61: 33.42 | CC61: 83 | CD61: 35 | CE61: 189 | CF61: 48 | CG61: 218 | CH61: 63 | CI61: 157 | CJ61: 53 | CK61: 0.04 | CL61: 0 | CM61: 0.05 | CN61: 0.09 | CO61: 1.43 | CP61: 1.03 | CQ61: 170 | CR61: 23 | CS61: 407 | CT61: 165 | CU61: 73 | CV61: 28 | CW61: 149 | CX61: 58 | CY61: 0.94 | CZ61: 0.34 | DA61: 0
A62: TRUE | B62: TRUE | E62: 494521 | F62: 0 | G62: 0 | H62: 0 | I62: 0 | J62: 0 | K62: 0 | L62: 2 | M62: 2.5 | O62: 0 | P62: Adrien | Q62: 0 | R62: 61 | S62: FALSE | V62: 55 | W62: 494521.jpg | X62: 4.3 | Y62: FALSE | Z62: Truffert | AA62: 5.2 | AB62: FALSE | AD62: a | AE62: 3 | AF62: 91 | AG62: 165 | AH62: 0 | AI62: 0 | AJ62: 0 | AK62: 0 | AL62: 0 | AM62: 30 | AN62: Truffert | AS62: FALSE | AT62: p494521 | AU62: 3378 | AV62: 1 | AW62: 6 | AX62: 11 | AY62: 51 | AZ62: 0 | BA62: 0 | BB62: 0 | BC62: 5 | BD62: 0 | BE62: 0 | BF62: 19 | BG62: 607 | BH62: 857 | BI62: 574.2 | BJ62: 194 | BK62: 162.6 | BL62: 0 | BM62: 0 | BN62: 0 | BO62: 0 | BP62: 38 | BQ62: 1.35 | BR62: 3.07 | BS62: 4.42 | BT62: 54.42 | CC62: 19 | CD62: 7 | CE62: 37 | CF62: 2 | CG62: 160 | CH62: 43 | CI62: 43 | CJ62: 7 | CK62: 0.04 | CL62: 0 | CM62: 0.08 | CN62: 0.12 | CO62: 1.45 | CP62: 1.36 | CQ62: 185 | CR62: 27 | CS62: 422 | CT62: 169 | CU62: 39 | CV62: 15 | CW62: 74 | CX62: 30 | CY62: 1.01 | CZ62: 0.29 | DA62: 0
A63: TRUE | B63: TRUE | E63: 242882 | F63: 0 | G63: 0 | H63: 0 | I63: 0 | J63: 0 | K63: 0 | L63: 2 | M63: 2.2 | O63: 0 | P63: Bafodé | Q63: 0 | R63: 62 | S63: FALSE | V63: 50 | W63: 242882.jpg | X63: 2.6 | Y63: FALSE | Z63: Diakité | AA63: 0.2 | AB63: FALSE | AD63: a | AE63: 3 | AF63: 91 | AG63: 46 | AH63: 0 | AI63: 0 | AJ63: 0 | AK63: 0 | AL63: 0 | AM63: 9.2 | AN63: Diakité | AS63: FALSE | AT63: p242882 | AU63: 1275 | AV63: 0 | AW63: 0 | AX63: 4 | AY63: 27 | AZ63: 0 | BA63: 0 | BB63: 0 | BC63: 1 | BD63: 0 | BE63: 0 | BF63: 2 | BG63: 164 | BH63: 267 | BI63: 54.3 | BJ63: 22 | BK63: 34.4 | BL63: 0 | BM63: 0 | BN63: 0 | BO63: 0 | BP63: 15 | BQ63: 0.02 | BR63: 0.19 | BS63: 0.21 | BT63: 22.47 | CC63: 217 | CD63: 83 | CE63: 280 | CF63: 95 | CG63: 308 | CH63: 107 | CI63: 279 | CJ63: 91 | CK63: 0 | CL63: 0 | CM63: 0.01 | CN63: 0.01 | CO63: 1.59 | CP63: 1.91 | CQ63: 277 | CR63: 50 | CS63: 255 | CT63: 129 | CU63: 224 | CV63: 91 | CW63: 367 | CX63: 130 | CY63: 1.06 | CZ63: 0.28 | DA63: 0
A64: TRUE | B64: TRUE | E64: 620487 | F64: 0 | G64: 0 | H64: 0 | I64: 0 | J64: 0 | K64: 0 | L64: 2 | M64: 2.2 | O64: 0 | P64: Veljko | Q64: 0 | R64: 63 | S64: FALSE | V64: 50 | W64: 620487.jpg | X64: 2.7 | Y64: FALSE | Z64: Milosavljevic | AA64: 0.1 | AB64: FALSE | AD64: a | AE64: 3 | AF64: 91 | AG64: 19 | AH64: 0 | AI64: 0 | AJ64: 0 | AK64: 0 | AL64: 0 | AM64: 3.8 | AN64: Milosavljević | AS64: FALSE | AT64: p620487 | AU64: 367 | AV64: 0 | AW64: 0 | AX64: 1 | AY64: 6 | AZ64: 0 | BA64: 0 | BB64: 0 | BC64: 0 | BD64: 0 | BE64: 0 | BF64: 0 | BG64: 63 | BH64: 98.4 | BI64: 13.9 | BJ64: 10 | BK64: 12.2 | BL64: 0 | BM64: 0 | BN64: 0 | BO64: 0 | BP64: 4 | BQ64: 0.15 | BR64: 0.19 | BS64: 0.34 | BT64: 4.42 | CC64: 306 | CD64: 111 | CE64: 331 | CF64: 117 | CG64: 328 | CH64: 118 | CI64: 330 | CJ64: 114 | CK64: 0.04 | CL64: 0 | CM64: 0.05 | CN64: 0.09 | CO64: 1.08 | CP64: 1.47 | CQ64: 361 | CR64: 72 | CS64: 339 | CT64: 151 | CU64: 207 | CV64: 85 | CW64: 471 | CX64: 162 | CY64: 0.98 | CZ64: 0.25 | DA64: 0
A65: TRUE | B65: TRUE | E65: 54469 | F65: 0 | G65: 0 | H65: 0 | I65: 0 | J65: 0 | K65: 0 | L65: 2 | M65: 1.7 | O65: 0 | P65: Adam | Q65: 0 | R65: 64 | S65: FALSE | V65: 45 | W65: 54469.jpg | X65: 2.6 | Y65: FALSE | Z65: Smith | AA65: 0.1 | AB65: FALSE | AD65: a | AE65: 3 | AF65: 91 | AG65: 58 | AH65: 0 | AI65: 0 | AJ65: 0 | AK65: 0 | AL65: 0 | AM65: 12.9 | AN65: Smith | AS65: FALSE | AT65: p54469 | AU65: 1073 | AV65: 0 | AW65: 2 | AX65: 6 | AY65: 16 | AZ65: 0 | BA65: 0 | BB65: 0 | BC65: 3 | BD65: 0 | BE65: 0 | BF65: 4 | BG65: 185 | BH65: 176.2 | BI65: 76.6 | BJ65: 18 | BK65: 27.1 | BL65: 0 | BM65: 0 | BN65: 0 | BO65: 0 | BP65: 14 | BQ65: 0 | BR65: 0.23 | BS65: 0.23 | BT65: 18.18 | CC65: 259 | CD65: 97 | CE65: 260 | CF65: 87 | CG65: 314 | CH65: 112 | CI65: 296 | CJ65: 100 | CK65: 0 | CL65: 0 | CM65: 0.02 | CN65: 0.02 | CO65: 1.52 | CP65: 1.34 | CQ65: 369 | CR65: 74 | CS65: 68 | CT65: 48 | CU65: 217 | CV65: 86 | CW65: 407 | CX65: 145 | CY65: 1.17 | CZ65: 0.5 | DA65: 0
A66: TRUE | B66: TRUE | E66: 436893 | F66: 0 | G66: 0 | H66: 0 | I66: 0 | J66: 0 | K66: 0 | L66: 2 | M66: 1.7 | O66: 0 | P66: Julián | Q66: 0 | R66: 65 | S66: FALSE | V66: 45 | W66: 436893.jpg | X66: 0 | Y66: FALSE | Z66: Araujo Zúñiga | AA66: 0.1 | AB66: FALSE | AD66: a | AE66: 3 | AF66: 91 | AG66: 0 | AH66: 0 | AI66: 0 | AJ66: 0 | AK66: 0 | AL66: 0 | AM66: 0 | AN66: J.Araujo | AS66: FALSE | AT66: p436893 | AU66: 0 | AV66: 0 | AW66: 0 | AX66: 0 | AY66: 0 | AZ66: 0 | BA66: 0 | BB66: 0 | BC66: 0 | BD66: 0 | BE66: 0 | BF66: 0 | BG66: 0 | BH66: 0 | BI66: 0 | BJ66: 0 | BK66: 0 | BL66: 0 | BM66: 0 | BN66: 0 | BO66: 0 | BP66: 0 | BQ66: 0 | BR66: 0 | BS66: 0 | BT66: 0 | CC66: 462 | CD66: 173 | CE66: 454 | CF66: 173 | CG66: 439 | CH66: 172 | CI66: 464 | CJ66: 173 | CK66: 0 | CL66: 0 | CM66: 0 | CN66: 0 | CO66: 0 | CP66: 0 | CQ66: 428 | CR66: 113 | CS66: 127 | CT66: 87 | CU66: 467 | CV66: 173 | CW66: 429 | CX66: 151 | CY66: 0 | CZ66: 0 | DA66: 0
A67: TRUE | B67: TRUE | E67: 575901 | F67: 0 | G67: 0 | H67: 0 | I67: 0 | J67: 0 | K67: 0 | L67: 2 | M67: 1 | O67: 0 | P67: Julio | Q67: 0 | R67: 66 | S67: FALSE | V67: 40 | W67: 575901.jpg | X67: 1 | Y67: FALSE | Z67: Soler Barreto | AA67: 0.6 | AB67: FALSE | AD67: a | AE67: 3 | AF67: 91 | AG67: 3 | AH67: 0 | AI67: 0 | AJ67: 0 | AK67: 0 | AL67: 0 | AM67: 0.8 | AN67: Soler | AS67: FALSE | AT67: p575901 | AU67: 34 | AV67: 0 | AW67: 0 | AX67: 0 | AY67: 2 | AZ67: 0 | BA67: 0 | BB67: 0 | BC67: 0 | BD67: 0 | BE67: 0 | BF67: 0 | BG67: 2 | BH67: 1.8 | BI67: 2.5 | BJ67: 2 | BK67: 0.6 | BL67: 0 | BM67: 0 | BN67: 0 | BO67: 0 | BP67: 0 | BQ67: 0 | BR67: 0 | BS67: 0 | BT67: 1.62 | CC67: 388 | CD67: 132 | CE67: 362 | CF67: 127 | CG67: 347 | CH67: 125 | CI67: 387 | CJ67: 131 | CK67: 0 | CL67: 0 | CM67: 0 | CN67: 0 | CO67: 4.29 | CP67: 5.29 | CQ67: 549 | CR67: 176 | CS67: 58 | CT67: 39 | CU67: 360 | CV67: 125 | CW67: 246 | CX67: 88 | CY67: 0 | CZ67: 0 | DA67: 0
A68: TRUE | B68: TRUE | E68: 499604 | F68: 0 | G68: 0 | H68: 0 | I68: 0 | J68: 0 | K68: 0 | L68: 3 | M68: 2.3 | O68: 0 | P68: Rayan Vitor | Q68: 0 | R68: 67 | S68: FALSE | V68: 65 | W68: 499604.jpg | X68: 4.5 | Y68: FALSE | Z68: Simplício Rocha | AA68: 4.2 | AB68: FALSE | AD68: a | AE68: 3 | AF68: 91 | AG68: 67 | AH68: 0 | AI68: 0 | AJ68: 0 | AK68: 0 | AL68: 0 | AM68: 10.3 | AN68: Rayan | AS68: FALSE | AT68: p499604 | AU68: 1110 | AV68: 5 | AW68: 2 | AX68: 6 | AY68: 10 | AZ68: 0 | BA68: 0 | BB68: 0 | BC68: 1 | BD68: 0 | BE68: 0 | BF68: 3 | BG68: 238 | BH68: 277.6 | BI68: 211.9 | BJ68: 263 | BK68: 75.3 | BL68: 0 | BM68: 0 | BN68: 0 | BO68: 0 | BP68: 13 | BQ68: 2.67 | BR68: 1.84 | BS68: 4.51 | BT68: 19.14 | CC68: 213 | CD68: 94 | CE68: 157 | CF68: 105 | CG68: 112 | CH68: 65 | CI68: 182 | CJ68: 90 | CK68: 0.22 | CL68: 0 | CM68: 0.15 | CN68: 0.37 | CO68: 1.55 | CP68: 0.81 | CQ68: 50 | CR68: 35 | CS68: 523 | CT68: 223 | CU68: 27 | CV68: 12 | CW68: 84 | CX68: 27 | CY68: 1.05 | CZ68: 0.49 | DA68: 0
A69: TRUE | B69: TRUE | E69: 201658 | F69: 0 | G69: 0 | H69: 0 | I69: 0 | J69: 0 | K69: 0 | L69: 3 | M69: 2.1 | O69: 0 | P69: Marcus | Q69: 0 | R69: 68 | S69: FALSE | V69: 60 | W69: 201658.jpg | X69: 4 | Y69: FALSE | Z69: Tavernier | AA69: 1.7 | AB69: FALSE | AD69: a | AE69: 3 | AF69: 91 | AG69: 137 | AH69: 0 | AI69: 0 | AJ69: 0 | AK69: 0 | AL69: 0 | AM69: 22.8 | AN69: Tavernier | AS69: FALSE | AT69: p201658 | AU69: 2732 | AV69: 7 | AW69: 4 | AX69: 11 | AY69: 44 | AZ69: 0 | BA69: 0 | BB69: 0 | BC69: 6 | BD69: 0 | BE69: 0 | BF69: 14 | BG69: 552 | BH69: 656.8 | BI69: 816.6 | BJ69: 605 | BK69: 207.9 | BL69: 0 | BM69: 0 | BN69: 0 | BO69: 0 | BP69: 31 | BQ69: 9.06 | BR69: 4.6 | BS69: 13.66 | BT69: 41.06 | BU69: 6 | BW69: 1 | BY69: 3 | CC69: 60 | CD69: 17 | CE69: 15 | CF69: 14 | CG69: 30 | CH69: 16 | CI69: 19 | CJ69: 15 | CK69: 0.3 | CL69: 0 | CM69: 0.15 | CN69: 0.45 | CO69: 1.35 | CP69: 1.45 | CQ69: 66 | CR69: 44 | CS69: 460 | CT69: 179 | CU69: 57 | CV69: 24 | CW69: 151 | CX69: 46 | CY69: 1.02 | CZ69: 0.36 | DA69: 0
A70: TRUE | B70: TRUE | E70: 503139 | F70: 0 | G70: 0 | H70: 0 | I70: 0 | J70: 0 | K70: 0 | L70: 3 | M70: 2.1 | O70: 0 | P70: Alex | Q70: 0 | R70: 69 | S70: FALSE | V70: 60 | W70: 503139.jpg | X70: 3.7 | Y70: FALSE | Z70: Scott | AA70: 1.6 | AB70: FALSE | AD70: a | AE70: 3 | AF70: 91 | AG70: 136 | AH70: 0 | AI70: 0 | AJ70: 0 | AK70: 0 | AL70: 0 | AM70: 22.7 | AN70: Scott | AS70: FALSE | AT70: p503139 | AU70: 2848 | AV70: 3 | AW70: 2 | AX70: 11 | AY70: 41 | AZ70: 0 | BA70: 0 | BB70: 0 | BC70: 5 | BD70: 0 | BE70: 0 | BF70: 9 | BG70: 603 | BH70: 597.2 | BI70: 482 | BJ70: 314 | BK70: 139 | BL70: 0 | BM70: 0 | BN70: 0 | BO70: 0 | BP70: 34 | BQ70: 3.8 | BR70: 2.94 | BS70: 6.74 | BT70: 47.02 | BU70: 7 | BW70: 4 | CC70: 77 | CD70: 25 | CE70: 53 | CF70: 46 | CG70: 91 | CH70: 57 | CI70: 63 | CJ70: 41 | CK70: 0.12 | CL70: 0 | CM70: 0.09 | CN70: 0.21 | CO70: 1.49 | CP70: 1.3 | CQ70: 98 | CR70: 63 | CS70: 492 | CT70: 198 | CU70: 81 | CV70: 35 | CW70: 152 | CX70: 47 | CY70: 1.07 | CZ70: 0.35 | DA70: 0
A71: TRUE | B71: TRUE | E71: 222683 | F71: 0 | G71: 0 | H71: 0 | I71: 0 | J71: 0 | K71: 0 | L71: 3 | M71: 2.1 | O71: 0 | P71: Justin | Q71: 0 | R71: 70 | S71: FALSE | V71: 60 | W71: 222683.jpg | X71: 2 | Y71: FALSE | Z71: Kluivert | AA71: 0.8 | AB71: FALSE | AD71: a | AE71: 3 | AF71: 91 | AG71: 41 | AH71: 0 | AI71: 0 | AJ71: 0 | AK71: 0 | AL71: 0 | AM71: 6.8 | AN71: Kluivert | AS71: FALSE | AT71: p222683 | AU71: 945 | AV71: 2 | AW71: 0 | AX71: 4 | AY71: 19 | AZ71: 0 | BA71: 0 | BB71: 0 | BC71: 5 | BD71: 0 | BE71: 0 | BF71: 3 | BG71: 147 | BH71: 148 | BI71: 305.1 | BJ71: 135 | BK71: 58.8 | BL71: 0 | BM71: 0 | BN71: 0 | BO71: 0 | BP71: 10 | BQ71: 2.31 | BR71: 1.55 | BS71: 3.86 | BT71: 17.96 | BW71: 2 | BY71: 2 | CC71: 276 | CD71: 127 | CE71: 124 | CF71: 86 | CG71: 202 | CH71: 112 | CI71: 224 | CJ71: 114 | CK71: 0.22 | CL71: 0 | CM71: 0.15 | CN71: 0.37 | CO71: 1.71 | CP71: 1.81 | CQ71: 74 | CR71: 47 | CS71: 468 | CT71: 182 | CU71: 290 | CV71: 124 | CW71: 216 | CX71: 72 | CY71: 0.95 | CZ71: 0.38 | DA71: 0
A72: TRUE | B72: TRUE | E72: 155408 | F72: 0 | G72: 0 | H72: 0 | I72: 0 | J72: 0 | K72: 0 | L72: 3 | M72: 1.5 | O72: 0 | P72: Lewis | Q72: 0 | R72: 71 | S72: FALSE | V72: 50 | W72: 155408.jpg | X72: 2.2 | Y72: FALSE | Z72: Cook | AA72: 0.1 | AB72: FALSE | AD72: a | AE72: 3 | AF72: 91 | AG72: 40 | AH72: 0 | AI72: 0 | AJ72: 0 | AK72: 0 | AL72: 0 | AM72: 8 | AN72: Cook | AS72: FALSE | AT72: p155408 | AU72: 872 | AV72: 0 | AW72: 1 | AX72: 1 | AY72: 19 | AZ72: 0 | BA72: 0 | BB72: 0 | BC72: 1 | BD72: 1 | BE72: 0 | BF72: 0 | BG72: 190 | BH72: 206.8 | BI72: 183.8 | BJ72: 12 | BK72: 40.6 | BL72: 0 | BM72: 0 | BN72: 0 | BO72: 0 | BP72: 8 | BQ72: 0.07 | BR72: 0.52 | BS72: 0.59 | BT72: 14 | BU72: 8 | CC72: 247 | CD72: 111 | CE72: 181 | CF72: 120 | CG72: 324 | CH72: 165 | CI72: 269 | CJ72: 131 | CK72: 0.01 | CL72: 0 | CM72: 0.05 | CN72: 0.06 | CO72: 1.44 | CP72: 1.96 | CQ72: 231 | CR72: 140 | CS72: 209 | CT72: 34 | CU72: 266 | CV72: 111 | CW72: 415 | CX72: 156 | CY72: 0.83 | CZ72: 0.1 | DA72: 0
A73: TRUE | B73: TRUE | E73: 496208 | F73: 0 | G73: 0 | H73: 0 | I73: 0 | J73: 0 | K73: 0 | L73: 3 | M73: 1.5 | O73: 0 | P73: Ben | Q73: 0 | R73: 72 | S73: FALSE | V73: 50 | W73: 496208.jpg | X73: 1.4 | Y73: FALSE | Z73: Gannon-Doak | AA73: 0.1 | AB73: FALSE | AD73: a | AE73: 3 | AF73: 91 | AG73: 11 | AH73: 0 | AI73: 0 | AJ73: 0 | AK73: 0 | AL73: 0 | AM73: 2.2 | AN73: Gannon-Doak | AS73: FALSE | AT73: p496208 | AU73: 105 | AV73: 0 | AW73: 1 | AX73: 0 | AY73: 1 | AZ73: 0 | BA73: 0 | BB73: 0 | BC73: 0 | BD73: 0 | BE73: 0 | BF73: 0 | BG73: 33 | BH73: 32.4 | BI73: 17.8 | BJ73: 39 | BK73: 8.9 | BL73: 0 | BM73: 0 | BN73: 0 | BO73: 0 | BP73: 0 | BQ73: 0.26 | BR73: 0.13 | BS73: 0.39 | BT73: 4.74 | CC73: 347 | CD73: 160 | CE73: 326 | CF73: 167 | CG73: 286 | CH73: 150 | CI73: 341 | CJ73: 161 | CK73: 0.22 | CL73: 0 | CM73: 0.11 | CN73: 0.33 | CO73: 4.06 | CP73: 0.86 | CQ73: 320 | CR73: 186 | CS73: 298 | CT73: 80 | CU73: 337 | CV73: 151 | CW73: 393 | CX73: 147 | CY73: 0 | CZ73: 0 | DA73: 0
A74: TRUE | B74: TRUE | E74: 200785 | F74: 0 | G74: 0 | H74: 0 | I74: 0 | J74: 0 | K74: 0 | L74: 3 | M74: 1.5 | O74: 0 | P74: Tyler | Q74: 0 | R74: 73 | S74: FALSE | V74: 50 | W74: 200785.jpg | X74: 3.1 | Y74: FALSE | Z74: Adams | AA74: 0.7 | AB74: FALSE | AD74: a | AE74: 3 | AF74: 91 | AG74: 77 | AH74: 0 | AI74: 0 | AJ74: 0 | AK74: 0 | AL74: 0 | AM74: 15.4 | AN74: Adams | AS74: FALSE | AT74: p200785 | AU74: 1769 | AV74: 2 | AW74: 2 | AX74: 7 | AY74: 28 | AZ74: 0 | BA74: 0 | BB74: 0 | BC74: 8 | BD74: 0 | BE74: 0 | BF74: 3 | BG74: 346 | BH74: 387 | BI74: 158.2 | BJ74: 115 | BK74: 66.3 | BL74: 0 | BM74: 0 | BN74: 0 | BO74: 0 | BP74: 21 | BQ74: 0.63 | BR74: 0.63 | BS74: 1.26 | BT74: 27.18 | CC74: 157 | CD74: 62 | CE74: 197 | CF74: 126 | CG74: 223 | CH74: 121 | CI74: 208 | CJ74: 105 | CK74: 0.03 | CL74: 0 | CM74: 0.03 | CN74: 0.06 | CO74: 1.38 | CP74: 1.42 | CQ74: 244 | CR74: 149 | CS74: 222 | CT74: 43 | CU74: 158 | CV74: 60 | CW74: 235 | CX74: 79 | CY74: 1.07 | CZ74: 0.36 | DA74: 0
A75: TRUE | B75: TRUE | E75: 111317 | F75: 0 | G75: 0 | H75: 0 | I75: 0 | J75: 0 | K75: 0 | L75: 3 | M75: 1.5 | O75: 0 | P75: David | Q75: 0 | R75: 74 | S75: FALSE | V75: 50 | W75: 111317.jpg | X75: 1.9 | Y75: FALSE | Z75: Brooks | AA75: 0.2 | AB75: FALSE | AD75: a | AE75: 3 | AF75: 91 | AG75: 59 | AH75: 0 | AI75: 0 | AJ75: 0 | AK75: 0 | AL75: 0 | AM75: 11.8 | AN75: Brooks | AS75: FALSE | AT75: p111317 | AU75: 1188 | AV75: 1 | AW75: 3 | AX75: 5 | AY75: 20 | AZ75: 0 | BA75: 0 | BB75: 0 | BC75: 7 | BD75: 0 | BE75: 0 | BF75: 4 | BG75: 215 | BH75: 236.2 | BI75: 384.5 | BJ75: 434 | BK75: 104.1 | BL75: 0 | BM75: 0 | BN75: 0 | BO75: 0 | BP75: 13 | BQ75: 5.81 | BR75: 3.4 | BS75: 9.21 | BT75: 20.25 | BU75: 9 | BW75: 3 | CC75: 230 | CD75: 102 | CE75: 87 | CF75: 65 | CG75: 53 | CH75: 32 | CI75: 121 | CJ75: 69 | CK75: 0.44 | CL75: 0 | CM75: 0.26 | CN75: 0.7 | CO75: 1.53 | CP75: 1.52 | CQ75: 223 | CR75: 135 | CS75: 201 | CT75: 29 | CU75: 291 | CV75: 125 | CW75: 360 | CX75: 133 | CY75: 0.98 | CZ75: 0.38 | DA75: 0
A76: TRUE | B76: TRUE | E76: 158499 | F76: 0 | G76: 0 | H76: 0 | I76: 0 | J76: 0 | K76: 0 | L76: 3 | M76: 1.5 | O76: 0 | P76: Ryan | Q76: 0 | R76: 75 | S76: FALSE | V76: 50 | W76: 158499.jpg | X76: 1.8 | Y76: FALSE | Z76: Christie | AA76: 0.2 | AB76: FALSE | AD76: a | AE76: 3 | AF76: 91 | AG76: 47 | AH76: 0 | AI76: 0 | AJ76: 0 | AK76: 0 | AL76: 0 | AM76: 9.4 | AN76: Christie | AS76: FALSE | AT76: p158499 | AU76: 978 | AV76: 2 | AW76: 1 | AX76: 3 | AY76: 14 | AZ76: 0 | BA76: 0 | BB76: 0 | BC76: 3 | BD76: 1 | BE76: 0 | BF76: 2 | BG76: 214 | BH76: 226.6 | BI76: 197 | BJ76: 220 | BK76: 64.7 | BL76: 0 | BM76: 0 | BN76: 0 | BO76: 0 | BP76: 9 | BQ76: 1.81 | BR76: 0.79 | BS76: 2.6 | BT76: 19.14 | BU76: 10 | CC76: 235 | CD76: 105 | CE76: 173 | CF76: 115 | CG76: 138 | CH76: 78 | CI76: 210 | CJ76: 107 | CK76: 0.17 | CL76: 0 | CM76: 0.07 | CN76: 0.24 | CO76: 1.76 | CP76: 1.29 | CQ76: 232 | CR76: 141 | CS76: 210 | CT76: 35 | CU76: 302 | CV76: 131 | CW76: 361 | CX76: 134 | CY76: 0.83 | CZ76: 0.28 | DA76: 0
A77: TRUE | B77: TRUE | E77: 614574 | F77: 0 | G77: 0 | H77: 0 | I77: 0 | J77: 0 | K77: 0 | L77: 3 | M77: 1.5 | O77: 0 | P77: Alex | Q77: 0 | R77: 76 | S77: FALSE | V77: 50 | W77: 614574.jpg | X77: 0.9 | Y77: FALSE | Z77: Tóth | AA77: 0 | AB77: FALSE | AD77: a | AE77: 3 | AF77: 91 | AG77: 8 | AH77: 0 | AI77: 0 | AJ77: 0 | AK77: 0 | AL77: 0 | AM77: 1.6 | AN77: Tóth.A | AS77: FALSE | AT77: p614574 | AU77: 135 | AV77: 0 | AW77: 0 | AX77: 0 | AY77: 3 | AZ77: 0 | BA77: 0 | BB77: 0 | BC77: 1 | BD77: 0 | BE77: 0 | BF77: 0 | BG77: 32 | BH77: 18.6 | BI77: 60.2 | BJ77: 18 | BK77: 9.6 | BL77: 0 | BM77: 0 | BN77: 0 | BO77: 0 | BP77: 2 | BQ77: 0.11 | BR77: 0.33 | BS77: 0.44 | BT77: 4.9 | CC77: 359 | CD77: 166 | CE77: 276 | CF77: 151 | CG77: 315 | CH77: 160 | CI77: 339 | CJ77: 159 | CK77: 0.07 | CL77: 0 | CM77: 0.22 | CN77: 0.29 | CO77: 3.27 | CP77: 2 | CQ77: 360 | CR77: 216 | CS77: 338 | CT77: 110 | CU77: 394 | CV77: 185 | CW77: 519 | CX77: 216 | CY77: 1.33 | CZ77: 0 | DA77: 0
A78: TRUE | B78: TRUE | E78: 489888 | F78: 0 | G78: 0 | H78: 0 | I78: 0 | J78: 0 | K78: 0 | L78: 3 | M78: 1.5 | O78: 0 | P78: Amine | Q78: 0 | R78: 77 | S78: FALSE | V78: 50 | W78: 489888.jpg | X78: 2.2 | Y78: FALSE | Z78: Adli | AA78: 0.2 | AB78: FALSE | AD78: a | AE78: 3 | AF78: 91 | AG78: 67 | AH78: 0 | AI78: 0 | AJ78: 0 | AK78: 0 | AL78: 0 | AM78: 13.4 | AN78: Adli | AS78: FALSE | AT78: p489888 | AU78: 1074 | AV78: 3 | AW78: 2 | AX78: 3 | AY78: 17 | AZ78: 0 | BA78: 0 | BB78: 0 | BC78: 2 | BD78: 0 | BE78: 0 | BF78: 4 | BG78: 241 | BH78: 272.6 | BI78: 235.9 | BJ78: 260 | BK78: 76.1 | BL78: 0 | BM78: 0 | BN78: 0 | BO78: 0 | BP78: 10 | BQ78: 2.6 | BR78: 1.62 | BS78: 4.22 | BT78: 18.22 | CC78: 216 | CD78: 95 | CE78: 145 | CF78: 98 | CG78: 113 | CH78: 66 | CI78: 180 | CJ78: 88 | CK78: 0.22 | CL78: 0 | CM78: 0.14 | CN78: 0.36 | CO78: 1.53 | CP78: 1.42 | CQ78: 312 | CR78: 181 | CS78: 290 | CT78: 75 | CU78: 269 | CV78: 114 | CW78: 342 | CX78: 125 | CY78: 0.84 | CZ78: 0.25 | DA78: 0
A79: TRUE | B79: TRUE | E79: 560262 | F79: 0 | G79: 0 | H79: 0 | I79: 0 | J79: 0 | K79: 0 | L79: 3 | M79: 2.6 | O79: 0 | P79: Junior | Q79: 0 | R79: 78 | S79: FALSE | V79: 75 | W79: 560262.jpg | X79: 3.4 | Y79: FALSE | Z79: Kroupi | AA79: 17.3 | AB79: FALSE | AD79: a | AE79: 3 | AF79: 91 | AG79: 113 | AH79: 0 | AI79: 0 | AJ79: 0 | AK79: 0 | AL79: 0 | AM79: 15.1 | AN79: Kroupi.Jr | AS79: FALSE | AT79: p560262 | AU79: 1663 | AV79: 13 | AW79: 0 | AX79: 10 | AY79: 21 | AZ79: 0 | BA79: 0 | BB79: 0 | BC79: 5 | BD79: 0 | BE79: 0 | BF79: 13 | BG79: 480 | BH79: 532.2 | BI79: 306.9 | BJ79: 563 | BK79: 139.9 | BL79: 0 | BM79: 0 | BN79: 0 | BO79: 0 | BP79: 21 | BQ79: 8.31 | BR79: 1.51 | BS79: 9.82 | BT79: 25.91 | BY79: 1 | CC79: 103 | CD79: 33 | CE79: 122 | CF79: 84 | CG79: 37 | CH79: 22 | CI79: 60 | CJ79: 39 | CK79: 0.45 | CL79: 0 | CM79: 0.08 | CN79: 0.53 | CO79: 1.4 | CP79: 1.14 | CQ79: 22 | CR79: 13 | CS79: 546 | CT79: 239 | CU79: 123 | CV79: 51 | CW79: 20 | CX79: 7 | CY79: 1.14 | CZ79: 0.54 | DA79: 0
A80: TRUE | B80: TRUE | E80: 444102 | F80: 0 | G80: 0 | H80: 0 | I80: 0 | J80: 0 | K80: 0 | L80: 4 | M80: 2 | O80: 0 | P80: Francisco Evanilson | Q80: 0 | R80: 79 | S80: FALSE | V80: 60 | W80: 444102.jpg | X80: 3.2 | Y80: FALSE | Z80: de Lima Barbosa | AA80: 2 | AB80: FALSE | AD80: a | AE80: 3 | AF80: 91 | AG80: 115 | AH80: 0 | AI80: 0 | AJ80: 0 | AK80: 0 | AL80: 0 | AM80: 19.2 | AN80: Evanilson | AS80: FALSE | AT80: p444102 | AU80: 2741 | AV80: 6 | AW80: 7 | AX80: 11 | AY80: 40 | AZ80: 0 | BA80: 0 | BB80: 0 | BC80: 2 | BD80: 0 | BE80: 0 | BF80: 6 | BG80: 412 | BH80: 350.6 | BI80: 397.9 | BJ80: 809 | BK80: 155.5 | BL80: 0 | BM80: 0 | BN80: 0 | BO80: 0 | BP80: 32 | BQ80: 10.64 | BR80: 1.48 | BS80: 12.12 | BT80: 39.02 | CC80: 171 | CD80: 15 | CE80: 78 | CF80: 2 | CG80: 14 | CH80: 7 | CI80: 48 | CJ80: 10 | CK80: 0.35 | CL80: 0 | CM80: 0.05 | CN80: 0.4 | CO80: 1.28 | CP80: 1.31 | CQ80: 84 | CR80: 22 | CS80: 478 | CT80: 52 | CU80: 152 | CV80: 13 | CW80: 134 | CX80: 22 | CY80: 1.05 | CZ80: 0.36 | DA80: 0
A81: TRUE | B81: TRUE | E81: 168636 | F81: 0 | G81: 0 | H81: 0 | I81: 0 | J81: 0 | K81: 0 | L81: 4 | M81: 1.8 | O81: 0 | P81: Enes | Q81: 0 | R81: 80 | S81: FALSE | V81: 55 | W81: 168636.jpg | X81: 1.2 | Y81: FALSE | Z81: Ünal | AA81: 0.2 | AB81: FALSE | AD81: a | AE81: 3 | AF81: 91 | AG81: 27 | AH81: 0 | AI81: 0 | AJ81: 0 | AK81: 0 | AL81: 0 | AM81: 4.9 | AN81: Enes Ünal | AS81: FALSE | AT81: p168636 | AU81: 214 | AV81: 1 | AW81: 0 | AX81: 0 | AY81: 3 | AZ81: 0 | BA81: 0 | BB81: 0 | BC81: 1 | BD81: 0 | BE81: 0 | BF81: 1 | BG81: 83 | BH81: 70.2 | BI81: 25 | BJ81: 104 | BK81: 19.1 | BL81: 0 | BM81: 0 | BN81: 0 | BO81: 0 | BP81: 0 | BQ81: 2 | BR81: 0.07 | BS81: 2.07 | BT81: 6.16 | BW81: 5 | CC81: 322 | CD81: 35 | CE81: 315 | CF81: 40 | CG81: 229 | CH81: 38 | CI81: 311 | CJ81: 37 | CK81: 0.84 | CL81: 0 | CM81: 0.03 | CN81: 0.87 | CO81: 2.59 | CP81: 1.26 | CQ81: 118 | CR81: 28 | CS81: 355 | CT81: 25 | CU81: 350 | CV81: 40 | CW81: 335 | CX81: 59 | CY81: 0 | CZ81: 0 | DA81: 0
A82: TRUE | B82: TRUE | E82: 561245 | F82: 0 | G82: 0 | H82: 0 | I82: 0 | J82: 0 | K82: 0 | L82: 4 | M82: 2 | O82: 0 | P82: Álvaro | Q82: 0 | R82: 81 | S82: FALSE | V82: 60 | W82: 561245.jpg | X82: 0 | Y82: FALSE | Z82: Rodríguez | AA82: 0.3 | AB82: FALSE | AD82: a | AE82: 3 | AF82: 91 | AG82: 0 | AH82: 0 | AI82: 0 | AJ82: 0 | AK82: 0 | AL82: 0 | AM82: 0 | AN82: Rodríguez | AS82: FALSE | AT82: p561245 | AU82: 0 | AV82: 0 | AW82: 0 | AX82: 0 | AY82: 0 | AZ82: 0 | BA82: 0 | BB82: 0 | BC82: 0 | BD82: 0 | BE82: 0 | BF82: 0 | BG82: 0 | BH82: 0 | BI82: 0 | BJ82: 0 | BK82: 0 | BL82: 0 | BM82: 0 | BN82: 0 | BO82: 0 | BP82: 0 | BQ82: 0 | BR82: 0 | BS82: 0 | BT82: 0 | CC82: 551 | CD82: 67 | CE82: 551 | CF82: 67 | CG82: 551 | CH82: 67 | CI82: 551 | CJ82: 67 | CK82: 0 | CL82: 0 | CM82: 0 | CN82: 0 | CO82: 0 | CP82: 0 | CQ82: 104 | CR82: 26 | CS82: 498 | CT82: 56 | CU82: 551 | CV82: 67 | CW82: 328 | CX82: 58 | CY82: 0 | CZ82: 0 | DA82: 0
A83: TRUE | B83: TRUE | E83: 200720 | F83: 0 | G83: 0 | H83: 0 | I83: 0 | J83: 0 | K83: 0 | L83: 1 | M83: 2.6 | O83: 0 | P83: Caoimhín | Q83: 0 | R83: 82 | S83: FALSE | V83: 50 | W83: 200720.jpg | X83: 3.9 | Y83: FALSE | Z83: Kelleher | AA83: 5.8 | AB83: FALSE | AD83: a | AE83: 4 | AF83: 94 | AG83: 143 | AH83: 0 | AI83: 0 | AJ83: 0 | AK83: 0 | AL83: 0 | AM83: 28.6 | AN83: Kelleher | AS83: FALSE | AT83: p200720 | AU83: 3330 | AV83: 0 | AW83: 0 | AX83: 10 | AY83: 49 | AZ83: 0 | BA83: 3 | BB83: 0 | BC83: 1 | BD83: 0 | BE83: 109 | BF83: 11 | BG83: 570 | BH83: 913.8 | BI83: 23 | BJ83: 0 | BK83: 93.8 | BL83: 0 | BM83: 0 | BN83: 0 | BO83: 0 | BP83: 37 | BQ83: 0 | BR83: 0.22 | BS83: 0.22 | BT83: 53.48 | CC83: 12 | CD83: 3 | CE83: 320 | CF83: 5 | CG83: 487 | CH83: 51 | CI83: 143 | CJ83: 3 | CK83: 0 | CL83: 2.95 | CM83: 0.01 | CN83: 0.01 | CO83: 1.45 | CP83: 1.32 | CQ83: 243 | CR83: 10 | CS83: 221 | CT83: 48 | CU83: 64 | CV83: 5 | CW83: 69 | CX83: 11 | CY83: 1 | CZ83: 0.27 | DA83: 0
A84: TRUE | B84: TRUE | E84: 507433 | F84: 0 | G84: 0 | H84: 0 | I84: 0 | J84: 0 | K84: 0 | L84: 1 | M84: 2 | O84: 0 | P84: Hákon Rafn | Q84: 0 | R84: 83 | S84: FALSE | V84: 45 | W84: 507433.jpg | X84: 1 | Y84: FALSE | Z84: Valdimarsson | AA84: 0.1 | AB84: FALSE | AD84: a | AE84: 4 | AF84: 94 | AG84: 1 | AH84: 0 | AI84: 0 | AJ84: 0 | AK84: 0 | AL84: 0 | AM84: 0.2 | AN84: Valdimarsson | AS84: FALSE | AT84: p507433 | AU84: 90 | AV84: 0 | AW84: 0 | AX84: 0 | AY84: 3 | AZ84: 0 | BA84: 0 | BB84: 0 | BC84: 0 | BD84: 0 | BE84: 1 | BF84: 0 | BG84: 1 | BH84: 13 | BI84: 0 | BJ84: 0 | BK84: 1.3 | BL84: 0 | BM84: 0 | BN84: 0 | BO84: 0 | BP84: 1 | BQ84: 0 | BR84: 0 | BS84: 0 | BT84: 0.97 | CC84: 365 | CD84: 31 | CE84: 466 | CF84: 49 | CG84: 454 | CH84: 43 | CI84: 383 | CJ84: 31 | CK84: 0 | CL84: 1 | CM84: 0 | CN84: 0 | CO84: 0.97 | CP84: 3 | CQ84: 454 | CR84: 37 | CS84: 153 | CT84: 39 | CU84: 364 | CV84: 31 | CW84: 404 | CX84: 47 | CY84: 1 | CZ84: 0 | DA84: 0
A85: TRUE | B85: TRUE | E85: 432830 | F85: 0 | G85: 0 | H85: 0 | I85: 0 | J85: 0 | K85: 0 | L85: 2 | M85: 2.5 | O85: 0 | P85: Nathan | Q85: 0 | R85: 84 | S85: FALSE | V85: 55 | W85: 432830.jpg | X85: 3.7 | Y85: FALSE | Z85: Collins | AA85: 2.3 | AB85: FALSE | AD85: a | AE85: 4 | AF85: 94 | AG85: 129 | AH85: 0 | AI85: 0 | AJ85: 0 | AK85: 0 | AL85: 0 | AM85: 23.5 | AN85: Collins | AS85: FALSE | AT85: p432830 | AU85: 2971 | AV85: 1 | AW85: 2 | AX85: 9 | AY85: 44 | AZ85: 1 | BA85: 0 | BB85: 0 | BC85: 7 | BD85: 0 | BE85: 0 | BF85: 7 | BG85: 450 | BH85: 848.6 | BI85: 143.8 | BJ85: 325 | BK85: 131.9 | BL85: 0 | BM85: 0 | BN85: 0 | BO85: 0 | BP85: 32 | BQ85: 2.24 | BR85: 1.71 | BS85: 3.95 | BT85: 47.52 | CC85: 20 | CD85: 8 | CE85: 206 | CF85: 54 | CG85: 86 | CH85: 10 | CI85: 73 | CJ85: 16 | CK85: 0.07 | CL85: 0 | CM85: 0.05 | CN85: 0.12 | CO85: 1.44 | CP85: 1.33 | CQ85: 155 | CR85: 19 | CS85: 392 | CT85: 161 | CU85: 79 | CV85: 32 | CW85: 122 | CX85: 46 | CY85: 0.97 | CZ85: 0.27 | DA85: 0
A86: TRUE | B86: TRUE | E86: 444765 | F86: 0 | G86: 0 | H86: 0 | I86: 0 | J86: 0 | K86: 0 | L86: 2 | M86: 2.2 | O86: 0 | P86: Sepp | Q86: 0 | R86: 85 | S86: FALSE | V86: 50 | W86: 444765.jpg | X86: 3.5 | Y86: FALSE | Z86: van den Berg | AA86: 0.7 | AB86: FALSE | AD86: a | AE86: 4 | AF86: 94 | AG86: 113 | AH86: 0 | AI86: 0 | AJ86: 0 | AK86: 0 | AL86: 0 | AM86: 22.6 | AN86: Van den Berg | AS86: FALSE | AT86: p444765 | AU86: 2761 | AV86: 0 | AW86: 3 | AX86: 8 | AY86: 41 | AZ86: 0 | BA86: 0 | BB86: 0 | BC86: 2 | BD86: 0 | BE86: 0 | BF86: 3 | BG86: 435 | BH86: 659 | BI86: 98 | BJ86: 305 | BK86: 106.3 | BL86: 0 | BM86: 0 | BN86: 0 | BO86: 0 | BP86: 30 | BQ86: 3.36 | BR86: 1.45 | BS86: 4.81 | BT86: 41.59 | CC86: 58 | CD86: 25 | CE86: 239 | CF86: 76 | CG86: 97 | CH86: 13 | CI86: 115 | CJ86: 34 | CK86: 0.11 | CL86: 0 | CM86: 0.05 | CN86: 0.16 | CO86: 1.36 | CP86: 1.34 | CQ86: 290 | CR86: 55 | CS86: 268 | CT86: 134 | CU86: 103 | CV86: 42 | CW86: 222 | CX86: 79 | CY86: 0.98 | CZ86: 0.26 | DA86: 0
A87: TRUE | B87: TRUE | E87: 249231 | F87: 0 | G87: 0 | H87: 0 | I87: 0 | J87: 0 | K87: 0 | L87: 3 | M87: 2 | O87: 0 | P87: Keane | Q87: 0 | R87: 86 | S87: FALSE | V87: 55 | W87: 249231.jpg | X87: 3.2 | Y87: FALSE | Z87: Lewis-Potter | AA87: 0.8 | AB87: FALSE | AD87: a | AE87: 4 | AF87: 94 | AG87: 115 | AH87: 0 | AI87: 0 | AJ87: 0 | AK87: 0 | AL87: 0 | AM87: 20.9 | AN87: Lewis-Potter | AS87: FALSE | AT87: p249231 | AU87: 1960 | AV87: 3 | AW87: 4 | AX87: 9 | AY87: 32 | AZ87: 0 | BA87: 0 | BB87: 0 | BC87: 1 | BD87: 0 | BE87: 0 | BF87: 5 | BG87: 356 | BH87: 378.2 | BI87: 332.2 | BJ87: 353 | BK87: 106.4 | BL87: 0 | BM87: 0 | BN87: 0 | BO87: 0 | BP87: 22 | BQ87: 3.01 | BR87: 2.51 | BS87: 5.52 | BT87: 33.74 | BW87: 1 | CC87: 159 | CD87: 63 | CE87: 106 | CF87: 76 | CG87: 75 | CH87: 46 | CI87: 114 | CJ87: 64 | CK87: 0.14 | CL87: 0 | CM87: 0.12 | CN87: 0.26 | CO87: 1.55 | CP87: 1.47 | CQ87: 151 | CR87: 94 | CS87: 388 | CT87: 137 | CU87: 148 | CV87: 58 | CW87: 215 | CX87: 71 | CY87: 1.01 | CZ87: 0.41 | DA87: 0
A88: TRUE | B88: TRUE | E88: 191866 | F88: 0 | G88: 0 | H88: 0 | I88: 0 | J88: 0 | K88: 0 | L88: 2 | M88: 1.7 | O88: 0 | P88: Kristoffer | Q88: 0 | R88: 87 | S88: FALSE | V88: 45 | W88: 191866.jpg | X88: 2.8 | Y88: FALSE | Z88: Ajer | AA88: 0.5 | AB88: FALSE | AD88: a | AE88: 4 | AF88: 94 | AG88: 76 | AH88: 0 | AI88: 0 | AJ88: 0 | AK88: 0 | AL88: 0 | AM88: 16.9 | AN88: Ajer | AS88: FALSE | AT88: p191866 | AU88: 1805 | AV88: 0 | AW88: 2 | AX88: 5 | AY88: 32 | AZ88: 0 | BA88: 0 | BB88: 0 | BC88: 4 | BD88: 0 | BE88: 0 | BF88: 1 | BG88: 211 | BH88: 401.4 | BI88: 59.1 | BJ88: 165 | BK88: 62.7 | BL88: 0 | BM88: 0 | BN88: 0 | BO88: 0 | BP88: 20 | BQ88: 0.69 | BR88: 0.73 | BS88: 1.42 | BT88: 31.51 | CC88: 152 | CD88: 62 | CE88: 278 | CF88: 94 | CG88: 182 | CH88: 49 | CI88: 216 | CJ88: 70 | CK88: 0.03 | CL88: 0 | CM88: 0.04 | CN88: 0.07 | CO88: 1.57 | CP88: 1.6 | CQ88: 398 | CR88: 88 | CS88: 97 | CT88: 62 | CU88: 189 | CV88: 77 | CW88: 255 | CX88: 94 | CY88: 1 | CZ88: 0.25 | DA88: 0
A89: TRUE | B89: TRUE | E89: 607464 | F89: 0 | G89: 0 | H89: 0 | I89: 0 | J89: 0 | K89: 0 | L89: 2 | M89: 1.7 | O89: 0 | P89: Michael | Q89: 0 | R89: 88 | S89: FALSE | V89: 45 | W89: 607464.jpg | X89: 3.1 | Y89: FALSE | Z89: Kayode | AA89: 5.6 | AB89: FALSE | AD89: a | AE89: 4 | AF89: 94 | AG89: 113 | AH89: 0 | AI89: 0 | AJ89: 0 | AK89: 0 | AL89: 0 | AM89: 25.1 | AN89: Kayode | AS89: FALSE | AT89: p607464 | AU89: 3258 | AV89: 1 | AW89: 2 | AX89: 10 | AY89: 49 | AZ89: 1 | BA89: 0 | BB89: 0 | BC89: 8 | BD89: 0 | BE89: 0 | BF89: 9 | BG89: 494 | BH89: 613.8 | BI89: 470.2 | BJ89: 130 | BK89: 121.7 | BL89: 0 | BM89: 0 | BN89: 0 | BO89: 0 | BP89: 37 | BQ89: 1.28 | BR89: 2.89 | BS89: 4.17 | BT89: 52.65 | CC89: 71 | CD89: 30 | CE89: 55 | CF89: 8 | CG89: 207 | CH89: 57 | CI89: 84 | CJ89: 21 | CK89: 0.04 | CL89: 0 | CM89: 0.08 | CN89: 0.12 | CO89: 1.45 | CP89: 1.35 | CQ89: 485 | CR89: 136 | CS89: 184 | CT89: 110 | CU89: 157 | CV89: 64 | CW89: 71 | CX89: 28 | CY89: 1.02 | CZ89: 0.28 | DA89: 0
A90: TRUE | B90: TRUE | E90: 194010 | F90: 0 | G90: 0 | H90: 0 | I90: 0 | J90: 0 | K90: 0 | L90: 2 | M90: 1.7 | O90: 0 | P90: Rico | Q90: 0 | R90: 89 | S90: FALSE | V90: 45 | W90: 194010.jpg | X90: 2.1 | Y90: FALSE | Z90: Henry | AA90: 0.2 | AB90: FALSE | AD90: a | AE90: 4 | AF90: 94 | AG90: 52 | AH90: 0 | AI90: 0 | AJ90: 0 | AK90: 0 | AL90: 0 | AM90: 11.6 | AN90: Henry | AS90: FALSE | AT90: p194010 | AU90: 1322 | AV90: 0 | AW90: 2 | AX90: 4 | AY90: 22 | AZ90: 0 | BA90: 0 | BB90: 0 | BC90: 2 | BD90: 0 | BE90: 0 | BF90: 0 | BG90: 144 | BH90: 151.6 | BI90: 82 | BJ90: 35 | BK90: 26.9 | BL90: 0 | BM90: 0 | BN90: 0 | BO90: 0 | BP90: 14 | BQ90: 0.18 | BR90: 0.54 | BS90: 0.72 | BT90: 23.91 | CC90: 275 | CD90: 102 | CE90: 254 | CF90: 84 | CG90: 292 | CH90: 98 | CI90: 299 | CJ90: 101 | CK90: 0.01 | CL90: 0 | CM90: 0.04 | CN90: 0.05 | CO90: 1.63 | CP90: 1.5 | CQ90: 399 | CR90: 89 | CS90: 98 | CT90: 63 | CU90: 274 | CV90: 104 | CW90: 347 | CX90: 121 | CY90: 0.95 | CZ90: 0.27 | DA90: 0
A91: TRUE | B91: TRUE | E91: 472713 | F91: 0 | G91: 0 | H91: 0 | I91: 0 | J91: 0 | K91: 0 | L91: 2 | M91: 1.7 | O91: 0 | P91: Aaron | Q91: 0 | R91: 90 | S91: FALSE | V91: 45 | W91: 472713.jpg | X91: 1.8 | Y91: FALSE | Z91: Hickey | AA91: 0.1 | AB91: FALSE | AD91: a | AE91: 4 | AF91: 94 | AG91: 37 | AH91: 0 | AI91: 0 | AJ91: 0 | AK91: 0 | AL91: 0 | AM91: 8.2 | AN91: Hickey | AS91: FALSE | AT91: p472713 | AU91: 679 | AV91: 0 | AW91: 0 | AX91: 2 | AY91: 9 | AZ91: 0 | BA91: 0 | BB91: 0 | BC91: 1 | BD91: 0 | BE91: 0 | BF91: 0 | BG91: 105 | BH91: 101.4 | BI91: 17.1 | BJ91: 43 | BK91: 16 | BL91: 0 | BM91: 0 | BN91: 0 | BO91: 0 | BP91: 8 | BQ91: 0.44 | BR91: 0.17 | BS91: 0.61 | BT91: 9.03 | CC91: 304 | CD91: 109 | CE91: 328 | CF91: 114 | CG91: 281 | CH91: 91 | CI91: 320 | CJ91: 109 | CK91: 0.06 | CL91: 0 | CM91: 0.02 | CN91: 0.08 | CO91: 1.2 | CP91: 1.19 | CQ91: 439 | CR91: 119 | CS91: 138 | CT91: 93 | CU91: 301 | CV91: 112 | CW91: 460 | CX91: 159 | CY91: 1.06 | CZ91: 0.27 | DA91: 0
A92: TRUE | B92: TRUE | E92: 231065 | F92: 0 | G92: 0 | H92: 0 | I92: 0 | J92: 0 | K92: 0 | L92: 2 | M92: 1.7 | O92: 0 | P92: Ethan | Q92: 0 | R92: 91 | S92: FALSE | V92: 45 | W92: 231065.jpg | X92: 3.5 | Y92: FALSE | Z92: Pinnock | AA92: 0.1 | AB92: FALSE | AD92: a | AE92: 4 | AF92: 94 | AG92: 14 | AH92: 0 | AI92: 0 | AJ92: 0 | AK92: 0 | AL92: 0 | AM92: 3.1 | AN92: Pinnock | AS92: FALSE | AT92: p231065 | AU92: 318 | AV92: 0 | AW92: 0 | AX92: 1 | AY92: 5 | AZ92: 1 | BA92: 0 | BB92: 0 | BC92: 1 | BD92: 0 | BE92: 0 | BF92: 2 | BG92: 53 | BH92: 88.6 | BI92: 1.2 | BJ92: 33 | BK92: 12.3 | BL92: 0 | BM92: 0 | BN92: 0 | BO92: 0 | BP92: 4 | BQ92: 0.01 | BR92: 0.06 | BS92: 0.07 | BT92: 3.7 | CC92: 310 | CD92: 113 | CE92: 370 | CF92: 129 | CG92: 295 | CH92: 99 | CI92: 328 | CJ92: 112 | CK92: 0 | CL92: 0 | CM92: 0.02 | CN92: 0.02 | CO92: 1.05 | CP92: 1.42 | CQ92: 414 | CR92: 101 | CS92: 113 | CT92: 75 | CU92: 99 | CV92: 39 | CW92: 436 | CX92: 153 | CY92: 1.13 | CZ92: 0.28 | DA92: 0
A93: TRUE | B93: TRUE | E93: 570241 | F93: 0 | G93: 0 | H93: 0 | I93: 0 | J93: 0 | K93: 0 | L93: 2 | M93: 1.7 | O93: 0 | P93: Kim | Q93: 0 | R93: 92 | S93: FALSE | V93: 45 | W93: 570241.jpg | X93: 0 | Y93: FALSE | Z93: Ji-soo | AA93: 0.1 | AB93: FALSE | AD93: a | AE93: 4 | AF93: 94 | AG93: 0 | AH93: 0 | AI93: 0 | AJ93: 0 | AK93: 0 | AL93: 0 | AM93: 0 | AN93: Ji-soo | AS93: FALSE | AT93: p570241 | AU93: 0 | AV93: 0 | AW93: 0 | AX93: 0 | AY93: 0 | AZ93: 0 | BA93: 0 | BB93: 0 | BC93: 0 | BD93: 0 | BE93: 0 | BF93: 0 | BG93: 0 | BH93: 0 | BI93: 0 | BJ93: 0 | BK93: 0 | BL93: 0 | BM93: 0 | BN93: 0 | BO93: 0 | BP93: 0 | BQ93: 0 | BR93: 0 | BS93: 0 | BT93: 0 | CC93: 482 | CD93: 177 | CE93: 478 | CF93: 177 | CG93: 469 | CH93: 177 | CI93: 484 | CJ93: 177 | CK93: 0 | CL93: 0 | CM93: 0 | CN93: 0 | CO93: 0 | CP93: 0 | CQ93: 472 | CR93: 130 | CS93: 171 | CT93: 104 | CU93: 486 | CV93: 177 | CW93: 503 | CX93: 172 | CY93: 0 | CZ93: 0 | DA93: 0
A94: TRUE | B94: TRUE | E94: 513086 | F94: 0 | G94: 0 | H94: 0 | I94: 0 | J94: 0 | K94: 0 | L94: 2 | M94: 1.7 | O94: 0 | P94: Jannik | Q94: 0 | R94: 93 | S94: FALSE | V94: 45 | W94: 513086.jpg | X94: 0 | Y94: FALSE | Z94: Schuster | AA94: 0.1 | AB94: FALSE | AD94: a | AE94: 4 | AF94: 94 | AG94: 0 | AH94: 0 | AI94: 0 | AJ94: 0 | AK94: 0 | AL94: 0 | AM94: 0 | AN94: Schuster | AS94: FALSE | AT94: p513086 | AU94: 0 | AV94: 0 | AW94: 0 | AX94: 0 | AY94: 0 | AZ94: 0 | BA94: 0 | BB94: 0 | BC94: 0 | BD94: 0 | BE94: 0 | BF94: 0 | BG94: 0 | BH94: 0 | BI94: 0 | BJ94: 0 | BK94: 0 | BL94: 0 | BM94: 0 | BN94: 0 | BO94: 0 | BP94: 0 | BQ94: 0 | BR94: 0 | BS94: 0 | BT94: 0 | CC94: 472 | CD94: 175 | CE94: 467 | CF94: 175 | CG94: 455 | CH94: 174 | CI94: 474 | CJ94: 175 | CK94: 0 | CL94: 0 | CM94: 0 | CN94: 0 | CO94: 0 | CP94: 0 | CQ94: 455 | CR94: 124 | CS94: 154 | CT94: 98 | CU94: 477 | CV94: 175 | CW94: 405 | CX94: 144 | CY94: 0 | CZ94: 0 | DA94: 0
A95: TRUE | B95: TRUE | E95: 513418 | F95: 0 | G95: 0 | H95: 0 | I95: 0 | J95: 0 | K95: 0 | L95: 3 | M95: 2.1 | O95: 0 | P95: Kevin | Q95: 0 | R95: 94 | S95: FALSE | V95: 60 | W95: 513418.jpg | X95: 3.6 | Y95: FALSE | Z95: Schade | AA95: 2.4 | AB95: FALSE | AD95: a | AE95: 4 | AF95: 94 | AG95: 125 | AH95: 0 | AI95: 0 | AJ95: 0 | AK95: 0 | AL95: 0 | AM95: 20.8 | AN95: Schade | AS95: FALSE | AT95: p513418 | AU95: 2744 | AV95: 8 | AW95: 5 | AX95: 11 | AY95: 34 | AZ95: 0 | BA95: 0 | BB95: 1 | BC95: 6 | BD95: 1 | BE95: 0 | BF95: 5 | BG95: 385 | BH95: 536.8 | BI95: 380.1 | BJ95: 821 | BK95: 172.8 | BL95: 0 | BM95: 0 | BN95: 0 | BO95: 0 | BP95: 32 | BQ95: 12.08 | BR95: 2.05 | BS95: 14.13 | BT95: 40.05 | BY95: 2 | CC95: 100 | CD95: 31 | CE95: 89 | CF95: 66 | CG95: 12 | CH95: 7 | CI95: 33 | CJ95: 25 | CK95: 0.4 | CL95: 0 | CM95: 0.07 | CN95: 0.47 | CO95: 1.31 | CP95: 1.12 | CQ95: 100 | CR95: 65 | CS95: 494 | CT95: 200 | CU95: 94 | CV95: 40 | CW95: 119 | CX95: 38 | CY95: 1.05 | CZ95: 0.36 | DA95: 0
A96: TRUE | B96: TRUE | E96: 533463 | F96: 0 | G96: 0 | H96: 0 | I96: 0 | J96: 0 | K96: 0 | L96: 3 | M96: 2.3 | O96: 0 | P96: Dango | Q96: 0 | R96: 95 | S96: FALSE | V96: 65 | W96: 533463.jpg | X96: 4.2 | Y96: FALSE | Z96: Ouattara | AA96: 1.8 | AB96: FALSE | AD96: a | AE96: 4 | AF96: 94 | AG96: 136 | AH96: 0 | AI96: 0 | AJ96: 0 | AK96: 0 | AL96: 0 | AM96: 20.9 | AN96: O.Dango | AS96: FALSE | AT96: p533463 | AU96: 2271 | AV96: 7 | AW96: 8 | AX96: 6 | AY96: 35 | AZ96: 0 | BA96: 0 | BB96: 0 | BC96: 5 | BD96: 0 | BE96: 0 | BF96: 16 | BG96: 429 | BH96: 509.8 | BI96: 422.8 | BJ96: 702 | BK96: 162.8 | BL96: 0 | BM96: 0 | BN96: 0 | BO96: 0 | BP96: 25 | BQ96: 7.94 | BR96: 4.12 | BS96: 12.06 | BT96: 34.75 | BU96: 8 | CC96: 112 | CD96: 38 | CE96: 65 | CF96: 50 | CG96: 23 | CH96: 10 | CI96: 42 | CJ96: 29 | CK96: 0.31 | CL96: 0 | CM96: 0.16 | CN96: 0.47 | CO96: 1.38 | CP96: 1.39 | CQ96: 53 | CR96: 37 | CS96: 526 | CT96: 225 | CU96: 44 | CV96: 20 | CW96: 142 | CX96: 43 | CY96: 0.99 | CZ96: 0.24 | DA96: 0
A97: TRUE | B97: TRUE | E97: 440089 | F97: 0 | G97: 0 | H97: 0 | I97: 0 | J97: 0 | K97: 0 | L97: 3 | M97: 2 | O97: 0 | P97: Mikkel | Q97: 0 | R97: 96 | S97: FALSE | V97: 55 | W97: 440089.jpg | X97: 3.4 | Y97: FALSE | Z97: Damsgaard | AA97: 0.7 | AB97: FALSE | AD97: a | AE97: 4 | AF97: 94 | AG97: 113 | AH97: 0 | AI97: 0 | AJ97: 0 | AK97: 0 | AL97: 0 | AM97: 20.5 | AN97: Damsgaard | AS97: FALSE | AT97: p440089 | AU97: 2046 | AV97: 4 | AW97: 4 | AX97: 5 | AY97: 32 | AZ97: 0 | BA97: 0 | BB97: 0 | BC97: 0 | BD97: 0 | BE97: 0 | BF97: 9 | BG97: 467 | BH97: 530.6 | BI97: 691.3 | BJ97: 326 | BK97: 155 | BL97: 0 | BM97: 0 | BN97: 0 | BO97: 0 | BP97: 24 | BQ97: 2.61 | BR97: 5.43 | BS97: 8.04 | BT97: 31.55 | BU97: 6 | BW97: 3 | CC97: 106 | CD97: 34 | CE97: 26 | CF97: 25 | CG97: 85 | CH97: 53 | CI97: 49 | CJ97: 31 | CK97: 0.11 | CL97: 0 | CM97: 0.24 | CN97: 0.35 | CO97: 1.39 | CP97: 1.41 | CQ97: 159 | CR97: 100 | CS97: 396 | CT97: 143 | CU97: 116 | CV97: 46 | CW97: 223 | CX97: 75 | CY97: 1.06 | CZ97: 0.22 | DA97: 0
A98: TRUE | B98: TRUE | E98: 207283 | F98: 0 | G98: 0 | H98: 0 | I98: 0 | J98: 0 | K98: 0 | L98: 3 | M98: 2 | O98: 0 | P98: Mathias | Q98: 0 | R98: 97 | S98: FALSE | V98: 55 | W98: 207283.jpg | X98: 2.7 | Y98: FALSE | Z98: Jensen | AA98: 0.1 | AB98: FALSE | AD98: a | AE98: 4 | AF98: 94 | AG98: 98 | AH98: 0 | AI98: 0 | AJ98: 0 | AK98: 0 | AL98: 0 | AM98: 17.8 | AN98: Jensen | AS98: FALSE | AT98: p207283 | AU98: 2239 | AV98: 3 | AW98: 2 | AX98: 9 | AY98: 33 | AZ98: 0 | BA98: 0 | BB98: 0 | BC98: 3 | BD98: 0 | BE98: 0 | BF98: 1 | BG98: 465 | BH98: 435.6 | BI98: 632.7 | BJ98: 201 | BK98: 126.9 | BL98: 0 | BM98: 0 | BN98: 0 | BO98: 0 | BP98: 26 | BQ98: 2.21 | BR98: 6.06 | BS98: 8.27 | BT98: 35.72 | BU98: 5 | BW98: 2 | BY98: 3 | CC98: 140 | CD98: 52 | CE98: 29 | CF98: 28 | CG98: 155 | CH98: 84 | CI98: 77 | CJ98: 48 | CK98: 0.09 | CL98: 0 | CM98: 0.24 | CN98: 0.33 | CO98: 1.44 | CP98: 1.33 | CQ98: 135 | CR98: 84 | CS98: 372 | CT98: 127 | CU98: 209 | CV98: 81 | CW98: 410 | CX98: 154 | CY98: 1.05 | CZ98: 0.36 | DA98: 0
A99: TRUE | B99: TRUE | E99: 204580 | F99: 0 | G99: 0 | H99: 0 | I99: 0 | J99: 0 | K99: 0 | L99: 3 | M99: 1.5 | O99: 0 | P99: Vitaly | Q99: 0 | R99: 98 | S99: FALSE | V99: 50 | W99: 204580.jpg | X99: 3 | Y99: FALSE | Z99: Janelt | AA99: 0.1 | AB99: FALSE | AD99: a | AE99: 4 | AF99: 94 | AG99: 74 | AH99: 0 | AI99: 0 | AJ99: 0 | AK99: 0 | AL99: 0 | AM99: 14.8 | AN99: Janelt | AS99: FALSE | AT99: p204580 | AU99: 1434 | AV99: 1 | AW99: 4 | AX99: 5 | AY99: 21 | AZ99: 0 | BA99: 0 | BB99: 0 | BC99: 8 | BD99: 0 | BE99: 0 | BF99: 6 | BG99: 334 | BH99: 350.4 | BI99: 351.8 | BJ99: 97 | BK99: 79 | BL99: 0 | BM99: 0 | BN99: 0 | BO99: 0 | BP99: 15 | BQ99: 0.82 | BR99: 2.27 | BS99: 3.09 | BT99: 26.62 | BU99: 7 | CC99: 172 | CD99: 69 | CE99: 99 | CF99: 72 | CG99: 234 | CH99: 126 | CI99: 176 | CJ99: 85 | CK99: 0.05 | CL99: 0 | CM99: 0.14 | CN99: 0.19 | CO99: 1.67 | CP99: 1.32 | CQ99: 247 | CR99: 151 | CS99: 225 | CT99: 45 | CU99: 169 | CV99: 63 | CW99: 406 | CX99: 152 | CY99: 0.94 | CZ99: 0.31 | DA99: 0
A100: TRUE | B100: TRUE | C100: 75 | E100: 543295 | F100: 0 | G100: 0 | H100: 0 | I100: 0 | J100: 0 | K100: 0 | L100: 3 | M100: 1.1 | O100: 0 | P100: Antoni | Q100: 0 | R100: 99 | S100: FALSE | T100: Knee injury - 75% chance of playing | U100: 2026-07-23T12:01:23.384798Z | V100: 50 | W100: 543295.jpg | X100: 1 | Y100: FALSE | Z100: Milambo | AA100: 0 | AB100: FALSE | AD100: d | AE100: 4 | AF100: 94 | AG100: 1 | AH100: 0 | AI100: 0 | AJ100: 0 | AK100: 0 | AL100: 0 | AM100: 0.2 | AN100: Milambo | AS100: FALSE | AT100: p543295 | AU100: 45 | AV100: 0 | AW100: 0 | AX100: 0 | AY100: 3 | AZ100: 0 | BA100: 0 | BB100: 0 | BC100: 0 | BD100: 0 | BE100: 0 | BF100: 0 | BG100: 5 | BH100: 4 | BI100: 1.8 | BJ100: 0 | BK100: 0.6 | BL100: 0 | BM100: 0 | BN100: 0 | BO100: 0 | BP100: 1 | BQ100: 0 | BR100: 0.01 | BS100: 0.01 | BT100: 1.49 | CB100: https://www.brentfordfc.com/en/news/article/first-team-brentford-v-crystal-palace-premier-league-team-news?utm_source=premier-league-web&utm_medium=referral&utm_campaign=pl-referral-always-on&utm_term=injuries&utm_content=club-injury-article | CC100: 380 | CD100: 176 | CE100: 368 | CF100: 184 | CG100: 526 | CH100: 226 | CI100: 388 | CJ100: 182 | CK100: 0 | CL100: 0 | CM100: 0.02 | CN100: 0.02 | CO100: 2.98 | CP100: 6 | CQ100: 345 | CR100: 205 | CS100: 323 | CT100: 99 | CU100: 380 | CV100: 176 | CW100: 556 | CX100: 245 | CY100: 2 | CZ100: 0 | DA100: 0
...

Sheet OLD
A1: can_transact | B1: can_select | C1: chance_of_playing_next_round | D1: chance_of_playing_this_round | E1: code | F1: cost_change_event | G1: cost_change_event_fall | H1: cost_change_start | I1: cost_change_start_fall | J1: dreamteam_count | K1: element_type | L1: ep_next | M1: ep_this | N1: event_points | O1: first_name | P1: form | Q1: id | R1: in_dreamteam | S1: news | T1: news_added | U1: now_cost | V1: photo | W1: points_per_game | X1: removed | Y1: second_name | Z1: selected_by_percent | AA1: special | AB1: squad_number | AC1: status | AD1: team | AE1: team_code | AF1: total_points | AG1: transfers_in | AH1: transfers_in_event | AI1: transfers_out | AJ1: transfers_out_event | AK1: value_form | AL1: value_season | AM1: web_name | AN1: known_name | AO1: region | AP1: team_join_date | AQ1: birth_date | AR1: has_temporary_code | AS1: opta_code | AT1: minutes | AU1: goals_scored | AV1: assists | AW1: clean_sheets | AX1: goals_conceded | AY1: own_goals | AZ1: penalties_saved | BA1: penalties_missed | BB1: yellow_cards | BC1: red_cards | BD1: saves | BE1: bonus | BF1: bps | BG1: influence | BH1: creativity | BI1: threat | BJ1: ict_index | BK1: clearances_blocks_interceptions | BL1: recoveries | BM1: tackles | BN1: defensive_contribution | BO1: starts | BP1: expected_goals | BQ1: expected_assists | BR1: expected_goal_involvements | BS1: expected_goals_conceded | BT1: corners_and_indirect_freekicks_order | BU1: corners_and_indirect_freekicks_text | BV1: direct_freekicks_order | BW1: direct_freekicks_text | BX1: penalties_order | BY1: penalties_text | BZ1: scout_risks | CA1: influence_rank | CB1: influence_rank_type | CC1: creativity_rank | CD1: creativity_rank_type | CE1: threat_rank | CF1: threat_rank_type | CG1: ict_index_rank | CH1: ict_index_rank_type | CI1: expected_goals_per_90 | CJ1: saves_per_90 | CK1: expected_assists_per_90 | CL1: expected_goal_involvements_per_90 | CM1: expected_goals_conceded_per_90 | CN1: goals_conceded_per_90 | CO1: now_cost_rank | CP1: now_cost_rank_type | CQ1: form_rank | CR1: form_rank_type | CS1: points_per_game_rank | CT1: points_per_game_rank_type | CU1: selected_rank | CV1: selected_rank_type | CW1: starts_per_90 | CX1: clean_sheets_per_90 | CY1: defensive_contribution_per_90
A2: TRUE | B2: FALSE | E2: 154561 | F2: 0 | G2: 0 | H2: 7 | I2: -7 | J2: 2 | K2: 1 | L2: 8.8 | M2: 6.2 | N2: 0 | O2: David | P2: 5.2 | Q2: =DA2 -> 1 | R2: TRUE | U2: 62 | V2: 154561.jpg | W2: 4.4 | X2: FALSE | Y2: Raya Martín | Z2: 36.4 | AA2: FALSE | AC2: a | AD2: 1 | AE2: 3 | AF2: 162 | AG2: 4930540 | AH2: 0 | AI2: 3003061 | AJ2: 0 | AK2: 0.8 | AL2: 26.1 | AM2: Raya | AO2: 200 | AP2: 45477 | AQ2: 34957 | AR2: FALSE | AS2: p154561 | AT2: 3330 | AU2: 0 | AV2: 0 | AW2: 19 | AX2: 26 | AY2: 0 | AZ2: 0 | BA2: 0 | BB2: 1 | BC2: 0 | BD2: 60 | BE2: 11 | BF2: 633 | BG2: 541.6 | BH2: 33.5 | BI2: 0 | BJ2: 57.5 | BK2: 37 | BL2: 304 | BM2: 1 | BN2: 0 | BO2: 37 | BP2: 0 | BQ2: 0.07 | BR2: 0.07 | BS2: 27.56 | CA2: 108 | CB2: 17 | CC2: 391 | CD2: 3 | CE2: 833 | CF2: 97 | CG2: 279 | CH2: 17 | CI2: 0 | CJ2: 1.62 | CK2: 0 | CL2: 0 | CM2: 0.74 | CN2: 0.7 | CO2: 72 | CP2: 1 | CQ2: 20 | CR2: 1 | CS2: 36 | CT2: 3 | CU2: 5 | CV2: 1 | CW2: 1 | CX2: 0.51 | CY2: 0 | CZ2: =O2&" "&Y2 -> David Raya Martín | DA2: =VLOOKUP(CZ2,[1]FINAL!$A$1:$AP$1000,MATCH("Element No.",[1]FINAL!$A$1:$AP$1,0),0) -> 1
A3: TRUE | B3: FALSE | E3: 109745 | F3: 0 | G3: 0 | H3: -5 | I3: 5 | J3: 0 | K3: 1 | L3: 1 | M3: 1.5 | N3: 2 | O3: Kepa | P3: 0.5 | Q3: =DA3 -> 2 | R3: FALSE | U3: 40 | V3: 109745.jpg | W3: 2 | X3: FALSE | Y3: Arrizabalaga Revuelta | Z3: 0.4 | AA3: FALSE | AC3: a | AD3: 1 | AE3: 3 | AF3: 2 | AG3: 23561 | AH3: 0 | AI3: 79865 | AJ3: 0 | AK3: 0.1 | AL3: 0.5 | AM3: Arrizabalaga | AO3: 200 | AP3: 45839 | AQ3: 34610 | AR3: FALSE | AS3: p109745 | AT3: 90 | AU3: 0 | AV3: 0 | AW3: 0 | AX3: 1 | AY3: 0 | AZ3: 0 | BA3: 0 | BB3: 0 | BC3: 0 | BD3: 2 | BE3: 0 | BF3: 11 | BG3: 19.8 | BH3: 0 | BI3: 0 | BJ3: 2 | BK3: 3 | BL3: 8 | BM3: 0 | BN3: 0 | BO3: 1 | BP3: 0 | BQ3: 0 | BR3: 0 | BS3: 0.98 | CA3: 464 | CB3: 38 | CC3: 572 | CD3: 55 | CE3: 541 | CF3: 40 | CG3: 489 | CH3: 38 | CI3: 0 | CJ3: 2 | CK3: 0 | CL3: 0 | CM3: 0.98 | CN3: 1 | CO3: 679 | CP3: 44 | CQ3: 326 | CR3: 25 | CS3: 343 | CT3: 35 | CU3: 287 | CV3: 37 | CW3: 1 | CX3: 0 | CY3: 0 | CZ3: =O3&" "&Y3 -> Kepa Arrizabalaga Revuelta | DA3: =VLOOKUP(CZ3,[1]FINAL!$A$1:$AP$1000,MATCH("Element No.",[1]FINAL!$A$1:$AP$1,0),0) -> 2
A4: TRUE | B4: FALSE | C4: 0 | D4: 0 | E4: 463748 | F4: 0 | G4: 0 | H4: 0 | I4: 0 | J4: 0 | K4: 1 | L4: 0 | M4: 0 | N4: 0 | O4: Karl | P4: 0 | Q4: =DA4 -> #N/A | R4: FALSE | S4: Has joined Werder Bremen on loan for the rest of the season. | T4: 2025-08-26T13:44:02.357864Z | U4: 40 | V4: 463748.jpg | W4: 0 | X4: FALSE | Y4: Hein | Z4: 0.2 | AA4: FALSE | AC4: u | AD4: 1 | AE4: 3 | AF4: 0 | AG4: 5545 | AH4: 0 | AI4: 48759 | AJ4: 0 | AK4: 0 | AL4: 0 | AM4: Hein | AO4: 67 | AP4: 44132 | AQ4: 37359 | AR4: FALSE | AS4: p463748 | AT4: 0 | AU4: 0 | AV4: 0 | AW4: 0 | AX4: 0 | AY4: 0 | AZ4: 0 | BA4: 0 | BB4: 0 | BC4: 0 | BD4: 0 | BE4: 0 | BF4: 0 | BG4: 0 | BH4: 0 | BI4: 0 | BJ4: 0 | BK4: 0 | BL4: 0 | BM4: 0 | BN4: 0 | BO4: 0 | BP4: 0 | BQ4: 0 | BR4: 0 | BS4: 0 | CA4: 599 | CB4: 76 | CC4: 590 | CD4: 65 | CE4: 559 | CF4: 50 | CG4: 602 | CH4: 76 | CI4: 0 | CJ4: 0 | CK4: 0 | CL4: 0 | CM4: 0 | CN4: 0 | CO4: 701 | CP4: 54 | CQ4: 488 | CR4: 68 | CS4: 610 | CT4: 76 | CU4: 385 | CV4: 55 | CW4: 0 | CX4: 0 | CY4: 0 | CZ4: =O4&" "&Y4 -> Karl Hein | DA4: =VLOOKUP(CZ4,[1]FINAL!$A$1:$AP$1000,MATCH("Element No.",[1]FINAL!$A$1:$AP$1,0),0) -> #N/A
A5: TRUE | B5: FALSE | E5: 551221 | F5: 0 | G5: 0 | H5: -1 | I5: 1 | J5: 0 | K5: 1 | L5: 1 | M5: 1 | N5: 0 | O5: Tommy | P5: 0 | Q5: =DA5 -> #N/A | R5: FALSE | U5: 39 | V5: 551221.jpg | W5: 0 | X5: FALSE | Y5: Setford | Z5: 0.2 | AA5: FALSE | AC5: a | AD5: 1 | AE5: 3 | AF5: 0 | AG5: 34587 | AH5: 0 | AI5: 36016 | AJ5: 0 | AK5: 0 | AL5: 0 | AM5: Setford | AO5: 241 | AP5: 45497 | AQ5: 38789 | AR5: FALSE | AS5: p551221 | AT5: 0 | AU5: 0 | AV5: 0 | AW5: 0 | AX5: 0 | AY5: 0 | AZ5: 0 | BA5: 0 | BB5: 0 | BC5: 0 | BD5: 0 | BE5: 0 | BF5: 0 | BG5: 0 | BH5: 0 | BI5: 0 | BJ5: 0 | BK5: 0 | BL5: 0 | BM5: 0 | BN5: 0 | BO5: 0 | BP5: 0 | BQ5: 0 | BR5: 0 | BS5: 0 | CA5: 572 | CB5: 62 | CC5: 558 | CD5: 46 | CE5: 527 | CF5: 31 | CG5: 575 | CH5: 62 | CI5: 0 | CJ5: 0 | CK5: 0 | CL5: 0 | CM5: 0 | CN5: 0 | CO5: 792 | CP5: 90 | CQ5: 455 | CR5: 52 | CS5: 583 | CT5: 62 | CU5: 375 | CV5: 53 | CW5: 0 | CX5: 0 | CY5: 0 | CZ5: =O5&" "&Y5 -> Tommy Setford | DA5: =VLOOKUP(CZ5,[1]FINAL!$A$1:$AP$1000,MATCH("Element No.",[1]FINAL!$A$1:$AP$1,0),0) -> #N/A
A6: TRUE | B6: FALSE | C6: 100 | D6: 100 | E6: 226597 | F6: 0 | G6: 0 | H6: 13 | I6: -13 | J6: 5 | K6: 2 | L6: 8.8 | M6: 7 | N6: 1 | O6: Gabriel | P6: 6 | Q6: =DA6 -> 4 | R6: TRUE | T6: 2026-03-24T00:00:10.555559Z | U6: 73 | V6: 226597.jpg | W6: 6.5 | X6: FALSE | Y6: dos Santos Magalhães | Z6: 45.4 | AA6: FALSE | AC6: a | AD6: 1 | AE6: 3 | AF6: 209 | AG6: 9241680 | AH6: 0 | AI6: 6017049 | AJ6: 0 | AK6: 0.8 | AL6: 28.6 | AM6: Gabriel | AN6: Gabriel Magalhães | AO6: 30 | AP6: 44075 | AQ6: 35783 | AR6: FALSE | AS6: p226597 | AT6: 2750 | AU6: 3 | AV6: 5 | AW6: 18 | AX6: 20 | AY6: 0 | AZ6: 0 | BA6: 0 | BB6: 4 | BC6: 0 | BD6: 0 | BE6: 30 | BF6: 724 | BG6: 824 | BH6: 128.5 | BI6: 298 | BJ6: 125 | BK6: 239 | BL6: 64 | BM6: 38 | BN6: 277 | BO6: 30 | BP6: 2.94 | BQ6: 1.75 | BR6: 4.69 | BS6: 22.01 | CA6: 27 | CB6: 9 | CC6: 274 | CD6: 77 | CE6: 116 | CF6: 18 | CG6: 91 | CH6: 20 | CI6: 0.1 | CJ6: 0 | CK6: 0.06 | CL6: 0.16 | CM6: 0.72 | CN6: 0.65 | CO6: 25 | CP6: 1 | CQ6: 11 | CR6: 3 | CS6: 4 | CT6: 1 | CU6: 4 | CV6: 1 | CW6: 0.98 | CX6: 0.59 | CY6: 9.07 | CZ6: =O6&" "&Y6 -> Gabriel dos Santos Magalhães | DA6: =VLOOKUP(CZ6,[1]FINAL!$A$1:$AP$1000,MATCH("Element No.",[1]FINAL!$A$1:$AP$1,0),0) -> 4
A7: TRUE | B7: FALSE | C7: 100 | D7: 100 | E7: 462424 | F7: 0 | G7: 0 | H7: 3 | I7: -3 | J7: 2 | K7: 2 | L7: 7.5 | M7: 5.8 | N7: 0 | O7: William | P7: 4.8 | Q7: =DA7 -> 6 | R7: FALSE | T7: 2026-03-23T13:00:10.244912Z | U7: 63 | V7: 462424.jpg | W7: 4.4 | X7: FALSE | Y7: Saliba | Z7: 17.1 | AA7: FALSE | AC7: a | AD7: 1 | AE7: 3 | AF7: 137 | AG7: 2702830 | AH7: 0 | AI7: 2551293 | AJ7: 0 | AK7: 0.8 | AL7: 21.7 | AM7: Saliba | AO7: 73 | AP7: 43671 | AQ7: 36974 | AR7: FALSE | AS7: p462424 | AT7: 2614 | AU7: 1 | AV7: 0 | AW7: 15 | AX7: 20 | AY7: 0 | AZ7: 0 | BA7: 0 | BB7: 2 | BC7: 0 | BD7: 0 | BE7: 12 | BF7: 581 | BG7: 552.6 | BH7: 201 | BI7: 90 | BJ7: 84.3 | BK7: 158 | BL7: 113 | BM7: 35 | BN7: 193 | BO7: 30 | BP7: 0.88 | BQ7: 1.21 | BR7: 2.09 | BS7: 20.41 | CA7: 104 | CB7: 48 | CC7: 205 | CD7: 51 | CE7: 302 | CF7: 91 | CG7: 192 | CH7: 66 | CI7: 0.03 | CJ7: 0 | CK7: 0.04 | CL7: 0.07 | CM7: 0.7 | CN7: 0.69 | CO7: 69 | CP7: 2 | CQ7: 37 | CR7: 13 | CS7: 37 | CT7: 13 | CU7: 19 | CV7: 7 | CW7: 1.03 | CX7: 0.52 | CY7: 6.64 | CZ7: =O7&" "&Y7 -> William Saliba | DA7: =VLOOKUP(CZ7,[1]FINAL!$A$1:$AP$1000,MATCH("Element No.",[1]FINAL!$A$1:$AP$1,0),0) -> 6
A8: TRUE | B8: FALSE | C8: 100 | D8: 100 | E8: 466075 | F8: 0 | G8: 0 | H8: 1 | I8: -1 | J8: 2 | K8: 2 | L8: 4.8 | M8: 5 | N8: 1 | O8: Riccardo | P8: 4 | Q8: =DA8 -> 8 | R8: FALSE | T8: 2026-05-11T00:00:10.879576Z | U8: 56 | V8: 466075.jpg | W8: 4.2 | X8: FALSE | Y8: Calafiori | Z8: 6 | AA8: FALSE | AC8: a | AD8: 1 | AE8: 3 | AF8: 109 | AG8: 2701773 | AH8: 0 | AI8: 2532675 | AJ8: 0 | AK8: 0.7 | AL8: 19.5 | AM8: Calafiori | AO8: 106 | AP8: 45502 | AQ8: 37395 | AR8: FALSE | AS8: p466075 | AT8: 1697 | AU8: 1 | AV8: 2 | AW8: 13 | AX8: 8 | AY8: 0 | AZ8: 0 | BA8: 0 | BB8: 5 | BC8: 0 | BD8: 0 | BE8: 6 | BF8: 389 | BG8: 283 | BH8: 182.3 | BI8: 313 | BJ8: 77.9 | BK8: 70 | BL8: 74 | BM8: 32 | BN8: 102 | BO8: 22 | BP8: 3.36 | BQ8: 0.76 | BR8: 4.12 | BS8: 9.72 | CA8: 257 | CB8: 101 | CC8: 223 | CD8: 56 | CE8: 107 | CF8: 14 | CG8: 211 | CH8: 74 | CI8: 0.18 | CJ8: 0 | CK8: 0.04 | CL8: 0.22 | CM8: 0.52 | CN8: 0.42 | CO8: 131 | CP8: 13 | CQ8: 75 | CR8: 23 | CS8: 46 | CT8: 16 | CU8: 69 | CV8: 22 | CW8: 1.17 | CX8: 0.69 | CY8: 5.41 | CZ8: =O8&" "&Y8 -> Riccardo Calafiori | DA8: =VLOOKUP(CZ8,[1]FINAL!$A$1:$AP$1000,MATCH("Element No.",[1]FINAL!$A$1:$AP$1,0),0) -> 8
A9: TRUE | B9: FALSE | C9: 25 | D9: 25 | E9: 445122 | F9: 0 | G9: 0 | H9: 5 | I9: -5 | J9: 3 | K9: 2 | L9: 0.2 | M9: 0.2 | N9: 0 | O9: Jurriën | P9: 0 | Q9: =DA9 -> 5 | R9: FALSE | S9: Lack of match fitness - 25% chance of playing | T9: 2026-03-23T13:00:10.259821Z | U9: 60 | V9: 445122.jpg | W9: 5 | X9: FALSE | Y9: Timber | Z9: 15.2 | AA9: FALSE | AC9: d | AD9: 1 | AE9: 3 | AF9: 149 | AG9: 6784707 | AH9: 0 | AI9: 5670508 | AJ9: 0 | AK9: 0 | AL9: 24.8 | AM9: J.Timber | AO9: 152 | AP9: 45121 | AQ9: 37059 | AR9: FALSE | AS9: p445122 | AT9: 2452 | AU9: 3 | AV9: 6 | AW9: 13 | AX9: 20 | AY9: 0 | AZ9: 0 | BA9: 0 | BB9: 5 | BC9: 0 | BD9: 0 | BE9: 9 | BF9: 532 | BG9: 499 | BH9: 402.6 | BI9: 352 | BJ9: 125.7 | BK9: 82 | BL9: 97 | BM9: 66 | BN9: 148 | BO9: 28 | BP9: 4.71 | BQ9: 1.53 | BR9: 6.24 | BS9: 17.45 | CA9: 132 | CB9: 58 | CC9: 89 | CD9: 22 | CE9: 90 | CF9: 10 | CG9: 90 | CH9: 19 | CI9: 0.17 | CJ9: 0 | CK9: 0.06 | CL9: 0.23 | CM9: 0.64 | CN9: 0.73 | CO9: 84 | CP9: 5 | CQ9: 822 | CR9: 269 | CS9: 13 | CT9: 3 | CU9: 23 | CV9: 8 | CW9: 1.03 | CX9: 0.48 | CY9: 5.43 | CZ9: =O9&" "&Y9 -> Jurriën Timber | DA9: =VLOOKUP(CZ9,[1]FINAL!$A$1:$AP$1000,MATCH("Element No.",[1]FINAL!$A$1:$AP$1,0),0) -> 5
A10: TRUE | B10: FALSE | C10: 0 | D10: 0 | E10: 440854 | F10: 0 | G10: 0 | H10: -1 | I10: 1 | J10: 0 | K10: 2 | L10: 0 | M10: 0 | N10: 0 | O10: Jakub | P10: 0 | Q10: =DA10 -> #N/A | R10: FALSE | S10: has joined Porto on loan for the rest of the season. | T10: 2025-09-02T13:37:25.929594Z | U10: 54 | V10: 440854.jpg | W10: 0 | X10: FALSE | Y10: Kiwior | Z10: 0 | AA10: FALSE | AC10: u | AD10: 1 | AE10: 3 | AF10: 0 | AG10: 1119 | AH10: 0 | AI10: 10955 | AJ10: 0 | AK10: 0 | AL10: 0 | AM10: Kiwior | AO10: 172 | AP10: 44949 | AQ10: 36571 | AR10: FALSE | AS10: p440854 | AT10: 0 | AU10: 0 | AV10: 0 | AW10: 0 | AX10: 0 | AY10: 0 | AZ10: 0 | BA10: 0 | BB10: 0 | BC10: 0 | BD10: 0 | BE10: 0 | BF10: 0 | BG10: 0 | BH10: 0 | BI10: 0 | BJ10: 0 | BK10: 0 | BL10: 0 | BM10: 0 | BN10: 0 | BO10: 0 | BP10: 0 | BQ10: 0 | BR10: 0 | BS10: 0 | CA10: 825 | CB10: 270 | CC10: 825 | CD10: 270 | CE10: 824 | CF10: 270 | CG10: 825 | CH10: 270 | CI10: 0 | CJ10: 0 | CK10: 0 | CL10: 0 | CM10: 0 | CN10: 0 | CO10: 165 | CP10: 20 | CQ10: 804 | CR10: 268 | CS10: 825 | CT10: 270 | CU10: 596 | CV10: 212 | CW10: 0 | CX10: 0 | CY10: 0 | CZ10: =O10&" "&Y10 -> Jakub Kiwior | DA10: =VLOOKUP(CZ10,[1]FINAL!$A$1:$AP$1000,MATCH("Element No.",[1]FINAL!$A$1:$AP$1,0),0) -> #N/A
A11: TRUE | B11: FALSE | E11: 499169 | F11: 0 | G11: 0 | H11: -5 | I11: 5 | J11: 0 | K11: 2 | L11: 4.5 | M11: 4.8 | N11: 2 | O11: Myles | P11: 3.8 | Q11: =DA11 -> 7 | R11: FALSE | U11: 50 | V11: 499169.jpg | W11: 1.4 | X11: FALSE | Y11: Lewis-Skelly | Z11: 1.9 | AA11: FALSE | AC11: a | AD11: 1 | AE11: 3 | AF11: 29 | AG11: 216990 | AH11: 0 | AI11: 478401 | AJ11: 0 | AK11: 0.8 | AL11: 5.8 | AM11: Lewis-Skelly | AO11: 241 | AP11: 44899 | AQ11: 38986 | AR11: FALSE | AS11: p499169 | AT11: 697 | AU11: 0 | AV11: 0 | AW11: 2 | AX11: 8 | AY11: 0 | AZ11: 0 | BA11: 0 | BB11: 3 | BC11: 0 | BD11: 0 | BE11: 0 | BF11: 110 | BG11: 73.2 | BH11: 74.6 | BI11: 29 | BJ11: 17.6 | BK11: 17 | BL11: 30 | BM11: 8 | BN11: 25 | BO11: 5 | BP11: 0.1 | BQ11: 0.2 | BR11: 0.3 | BS11: 9.01 | CA11: 410 | CB11: 153 | CC11: 336 | CD11: 115 | CE11: 383 | CF11: 133 | CG11: 403 | CH11: 144 | CI11: 0.01 | CJ11: 0 | CK11: 0.03 | CL11: 0.04 | CM11: 1.16 | CN11: 1.03 | CO11: 268 | CP11: 41 | CQ11: 80 | CR11: 27 | CS11: 436 | CT11: 159 | CU11: 139 | CV11: 55 | CW11: 0.65 | CX11: 0.26 | CY11: 3.23 | CZ11: =O11&" "&Y11 -> Myles Lewis-Skelly | DA11: =VLOOKUP(CZ11,[1]FINAL!$A$1:$AP$1000,MATCH("Element No.",[1]FINAL!$A$1:$AP$1,0),0) -> 7
A12: TRUE | B12: FALSE | C12: 0 | D12: 0 | E12: 198869 | F12: 0 | G12: 0 | H12: -4 | I12: 4 | J12: 1 | K12: 2 | L12: 0 | M12: 0 | N12: 0 | O12: Benjamin | P12: 1.8 | Q12: =DA12 -> 10 | R12: FALSE | S12: Knee injury - Expected back 24 May | T12: 2026-05-11T00:00:10.901815Z | U12: 51 | V12: 198869.jpg | W12: 3.8 | X12: FALSE | Y12: White | Z12: 0.5 | AA12: FALSE | AC12: i | AD12: 1 | AE12: 3 | AF12: 45 | AG12: 378865 | AH12: 0 | AI12: 434751 | AJ12: 0 | AK12: 0.4 | AL12: 8.8 | AM12: White | AO12: 241 | AP12: 44407 | AQ12: 35711 | AR12: FALSE | AS12: p198869 | AT12: 699 | AU12: 0 | AV12: 1 | AW12: 5 | AX12: 6 | AY12: 0 | AZ12: 0 | BA12: 0 | BB12: 0 | BC12: 0 | BD12: 0 | BE12: 3 | BF12: 181 | BG12: 154.8 | BH12: 133.4 | BI12: 54 | BJ12: 34.3 | BK12: 38 | BL12: 28 | BM12: 15 | BN12: 53 | BO12: 9 | BP12: 0.45 | BQ12: 0.69 | BR12: 1.14 | BS12: 8.68 | CA12: 344 | CB12: 130 | CC12: 267 | CD12: 73 | CE12: 344 | CF12: 113 | CG12: 355 | CH12: 118 | CI12: 0.06 | CJ12: 0 | CK12: 0.09 | CL12: 0.15 | CM12: 1.12 | CN12: 0.77 | CO12: 226 | CP12: 33 | CQ12: 206 | CR12: 72 | CS12: 81 | CT12: 29 | CU12: 269 | CV12: 100 | CW12: 1.16 | CX12: 0.64 | CY12: 6.82 | CZ12: =O12&" "&Y12 -> Benjamin White | DA12: =VLOOKUP(CZ12,[1]FINAL!$A$1:$AP$1000,MATCH("Element No.",[1]FINAL!$A$1:$AP$1,0),0) -> 10
A13: TRUE | B13: FALSE | E13: 563324 | F13: 0 | G13: 0 | H13: -3 | I13: 3 | J13: 0 | K13: 2 | L13: 1 | M13: 1 | N13: 0 | O13: Brayden | P13: 0 | Q13: =DA13 -> #N/A | R13: FALSE | U13: 37 | V13: 563324.jpg | W13: 0 | X13: FALSE | Y13: Clarke | Z13: 0.5 | AA13: FALSE | AC13: a | AD13: 1 | AE13: 3 | AF13: 0 | AG13: 65565 | AH13: 0 | AI13: 85106 | AJ13: 0 | AK13: 0 | AL13: 0 | AM13: Clarke | AR13: FALSE | AS13: p563324 | AT13: 0 | AU13: 0 | AV13: 0 | AW13: 0 | AX13: 0 | AY13: 0 | AZ13: 0 | BA13: 0 | BB13: 0 | BC13: 0 | BD13: 0 | BE13: 0 | BF13: 0 | BG13: 0 | BH13: 0 | BI13: 0 | BJ13: 0 | BK13: 0 | BL13: 0 | BM13: 0 | BN13: 0 | BO13: 0 | BP13: 0 | BQ13: 0 | BR13: 0 | BS13: 0 | CA13: 529 | CB13: 186 | CC13: 510 | CD13: 185 | CE13: 478 | CF13: 180 | CG13: 532 | CH13: 186 | CI13: 0 | CJ13: 0 | CK13: 0 | CL13: 0 | CM13: 0 | CN13: 0 | CO13: 838 | CP13: 267 | CQ13: 404 | CR13: 141 | CS13: 540 | CT13: 186 | CU13: 279 | CV13: 105 | CW13: 0 | CX13: 0 | CY13: 0 | CZ13: =O13&" "&Y13 -> Brayden Clarke | DA13: =VLOOKUP(CZ13,[1]FINAL!$A$1:$AP$1000,MATCH("Element No.",[1]FINAL!$A$1:$AP$1,0),0) -> #N/A
A14: TRUE | B14: FALSE | C14: 0 | D14: 0 | E14: 588793 | F14: 0 | G14: 0 | H14: -1 | I14: 1 | J14: 0 | K14: 2 | L14: 0 | M14: 0 | N14: 0 | O14: Maldini | P14: 0 | Q14: =DA14 -> #N/A | R14: FALSE | S14: has joined Morecambe on loan for the rest of the season. | T14: 2025-09-22T21:14:30.857843Z | U14: 39 | V14: 588793.jpg | W14: 0 | X14: FALSE | Y14: Kacurri | Z14: 0.1 | AA14: FALSE | AC14: u | AD14: 1 | AE14: 3 | AF14: 0 | AG14: 10218 | AH14: 0 | AI14: 22844 | AJ14: 0 | AK14: 0 | AL14: 0 | AM14: Kacurri | AR14: FALSE | AS14: p588793 | AT14: 0 | AU14: 0 | AV14: 0 | AW14: 0 | AX14: 0 | AY14: 0 | AZ14: 0 | BA14: 0 | BB14: 0 | BC14: 0 | BD14: 0 | BE14: 0 | BF14: 0 | BG14: 0 | BH14: 0 | BI14: 0 | BJ14: 0 | BK14: 0 | BL14: 0 | BM14: 0 | BN14: 0 | BO14: 0 | BP14: 0 | BQ14: 0 | BR14: 0 | BS14: 0 | CA14: 577 | CB14: 210 | CC14: 563 | CD14: 209 | CE14: 532 | CF14: 205 | CG14: 580 | CH14: 210 | CI14: 0 | CJ14: 0 | CK14: 0 | CL14: 0 | CM14: 0 | CN14: 0 | CO14: 798 | CP14: 232 | CQ14: 461 | CR14: 172 | CS14: 588 | CT14: 210 | CU14: 501 | CV14: 180 | CW14: 0 | CX14: 0 | CY14: 0 | CZ14: =O14&" "&Y14 -> Maldini Kacurri | DA14: =VLOOKUP(CZ14,[1]FINAL!$A$1:$AP$1000,MATCH("Element No.",[1]FINAL!$A$1:$AP$1,0),0) -> #N/A
A15: TRUE | B15: FALSE | E15: 499167 | F15: 0 | G15: 0 | H15: -3 | I15: 3 | J15: 0 | K15: 2 | L15: 1 | M15: 1 | N15: 0 | O15: Josh | P15: 0 | Q15: =DA15 -> #N/A | R15: FALSE | U15: 37 | V15: 499167.jpg | W15: 0 | X15: FALSE | Y15: Nichols | Z15: 0.2 | AA15: FALSE | AC15: a | AD15: 1 | AE15: 3 | AF15: 0 | AG15: 34995 | AH15: 0 | AI15: 35855 | AJ15: 0 | AK15: 0 | AL15: 0 | AM15: Nichols | AO15: 241 | AP15: 45497 | AQ15: 38924 | AR15: FALSE | AS15: p499167 | AT15: 0 | AU15: 0 | AV15: 0 | AW15: 0 | AX15: 0 | AY15: 0 | AZ15: 0 | BA15: 0 | BB15: 0 | BC15: 0 | BD15: 0 | BE15: 0 | BF15: 0 | BG15: 0 | BH15: 0 | BI15: 0 | BJ15: 0 | BK15: 0 | BL15: 0 | BM15: 0 | BN15: 0 | BO15: 0 | BP15: 0 | BQ15: 0 | BR15: 0 | BS15: 0 | CA15: 528 | CB15: 185 | CC15: 508 | CD15: 183 | CE15: 476 | CF15: 178 | CG15: 531 | CH15: 185 | CI15: 0 | CJ15: 0 | CK15: 0 | CL15: 0 | CM15: 0 | CN15: 0 | CO15: 836 | CP15: 265 | CQ15: 402 | CR15: 139 | CS15: 539 | CT15: 185 | CU15: 364 | CV15: 132 | CW15: 0 | CX15: 0 | CY15: 0 | CZ15: =O15&" "&Y15 -> Josh Nichols | DA15: =VLOOKUP(CZ15,[1]FINAL!$A$1:$AP$1000,MATCH("Element No.",[1]FINAL!$A$1:$AP$1,0),0) -> #N/A
A16: TRUE | B16: FALSE | C16: 100 | D16: 100 | E16: 223340 | F16: 0 | G16: 0 | H16: 0 | I16: 0 | J16: 3 | K16: 3 | L16: 7 | M16: 6.8 | N16: 0 | O16: Bukayo | P16: 5.8 | Q16: =DA16 -> 12 | R16: FALSE | T16: 2026-03-30T10:00:10.614078Z | U16: 100 | V16: 223340.jpg | W16: 5.1 | X16: FALSE | Y16: Saka | Z16: 11.6 | AA16: FALSE | AC16: a | AD16: 1 | AE16: 3 | AF16: 157 | AG16: 5027975 | AH16: 0 | AI16: 5509494 | AJ16: 0 | AK16: 0.6 | AL16: 15.7 | AM16: Saka | AO16: 241 | AP16: 43432 | AQ16: 37139 | AR16: FALSE | AS16: p223340 | AT16: 2218 | AU16: 7 | AV16: 10 | AW16: 12 | AX16: 16 | AY16: 0 | AZ16: 0 | BA16: 0 | BB16: 2 | BC16: 0 | BD16: 0 | BE16: 18 | BF16: 570 | BG16: 627 | BH16: 847.6 | BI16: 828 | BJ16: 230.6 | BK16: 28 | BL16: 116 | BM16: 40 | BN16: 184 | BO16: 25 | BP16: 7.57 | BQ16: 7.16 | BR16: 14.73 | BS16: 15.57 | BT16: 2 | BV16: 2 | BX16: 1 | CA16: 74 | CB16: 22 | CC16: 12 | CD16: 11 | CE16: 11 | CF16: 6 | CG16: 11 | CH16: 8 | CI16: 0.31 | CJ16: 0 | CK16: 0.29 | CL16: 0.6 | CM16: 0.63 | CN16: 0.65 | CO16: 6 | CP16: 4 | CQ16: 13 | CR16: 7 | CS16: 12 | CT16: 6 | CU16: 35 | CV16: 12 | CW16: 1.01 | CX16: 0.49 | CY16: 7.47 | CZ16: =O16&" "&Y16 -> Bukayo Saka | DA16: =VLOOKUP(CZ16,[1]FINAL!$A$1:$AP$1000,MATCH("Element No.",[1]FINAL!$A$1:$AP$1,0),0) -> 12
A17: TRUE | B17: FALSE | C17: 100 | D17: 100 | E17: 184029 | F17: 0 | G17: 0 | H17: -2 | I17: 2 | J17: 1 | K17: 3 | L17: 3.5 | M17: 2.8 | N17: 0 | O17: Martin | P17: 1.8 | Q17: =DA17 -> 15 | R17: FALSE | T17: 2026-05-01T14:00:09.623702Z | U17: 78 | V17: 184029.jpg | W17: 3.1 | X17: FALSE | Y17: Ødegaard | Z17: 1.7 | AA17: FALSE | AC17: a | AD17: 1 | AE17: 3 | AF17: 74 | AG17: 409252 | AH17: 0 | AI17: 664528 | AJ17: 0 | AK17: 0.2 | AL17: 9.5 | AM17: Ødegaard | AO17: 161 | AP17: 44428 | AQ17: 36146 | AR17: FALSE | AS17: p184029 | AT17: 1363 | AU17: 1 | AV17: 7 | AW17: 6 | AX17: 13 | AY17: 0 | AZ17: 0 | BA17: 0 | BB17: 0 | BC17: 0 | BD17: 0 | BE17: 5 | BF17: 306 | BG17: 311.8 | BH17: 564.4 | BI17: 168 | BJ17: 104.4 | BK17: 13 | BL17: 70 | BM17: 19 | BN17: 102 | BO17: 16 | BP17: 1.25 | BQ17: 3.65 | BR17: 4.9 | BS17: 16.2 | BT17: 4 | BX17: 3 | CA17: 238 | CB17: 100 | CC17: 44 | CD17: 38 | CE17: 218 | CF17: 117 | CG17: 138 | CH17: 75 | CI17: 0.08 | CJ17: 0 | CK17: 0.24 | CL17: 0.32 | CM17: 1.07 | CN17: 0.86 | CO17: 19 | CP17: 13 | CQ17: 214 | CR17: 95 | CS17: 187 | CT17: 73 | CU17: 156 | CV17: 50 | CW17: 1.06 | CX17: 0.4 | CY17: 6.74 | CZ17: =O17&" "&Y17 -> Martin Ødegaard | DA17: =VLOOKUP(CZ17,[1]FINAL!$A$1:$AP$1000,MATCH("Element No.",[1]FINAL!$A$1:$AP$1,0),0) -> 15
A18: TRUE | B18: FALSE | C18: 100 | D18: 100 | E18: 248857 | F18: 0 | G18: 0 | H18: -2 | I18: 2 | J18: 3 | K18: 3 | L18: 2.2 | M18: 4.2 | N18: 11 | O18: Noni | P18: 3.2 | Q18: =DA18 -> 16 | R18: FALSE | T18: 2026-04-16T13:00:09.580957Z | U18: 68 | V18: 248857.jpg | W18: 2.8 | X18: FALSE | Y18: Madueke | Z18: 0.8 | AA18: FALSE | AC18: a | AD18: 1 | AE18: 3 | AF18: 72 | AG18: 391478 | AH18: 0 | AI18: 439154 | AJ18: 0 | AK18: 0.5 | AL18: 10.6 | AM18: Madueke | AO18: 241 | AP18: 45856 | AQ18: 37325 | AR18: FALSE | AS18: p248857 | AT18: 1205 | AU18: 3 | AV18: 1 | AW18: 8 | AX18: 9 | AY18: 0 | AZ18: 0 | BA18: 0 | BB18: 0 | BC18: 0 | BD18: 0 | BE18: 9 | BF18: 254 | BG18: 257.4 | BH18: 352.8 | BI18: 404 | BJ18: 101.3 | BK18: 14 | BL18: 35 | BM18: 21 | BN18: 70 | BO18: 16 | BP18: 1.23 | BQ18: 2.86 | BR18: 4.09 | BS18: 12.77 | BT18: 3 | CA18: 272 | CB18: 115 | CC18: 113 | CD18: 79 | CE18: 77 | CF18: 45 | CG18: 145 | CH18: 79 | CI18: 0.09 | CJ18: 0 | CK18: 0.21 | CL18: 0.3 | CM18: 0.95 | CN18: 0.67 | CO18: 43 | CP18: 27 | CQ18: 108 | CR18: 50 | CS18: 230 | CT18: 90 | CU18: 218 | CV18: 75 | CW18: 1.2 | CX18: 0.6 | CY18: 5.23 | CZ18: =O18&" "&Y18 -> Noni Madueke | DA18: =VLOOKUP(CZ18,[1]FINAL!$A$1:$AP$1000,MATCH("Element No.",[1]FINAL!$A$1:$AP$1,0),0) -> 16
A19: TRUE | B19: FALSE | C19: 100 | D19: 100 | E19: 444145 | F19: 0 | G19: 0 | H19: -2 | I19: 2 | J19: 0 | K19: 3 | L19: 1.2 | M19: 3 | N19: 7 | O19: Gabriel | P19: 2 | Q19: =DA19 -> 18 | R19: FALSE | T19: 2025-12-24T02:30:10.584394Z | U19: 68 | V19: 444145.jpg | W19: 1.9 | X19: FALSE | Y19: Martinelli Silva | Z19: 0.9 | AA19: FALSE | AC19: a | AD19: 1 | AE19: 3 | AF19: 57 | AG19: 203187 | AH19: 0 | AI19: 278367 | AJ19: 0 | AK19: 0.3 | AL19: 8.4 | AM19: Martinelli | AN19: Gabriel Martinelli | AO19: 30 | AP19: 43661 | AQ19: 37060 | AR19: FALSE | AS19: p444145 | AT19: 1065 | AU19: 1 | AV19: 5 | AW19: 2 | AX19: 8 | AY19: 0 | AZ19: 0 | BA19: 0 | BB19: 3 | BC19: 0 | BD19: 0 | BE19: 3 | BF19: 195 | BG19: 204.6 | BH19: 202.2 | BI19: 390 | BJ19: 79 | BK19: 13 | BL19: 52 | BM19: 12 | BN19: 77 | BO19: 11 | BP19: 4.12 | BQ19: 1.27 | BR19: 5.39 | BS19: 10.51 | CA19: 308 | CB19: 131 | CC19: 204 | CD19: 135 | CE19: 82 | CF19: 49 | CG19: 209 | CH19: 99 | CI19: 0.35 | CJ19: 0 | CK19: 0.11 | CL19: 0.46 | CM19: 0.89 | CN19: 0.68 | CO19: 44 | CP19: 28 | CQ19: 193 | CR19: 89 | CS19: 372 | CT19: 161 | CU19: 208 | CV19: 72 | CW19: 0.93 | CX19: 0.17 | CY19: 6.51 | CZ19: =O19&" "&Y19 -> Gabriel Martinelli Silva | DA19: =VLOOKUP(CZ19,[1]FINAL!$A$1:$AP$1000,MATCH("Element No.",[1]FINAL!$A$1:$AP$1,0),0) -> 18
A20: TRUE | B20: FALSE | C20: 100 | D20: 100 | E20: 116216 | F20: 0 | G20: 0 | H20: -4 | I20: 4 | J20: 2 | K20: 3 | L20: 5.5 | M20: 5.5 | N20: 0 | O20: Leandro | P20: 4.5 | Q20: =DA20 -> #N/A | R20: FALSE | T20: 2026-03-24T00:00:10.597737Z | U20: 66 | V20: 116216.jpg | W20: 3.8 | X20: FALSE | Y20: Trossard | Z20: 1.8 | AA20: FALSE | AC20: a | AD20: 1 | AE20: 3 | AF20: 119 | AG20: 726467 | AH20: 0 | AI20: 554690 | AJ20: 0 | AK20: 0.7 | AL20: 18 | AM20: Trossard | AO20: 21 | AP20: 44946 | AQ20: 34672 | AR20: FALSE | AS20: p116216 | AT20: 1997 | AU20: 6 | AV20: 6 | AW20: 11 | AX20: 15 | AY20: 0 | AZ20: 0 | BA20: 0 | BB20: 2 | BC20: 0 | BD20: 0 | BE20: 11 | BF20: 445 | BG20: 494 | BH20: 545.5 | BI20: 541 | BJ20: 158.3 | BK20: 26 | BL20: 80 | BM20: 27 | BN20: 133 | BO20: 21 | BP20: 5.6 | BQ20: 3.59 | BR20: 9.18 | BS20: 13.94 | BX20: 4 | CA20: 134 | CB20: 45 | CC20: 47 | CD20: 41 | CE20: 48 | CF20: 27 | CG20: 51 | CH20: 35 | CI20: 0.25 | CJ20: 0 | CK20: 0.16 | CL20: 0.41 | CM20: 0.63 | CN20: 0.68 | CO20: 47 | CP20: 30 | CQ20: 45 | CR20: 19 | CS20: 85 | CT20: 41 | CU20: 144 | CV20: 46 | CW20: 0.95 | CX20: 0.5 | CY20: 5.99 | CZ20: =O20&" "&Y20 -> Leandro Trossard | DA20: =VLOOKUP(CZ20,[1]FINAL!$A$1:$AP$1000,MATCH("Element No.",[1]FINAL!$A$1:$AP$1,0),0) -> #N/A
A21: TRUE | B21: FALSE | C21: 100 | D21: 100 | E21: 204480 | F21: 0 | G21: 0 | H21: 7 | I21: -7 | J21: 5 | K21: 3 | L21: 4.8 | M21: 4.2 | N21: 0 | O21: Declan | P21: 3.2 | Q21: =DA21 -> 13 | R21: TRUE | T21: 2026-03-30T10:00:10.659246Z | U21: 72 | V21: 204480.jpg | W21: 5.1 | X21: FALSE | Y21: Rice | Z21: 23.3 | AA21: FALSE | AC21: a | AD21: 1 | AE21: 3 | AF21: 184 | AG21: 7631940 | AH21: 0 | AI21: 5848117 | AJ21: 0 | AK21: 0.4 | AL21: 25.6 | AM21: Rice | AO21: 241 | AP21: 45122 | AQ21: 36174 | AR21: FALSE | AS21: p204480 | AT21: 3093 | AU21: 4 | AV21: 9 | AW21: 18 | AX21: 25 | AY21: 0 | AZ21: 0 | BA21: 0 | BB21: 3 | BC21: 0 | BD21: 0 | BE21: 23 | BF21: 790 | BG21: 827.2 | BH21: 1027.4 | BI21: 298 | BJ21: 215.4 | BK21: 127 | BL21: 180 | BM21: 69 | BN21: 376 | BO21: 35 | BP21: 3.15 | BQ21: 7.32 | BR21: 10.47 | BS21: 23.87 | BT21: 1 | BV21: 1 | CA21: 26 | CB21: 9 | CC21: 4 | CD21: 4 | CE21: 115 | CF21: 69 | CG21: 15 | CH21: 11 | CI21: 0.09 | CJ21: 0 | CK21: 0.21 | CL21: 0.3 | CM21: 0.69 | CN21: 0.73 | CO21: 29 | CP21: 18 | CQ21: 109 | CR21: 51 | CS21: 9 | CT21: 4 | CU21: 11 | CV21: 3 | CW21: 1.02 | CX21: 0.52 | CY21: 10.94 | CZ21: =O21&" "&Y21 -> Declan Rice | DA21: =VLOOKUP(CZ21,[1]FINAL!$A$1:$AP$1000,MATCH("Element No.",[1]FINAL!$A$1:$AP$1,0),0) -> 13
A22: TRUE | B22: FALSE | C22: 100 | D22: 75 | E22: 195384 | F22: 0 | G22: 0 | H22: -7 | I22: 7 | J22: 1 | K22: 3 | L22: 0.8 | M22: 0.9 | N22: 1 | O22: Mikel | P22: 0.2 | Q22: =DA22 -> 17 | R22: FALSE | T22: 2026-02-02T11:30:08.998402Z | U22: 53 | V22: 195384.jpg | W22: 3 | X22: FALSE | Y22: Merino Zazón | Z22: 0.7 | AA22: FALSE | AC22: a | AD22: 1 | AE22: 3 | AF22: 67 | AG22: 836318 | AH22: 0 | AI22: 847590 | AJ22: 0 | AK22: 0 | AL22: 12.6 | AM22: Merino | AO22: 200 | AP22: 45531 | AQ22: 35238 | AR22: FALSE | AS22: p195384 | AT22: 1024 | AU22: 4 | AV22: 3 | AW22: 4 | AX22: 10 | AY22: 0 | AZ22: 0 | BA22: 0 | BB22: 1 | BC22: 0 | BD22: 0 | BE22: 5 | BF22: 236 | BG22: 304.4 | BH22: 191.8 | BI22: 244 | BJ22: 73.6 | BK22: 30 | BL22: 57 | BM22: 26 | BN22: 113 | BO22: 10 | BP22: 3.36 | BQ22: 1.45 | BR22: 4.81 | BS22: 7.36 | CA22: 242 | CB22: 102 | CC22: 215 | CD22: 143 | CE22: 143 | CF22: 78 | CG22: 225 | CH22: 108 | CI22: 0.3 | CJ22: 0 | CK22: 0.13 | CL22: 0.43 | CM22: 0.65 | CN22: 0.88 | CO22: 181 | CP22: 114 | CQ22: 391 | CR22: 178 | CS22: 199 | CT22: 78 | CU22: 228 | CV22: 79 | CW22: 0.88 | CX22: 0.35 | CY22: 9.93 | CZ22: =O22&" "&Y22 -> Mikel Merino Zazón | DA22: =VLOOKUP(CZ22,[1]FINAL!$A$1:$AP$1000,MATCH("Element No.",[1]FINAL!$A$1:$AP$1,0),0) -> 17
A23: TRUE | B23: FALSE | C23: 0 | D23: 0 | E23: 438098 | F23: 0 | G23: 0 | H23: -1 | I23: 1 | J23: 0 | K23: 3 | L23: 0 | M23: 0 | N23: 0 | O23: Fábio | P23: 0 | Q23: =DA23 -> 23 | R23: FALSE | S23: has joined Hamburger on loan for the rest of the season. | T23: 2025-09-02T13:38:06.128321Z | U23: 54 | V23: 438098.jpg | W23: 0 | X23: FALSE | Y23: Ferreira Vieira | Z23: 0 | AA23: FALSE | AC23: u | AD23: 1 | AE23: 3 | AF23: 0 | AG23: 933 | AH23: 0 | AI23: 4447 | AJ23: 0 | AK23: 0 | AL23: 0 | AM23: Fábio Vieira | AO23: 173 | AP23: 44733 | AQ23: 36676 | AR23: FALSE | AS23: p438098 | AT23: 0 | AU23: 0 | AV23: 0 | AW23: 0 | AX23: 0 | AY23: 0 | AZ23: 0 | BA23: 0 | BB23: 0 | BC23: 0 | BD23: 0 | BE23: 0 | BF23: 0 | BG23: 0 | BH23: 0 | BI23: 0 | BJ23: 0 | BK23: 0 | BL23: 0 | BM23: 0 | BN23: 0 | BO23: 0 | BP23: 0 | BQ23: 0 | BR23: 0 | BS23: 0 | CA23: 824 | CB23: 367 | CC23: 824 | CD23: 367 | CE23: 823 | CF23: 367 | CG23: 824 | CH23: 367 | CI23: 0 | CJ23: 0 | CK23: 0 | CL23: 0 | CM23: 0 | CN23: 0 | CO23: 164 | CP23: 101 | CQ23: 803 | CR23: 353 | CS23: 824 | CT23: 367 | CU23: 697 | CV23: 279 | CW23: 0 | CX23: 0 | CY23: 0 | CZ23: =O23&" "&Y23 -> Fábio Ferreira Vieira | DA23: =VLOOKUP(CZ23,[1]FINAL!$A$1:$AP$1000,MATCH("Element No.",[1]FINAL!$A$1:$AP$1,0),0) -> 23
A24: TRUE | B24: FALSE | C24: 100 | D24: 100 | E24: 128295 | F24: 0 | G24: 0 | H24: -4 | I24: 4 | J24: 0 | K24: 3 | L24: 1 | M24: 1.2 | N24: 1 | O24: Christian | P24: 0.2 | Q24: =DA24 -> 21 | R24: FALSE | T24: 2025-08-18T08:00:05.297235Z | U24: 51 | V24: 128295.jpg | W24: 1 | X24: FALSE | Y24: Nørgaard | Z24: 0.1 | AA24: FALSE | AC24: a | AD24: 1 | AE24: 3 | AF24: 7 | AG24: 8660 | AH24: 0 | AI24: 61962 | AJ24: 0 | AK24: 0 | AL24: 1.4 | AM24: Nørgaard | AO24: 58 | AP24: 45848 | AQ24: 34403 | AR24: FALSE | AS24: p128295 | AT24: 101 | AU24: 0 | AV24: 0 | AW24: 0 | AX24: 1 | AY24: 0 | AZ24: 0 | BA24: 0 | BB24: 0 | BC24: 0 | BD24: 0 | BE24: 0 | BF24: 28 | BG24: 23.4 | BH24: 5.5 | BI24: 10 | BJ24: 4 | BK24: 9 | BL24: 4 | BM24: 3 | BN24: 16 | BO24: 1 | BP24: 0.08 | BQ24: 0.04 | BR24: 0.12 | BS24: 2.28 | CA24: 459 | CB24: 203 | CC24: 461 | CD24: 221 | CE24: 429 | CF24: 210 | CG24: 472 | CH24: 211 | CI24: 0.07 | CJ24: 0 | CK24: 0.04 | CL24: 0.11 | CM24: 2.03 | CN24: 0.89 | CO24: 222 | CP24: 137 | CQ24: 386 | CR24: 175 | CS24: 514 | CT24: 236 | CU24: 442 | CV24: 151 | CW24: 0.89 | CX24: 0 | CY24: 14.26 | CZ24: =O24&" "&Y24 -> Christian Nørgaard | DA24: =VLOOKUP(CZ24,[1]FINAL!$A$1:$AP$1000,MATCH("Element No.",[1]FINAL!$A$1:$AP$1,0),0) -> 21
A25: TRUE | B25: FALSE | C25: 0 | D25: 0 | E25: 499175 | F25: 0 | G25: 0 | H25: -5 | I25: 5 | J25: 0 | K25: 3 | L25: 0 | M25: 0 | N25: 0 | O25: Ethan | P25: 0 | Q25: =DA25 -> 22 | R25: FALSE | S25: has joined Marseille on loan for the rest of the season. | T25: 2026-01-23T17:18:55.073277Z | U25: 50 | V25: 499175.jpg | W25: 1.3 | X25: FALSE | Y25: Nwaneri | Z25: 0.1 | AA25: FALSE | AC25: u | AD25: 1 | AE25: 3 | AF25: 8 | AG25: 13149 | AH25: 0 | AI25: 37244 | AJ25: 0 | AK25: 0 | AL25: 1.6 | AM25: Nwaneri | AO25: 241 | AP25: 44821 | AQ25: 39162 | AR25: FALSE | AS25: p499175 | AT25: 165 | AU25: 0 | AV25: 0 | AW25: 1 | AX25: 0 | AY25: 0 | AZ25: 0 | BA25: 0 | BB25: 0 | BC25: 0 | BD25: 0 | BE25: 0 | BF25: 20 | BG25: 8.6 | BH25: 22.5 | BI25: 24 | BJ25: 5.4 | BK25: 1 | BL25: 10 | BM25: 2 | BN25: 13 | BO25: 0 | BP25: 0.23 | BQ25: 0.08 | BR25: 0.31 | BS25: 0.73 | CA25: 483 | CB25: 215 | CC25: 410 | CD25: 204 | CE25: 392 | CF25: 195 | CG25: 461 | CH25: 205 | CI25: 0.13 | CJ25: 0 | CK25: 0.04 | CL25: 0.17 | CM25: 0.4 | CN25: 0 | CO25: 269 | CP25: 163 | CQ25: 774 | CR25: 333 | CS25: 448 | CT25: 198 | CU25: 462 | CV25: 158 | CW25: 0 | CX25: 0.55 | CY25: 7.09 | CZ25: =O25&" "&Y25 -> Ethan Nwaneri | DA25: =VLOOKUP(CZ25,[1]FINAL!$A$1:$AP$1000,MATCH("Element No.",[1]FINAL!$A$1:$AP$1,0),0) -> 22
A26: TRUE | B26: FALSE | C26: 100 | D26: 100 | E26: 481655 | F26: 0 | G26: 0 | H26: -6 | I26: 6 | J26: 1 | K26: 3 | L26: 3 | M26: 2.2 | N26: 2 | O26: Martín | P26: 1.2 | Q26: =DA26 -> 19 | R26: FALSE | T26: 2026-03-30T10:00:10.681664Z | U26: 49 | V26: 481655.jpg | W26: 3.5 | X26: FALSE | Y26: Zubimendi Ibáñez | Z26: 2.7 | AA26: FALSE | AC26: a | AD26: 1 | AE26: 3 | AF26: 133 | AG26: 1383151 | AH26: 0 | AI26: 1353576 | AJ26: 0 | AK26: 0.2 | AL26: 27.1 | AM26: Zubimendi | AO26: 200 | AP26: 45844 | AQ26: 36193 | AR26: FALSE | AS26: p481655 | AT26: 2991 | AU26: 5 | AV26: 1 | AW26: 16 | AX26: 25 | AY26: 0 | AZ26: 0 | BA26: 0 | BB26: 4 | BC26: 0 | BD26: 0 | BE26: 9 | BF26: 604 | BG26: 603.2 | BH26: 385.1 | BI26: 271 | BJ26: 126.2 | BK26: 123 | BL26: 116 | BM26: 68 | BN26: 307 | BO26: 34 | BP26: 2.84 | BQ26: 2.27 | BR26: 5.11 | BS26: 26.09 | CA26: 81 | CB26: 26 | CC26: 99 | CD26: 70 | CE26: 131 | CF26: 73 | CG26: 89 | CH26: 55 | CI26: 0.09 | CJ26: 0 | CK26: 0.07 | CL26: 0.16 | CM26: 0.79 | CN26: 0.75 | CO26: 327 | CP26: 202 | CQ26: 257 | CR26: 112 | CS26: 116 | CT26: 50 | CU26: 116 | CV26: 38 | CW26: 1.02 | CX26: 0.48 | CY26: 9.24 | CZ26: =O26&" "&Y26 -> Martín Zubimendi Ibáñez | DA26: =VLOOKUP(CZ26,[1]FINAL!$A$1:$AP$1000,MATCH("Element No.",[1]FINAL!$A$1:$AP$1,0),0) -> 19
A27: TRUE | B27: FALSE | C27: 0 | D27: 0 | E27: 588796 | F27: 0 | G27: 0 | H27: 0 | I27: 0 | J27: 0 | K27: 3 | L27: 0 | M27: 0 | N27: 0 | O27: Ismeal | P27: 0 | Q27: =DA27 -> #N/A | R27: FALSE | S27: has joined Shrewsbury Town on loan for the rest of the season. | T27: 2025-09-02T13:24:41.013511Z | U27: 45 | V27: 588796.jpg | W27: 0 | X27: FALSE | Y27: Kabia | Z27: 0.1 | AA27: FALSE | AC27: u | AD27: 1 | AE27: 3 | AF27: 0 | AG27: 6731 | AH27: 0 | AI27: 30392 | AJ27: 0 | AK27: 0 | AL27: 0 | AM27: Kabia | AO27: 152 | AP27: 45549 | AQ27: 38696 | AR27: FALSE | AS27: p588796 | AT27: 0 | AU27: 0 | AV27: 0 | AW27: 0 | AX27: 0 | AY27: 0 | AZ27: 0 | BA27: 0 | BB27: 0 | BC27: 0 | BD27: 0 | BE27: 0 | BF27: 0 | BG27: 0 | BH27: 0 | BI27: 0 | BJ27: 0 | BK27: 0 | BL27: 0 | BM27: 0 | BN27: 0 | BO27: 0 | BP27: 0 | BQ27: 0 | BR27: 0 | BS27: 0 | CA27: 753 | CB27: 314 | CC27: 746 | CD27: 313 | CE27: 733 | CF27: 310 | CG27: 753 | CH27: 314 | CI27: 0 | CJ27: 0 | CK27: 0 | CL27: 0 | CM27: 0 | CN27: 0 | CO27: 490 | CP27: 301 | CQ27: 683 | CR27: 269 | CS27: 755 | CT27: 315 | CU27: 496 | CV27: 177 | CW27: 0 | CX27: 0 | CY27: 0 | CZ27: =O27&" "&Y27 -> Ismeal Kabia | DA27: =VLOOKUP(CZ27,[1]FINAL!$A$1:$AP$1000,MATCH("Element No.",[1]FINAL!$A$1:$AP$1,0),0) -> #N/A
A28: TRUE | B28: FALSE | C28: 0 | D28: 0 | E28: 437742 | F28: 0 | G28: 0 | H28: 0 | I28: 0 | J28: 0 | K28: 3 | L28: 0 | M28: 0 | N28: 0 | O28: Albert | P28: 0 | Q28: =DA28 -> #N/A | R28: FALSE | S28: has joined Hamburger permanently. | T28: 2025-09-02T13:40:53.094922Z | U28: 45 | V28: 437742.jpg | W28: 0 | X28: FALSE | Y28: Sambi Lokonga | Z28: 0 | AA28: FALSE | AC28: u | AD28: 1 | AE28: 3 | AF28: 0 | AG28: 2952 | AH28: 0 | AI28: 14151 | AJ28: 0 | AK28: 0 | AL28: 0 | AM28: Sambi | AO28: 21 | AP28: 44396 | AQ28: 36455 | AR28: FALSE | AS28: p437742 | AT28: 0 | AU28: 0 | AV28: 0 | AW28: 0 | AX28: 0 | AY28: 0 | AZ28: 0 | BA28: 0 | BB28: 0 | BC28: 0 | BD28: 0 | BE28: 0 | BF28: 0 | BG28: 0 | BH28: 0 | BI28: 0 | BJ28: 0 | BK28: 0 | BL28: 0 | BM28: 0 | BN28: 0 | BO28: 0 | BP28: 0 | BQ28: 0 | BR28: 0 | BS28: 0 | CA28: 708 | CB28: 274 | CC28: 704 | CD28: 276 | CE28: 687 | CF28: 270 | CG28: 710 | CH28: 276 | CI28: 0 | CJ28: 0 | CK28: 0 | CL28: 0 | CM28: 0 | CN28: 0 | CO28: 433 | CP28: 256 | CQ28: 635 | CR28: 227 | CS28: 714 | CT28: 279 | CU28: 593 | CV28: 222 | CW28: 0 | CX28: 0 | CY28: 0 | CZ28: =O28&" "&Y28 -> Albert Sambi Lokonga | DA28: =VLOOKUP(CZ28,[1]FINAL!$A$1:$AP$1000,MATCH("Element No.",[1]FINAL!$A$1:$AP$1,0),0) -> #N/A
A29: TRUE | B29: FALSE | C29: 100 | D29: 100 | E29: 219847 | F29: 0 | G29: 0 | H29: -2 | I29: 2 | J29: 0 | K29: 4 | L29: 4.2 | M29: 4.2 | N29: 4 | O29: Kai | P29: 3.2 | Q29: =DA29 -> 26 | R29: FALSE | T29: 2026-04-25T22:30:09.266637Z | U29: 73 | V29: 219847.jpg | W29: 3 | X29: FALSE | Y29: Havertz | Z29: 0.7 | AA29: FALSE | AC29: a | AD29: 1 | AE29: 3 | AF29: 36 | AG29: 197946 | AH29: 0 | AI29: 255689 | AJ29: 0 | AK29: 0.4 | AL29: 4.9 | AM29: Havertz | AO29: 80 | AP29: 45105 | AQ29: 36322 | AR29: FALSE | AS29: p219847 | AT29: 577 | AU29: 2 | AV29: 3 | AW29: 4 | AX29: 4 | AY29: 0 | AZ29: 0 | BA29: 0 | BB29: 1 | BC29: 0 | BD29: 0 | BE29: 3 | BF29: 143 | BG29: 152.6 | BH29: 134.6 | BI29: 210 | BJ29: 49.9 | BK29: 10 | BL29: 14 | BM29: 8 | BN29: 32 | BO29: 7 | BP29: 3.31 | BQ29: 0.64 | BR29: 3.95 | BS29: 6.68 | CA29: 346 | CB29: 35 | CC29: 265 | CD29: 31 | CE29: 173 | CF29: 40 | CG29: 305 | CH29: 35 | CI29: 0.52 | CJ29: 0 | CK29: 0.1 | CL29: 0.62 | CM29: 1.04 | CN29: 0.62 | CO29: 24 | CP29: 10 | CQ29: 110 | CR29: 16 | CS29: 202 | CT29: 22 | CU29: 238 | CV29: 36 | CW29: 1.09 | CX29: 0.62 | CY29: 4.99 | CZ29: =O29&" "&Y29 -> Kai Havertz | DA29: =VLOOKUP(CZ29,[1]FINAL!$A$1:$AP$1000,MATCH("Element No.",[1]FINAL!$A$1:$AP$1,0),0) -> 26
A30: TRUE | B30: FALSE | C30: 100 | D30: 100 | E30: 205651 | F30: 0 | G30: 0 | H30: -1 | I30: 1 | J30: 0 | K30: 4 | L30: 1.2 | M30: 2.5 | N30: 5 | O30: Gabriel | P30: 1.5 | Q30: =DA30 -> 27 | R30: FALSE | T30: 2025-07-21T10:00:04.697564Z | U30: 64 | V30: 205651.jpg | W30: 1.7 | X30: FALSE | Y30: Fernando de Jesus | Z30: 0.4 | AA30: FALSE | AC30: a | AD30: 1 | AE30: 3 | AF30: 24 | AG30: 156814 | AH30: 0 | AI30: 134920 | AJ30: 0 | AK30: 0.2 | AL30: 3.8 | AM30: G.Jesus | AN30: Gabriel Jesus | AO30: 30 | AP30: 44746 | AQ30: 35523 | AR30: FALSE | AS30: p205651 | AT30: 418 | AU30: 3 | AV30: 0 | AW30: 1 | AX30: 6 | AY30: 0 | AZ30: 0 | BA30: 0 | BB30: 3 | BC30: 0 | BD30: 0 | BE30: 0 | BF30: 92 | BG30: 141.8 | BH30: 54.3 | BI30: 281 | BJ30: 47.5 | BK30: 7 | BL30: 19 | BM30: 4 | BN30: 30 | BO30: 3 | BP30: 2.71 | BQ30: 0.26 | BR30: 2.97 | BS30: 3.97 | CA30: 355 | CB30: 39 | CC30: 363 | CD30: 45 | CE30: 127 | CF30: 34 | CG30: 315 | CH30: 38 | CI30: 0.58 | CJ30: 0 | CK30: 0.06 | CL30: 0.64 | CM30: 0.85 | CN30: 1.29 | CO30: 57 | CP30: 21 | CQ30: 230 | CR30: 30 | CS30: 407 | CT30: 47 | CU30: 301 | CV30: 48 | CW30: 0.65 | CX30: 0.22 | CY30: 6.46 | CZ30: =O30&" "&Y30 -> Gabriel Fernando de Jesus | DA30: =VLOOKUP(CZ30,[1]FINAL!$A$1:$AP$1000,MATCH("Element No.",[1]FINAL!$A$1:$AP$1,0),0) -> 27
A31: TRUE | B31: FALSE | C31: 100 | D31: 100 | E31: 232413 | F31: 0 | G31: 0 | H31: -2 | I31: 2 | J31: 3 | K31: 3 | L31: 4.8 | M31: 3.5 | N31: 1 | O31: Eberechi | P31: 2.5 | Q31: =DA31 -> 14 | R31: FALSE | T31: 2026-04-25T22:30:09.375724Z | U31: 73 | V31: 232413.jpg | W31: 3.4 | X31: FALSE | Y31: Eze | Z31: 8.7 | AA31: FALSE | AC31: a | AD31: 1 | AE31: 3 | AF31: 113 | AG31: 3651571 | AH31: 0 | AI31: 3941829 | AJ31: 0 | AK31: 0.3 | AL31: 15.5 | AM31: Eze | AO31: 241 | AP31: 45892 | AQ31: 35975 | AR31: FALSE | AS31: p232413 | AT31: 1885 | AU31: 7 | AV31: 3 | AW31: 11 | AX31: 14 | AY31: 0 | AZ31: 0 | BA31: 0 | BB31: 1 | BC31: 0 | BD31: 0 | BE31: 8 | BF31: 439 | BG31: 393.4 | BH31: 305.7 | BI31: 455 | BJ31: 115.1 | BK31: 22 | BL31: 79 | BM31: 19 | BN31: 120 | BO31: 22 | BP31: 5.18 | BQ31: 2.66 | BR31: 7.84 | BS31: 14.21 | CA31: 187 | CB31: 73 | CC31: 143 | CD31: 95 | CE31: 60 | CF31: 34 | CG31: 108 | CH31: 60 | CI31: 0.25 | CJ31: 0 | CK31: 0.13 | CL31: 0.38 | CM31: 0.68 | CN31: 0.67 | CO31: 26 | CP31: 15 | CQ31: 157 | CR31: 71 | CS31: 141 | CT31: 61 | CU31: 48 | CV31: 17 | CW31: 1.05 | CX31: 0.53 | CY31: 5.73 | CZ31: =O31&" "&Y31 -> Eberechi Eze | DA31: =VLOOKUP(CZ31,[1]FINAL!$A$1:$AP$1000,MATCH("Element No.",[1]FINAL!$A$1:$AP$1,0),0) -> 14
A32: TRUE | B32: FALSE | C32: 100 | D32: 100 | E32: 500040 | F32: 0 | G32: 0 | H32: -2 | I32: 2 | J32: 0 | K32: 2 | L32: 2.8 | M32: 3.8 | N32: 4 | O32: Cristhian | P32: 2.8 | Q32: =DA32 -> 11 | R32: FALSE | T32: 2025-12-04T09:00:09.512338Z | U32: 53 | V32: 500040.jpg | W32: 2 | X32: FALSE | Y32: Mosquera | Z32: 0.3 | AA32: FALSE | AC32: a | AD32: 1 | AE32: 3 | AF32: 40 | AG32: 72218 | AH32: 0 | AI32: 57288 | AJ32: 0 | AK32: 0.5 | AL32: 7.5 | AM32: Mosquera | AO32: 200 | AP32: 45862 | AQ32: 38165 | AR32: FALSE | AS32: p500040 | AT32: 986 | AU32: 0 | AV32: 0 | AW32: 3 | AX32: 8 | AY32: 0 | AZ32: 0 | BA32: 0 | BB32: 4 | BC32: 0 | BD32: 0 | BE32: 1 | BF32: 195 | BG32: 219.2 | BH32: 88.7 | BI32: 20 | BJ32: 32.9 | BK32: 63 | BL32: 35 | BM32: 32 | BN32: 95 | BO32: 9 | BP32: 0.1 | BQ32: 0.63 | BR32: 0.73 | BS32: 9.04 | CA32: 295 | CB32: 117 | CC32: 307 | CD32: 100 | CE32: 405 | CF32: 145 | CG32: 359 | CH32: 121 | CI32: 0.01 | CJ32: 0 | CK32: 0.06 | CL32: 0.07 | CM32: 0.83 | CN32: 0.73 | CO32: 199 | CP32: 26 | CQ32: 135 | CR32: 42 | CS32: 357 | CT32: 132 | CU32: 324 | CV32: 118 | CW32: 0.82 | CX32: 0.27 | CY32: 8.67 | CZ32: =O32&" "&Y32 -> Cristhian Mosquera | DA32: =VLOOKUP(CZ32,[1]FINAL!$A$1:$AP$1000,MATCH("Element No.",[1]FINAL!$A$1:$AP$1,0),0) -> 11
A33: TRUE | B33: FALSE | C33: 100 | D33: 100 | E33: 224117 | F33: 0 | G33: 0 | H33: 1 | I33: -1 | J33: 4 | K33: 4 | L33: 6 | M33: 6 | N33: 1 | O33: Viktor | P33: 5 | Q33: =DA33 -> 25 | R33: FALSE | T33: 2025-11-01T18:00:08.847750Z | U33: 91 | V33: 224117.jpg | W33: 3.6 | X33: FALSE | Y33: Gyökeres | Z33: 16.4 | AA33: FALSE | AC33: a | AD33: 1 | AE33: 3 | AF33: 128 | AG33: 4626668 | AH33: 0 | AI33: 5611221 | AJ33: 0 | AK33: 0.5 | AL33: 14.1 | AM33: Gyökeres | AO33: 206 | AP33: 45864 | AQ33: 35950 | AR33: FALSE | AS33: p224117 | AT33: 2217 | AU33: 14 | AV33: 1 | AW33: 12 | AX33: 14 | AY33: 0 | AZ33: 0 | BA33: 0 | BB33: 5 | BC33: 0 | BD33: 0 | BE33: 16 | BF33: 474 | BG33: 539.6 | BH33: 271.7 | BI33: 772 | BJ33: 157.5 | BK33: 23 | BL33: 55 | BM33: 7 | BN33: 85 | BO33: 26 | BP33: 12.26 | BQ33: 1.94 | BR33: 14.19 | BS33: 17.81 | BX33: 2 | CA33: 111 | CB33: 10 | CC33: 159 | CD33: 14 | CE33: 21 | CF33: 12 | CG33: 52 | CH33: 9 | CI33: 0.5 | CJ33: 0 | CK33: 0.08 | CL33: 0.58 | CM33: 0.72 | CN33: 0.57 | CO33: 7 | CP33: 3 | CQ33: 28 | CR33: 6 | CS33: 110 | CT33: 11 | CU33: 20 | CV33: 5 | CW33: 1.06 | CX33: 0.49 | CY33: 3.45 | CZ33: =O33&" "&Y33 -> Viktor Gyökeres | DA33: =VLOOKUP(CZ33,[1]FINAL!$A$1:$AP$1000,MATCH("Element No.",[1]FINAL!$A$1:$AP$1,0),0) -> 25
A34: TRUE | B34: FALSE | C34: 100 | D34: 100 | E34: 616077 | F34: 0 | G34: 0 | H34: -3 | I34: 3 | J34: 0 | K34: 3 | L34: 1.2 | M34: 2 | N34: 3 | O34: Max | P34: 1 | Q34: =DA34 -> 20 | R34: FALSE | T34: 2025-12-10T00:00:08.266774Z | U34: 42 | V34: 616077.jpg | W34: 2.7 | X34: FALSE | Y34: Dowman | Z34: 0.9 | AA34: FALSE | AC34: a | AD34: 1 | AE34: 3 | AF34: 16 | AG34: 291075 | AH34: 0 | AI34: 193138 | AJ34: 0 | AK34: 0.2 | AL34: 3.8 | AM34: Dowman | AO34: 241 | AP34: 45860 | AQ34: 40178 | AR34: FALSE | AS34: p616077 | AT34: 152 | AU34: 1 | AV34: 1 | AW34: 1 | AX34: 1 | AY34: 0 | AZ34: 0 | BA34: 0 | BB34: 0 | BC34: 0 | BD34: 0 | BE34: 0 | BF34: 51 | BG34: 45.2 | BH34: 55.5 | BI34: 65 | BJ34: 16.6 | BK34: 1 | BL34: 13 | BM34: 2 | BN34: 16 | BO34: 1 | BP34: 1.19 | BQ34: 0.3 | BR34: 1.49 | BS34: 0.88 | CA34: 434 | CB34: 189 | CC34: 360 | CD34: 189 | CE34: 330 | CF34: 170 | CG34: 409 | CH34: 187 | CI34: 0.7 | CJ34: 0 | CK34: 0.18 | CL34: 0.88 | CM34: 0.52 | CN34: 0.59 | CO34: 659 | CP34: 379 | CQ34: 276 | CR34: 122 | CS34: 234 | CT34: 91 | CU34: 204 | CV34: 71 | CW34: 0.59 | CX34: 0.59 | CY34: 9.47 | CZ34: =O34&" "&Y34 -> Max Dowman | DA34: =VLOOKUP(CZ34,[1]FINAL!$A$1:$AP$1000,MATCH("Element No.",[1]FINAL!$A$1:$AP$1,0),0) -> 20
A35: TRUE | B35: FALSE | E35: 646243 | F35: 0 | G35: 0 | H35: -1 | I35: 1 | J35: 0 | K35: 3 | L35: 1 | M35: 1 | N35: 0 | O35: Andre | P35: 0 | Q35: =DA35 -> #N/A | R35: FALSE | U35: 44 | V35: 646243.jpg | W35: 0 | X35: FALSE | Y35: Harriman-Annous | Z35: 0 | AA35: FALSE | AC35: a | AD35: 1 | AE35: 3 | AF35: 0 | AG35: 2098 | AH35: 0 | AI35: 1977 | AJ35: 0 | AK35: 0 | AL35: 0 | AM35: Harriman-Annous | AO35: 241 | AP35: 45860 | AQ35: 39444 | AR35: FALSE | AS35: p646243 | AT35: 0 | AU35: 0 | AV35: 0 | AW35: 0 | AX35: 0 | AY35: 0 | AZ35: 0 | BA35: 0 | BB35: 0 | BC35: 0 | BD35: 0 | BE35: 0 | BF35: 0 | BG35: 0 | BH35: 0 | BI35: 0 | BJ35: 0 | BK35: 0 | BL35: 0 | BM35: 0 | BN35: 0 | BO35: 0 | BP35: 0 | BQ35: 0 | BR35: 0 | BS35: 0 | CA35: 697 | CB35: 268 | CC35: 692 | CD35: 270 | CE35: 673 | CF35: 263 | CG35: 699 | CH35: 270 | CI35: 0 | CJ35: 0 | CK35: 0 | CL35: 0 | CM35: 0 | CN35: 0 | CO35: 582 | CP35: 351 | CQ35: 621 | CR35: 220 | CS35: 703 | CT35: 273 | CU35: 707 | CV35: 287 | CW35: 0 | CX35: 0 | CY35: 0 | CZ35: =O35&" "&Y35 -> Andre Harriman-Annous | DA35: =VLOOKUP(CZ35,[1]FINAL!$A$1:$AP$1000,MATCH("Element No.",[1]FINAL!$A$1:$AP$1,0),0) -> #N/A
A36: TRUE | B36: FALSE | C36: 100 | D36: 100 | E36: 448104 | F36: 0 | G36: 0 | H36: -4 | I36: 4 | J36: 3 | K36: 2 | L36: 3.5 | M36: 1.8 | N36: 2 | O36: Piero | P36: 0.8 | Q36: =DA36 -> 9 | R36: FALSE | T36: 2026-03-30T10:00:11.369303Z | U36: 51 | V36: 448104.jpg | W36: 3.5 | X36: FALSE | Y36: Hincapié | Z36: 0.9 | AA36: FALSE | AC36: a | AD36: 1 | AE36: 3 | AF36: 87 | AG36: 625158 | AH36: 0 | AI36: 522735 | AJ36: 0 | AK36: 0.2 | AL36: 17.1 | AM36: Hincapie | AO36: 62 | AP36: 45901 | AQ36: 37265 | AR36: FALSE | AS36: p448104 | AT36: 1787 | AU36: 1 | AV36: 2 | AW36: 5 | AX36: 19 | AY36: 1 | AZ36: 0 | BA36: 0 | BB36: 2 | BC36: 0 | BD36: 0 | BE36: 7 | BF36: 335 | BG36: 453.6 | BH36: 184.7 | BI36: 72 | BJ36: 70.9 | BK36: 123 | BL36: 63 | BM36: 48 | BN36: 171 | BO36: 20 | BP36: 0.36 | BQ36: 1.67 | BR36: 2.03 | BS36: 17.53 | CA36: 150 | CB36: 63 | CC36: 221 | CD36: 55 | CE36: 321 | CF36: 103 | CG36: 235 | CH36: 80 | CI36: 0.02 | CJ36: 0 | CK36: 0.08 | CL36: 0.1 | CM36: 0.88 | CN36: 0.96 | CO36: 233 | CP36: 36 | CQ36: 310 | CR36: 111 | CS36: 118 | CT36: 45 | CU36: 212 | CV36: 82 | CW36: 1.01 | CX36: 0.25 | CY36: 8.61 | CZ36: =O36&" "&Y36 -> Piero Hincapié | DA36: =VLOOKUP(CZ36,[1]FINAL!$A$1:$AP$1000,MATCH("Element No.",[1]FINAL!$A$1:$AP$1,0),0) -> 9
A37: TRUE | B37: FALSE | E37: 616065 | F37: 0 | G37: 0 | H37: 0 | I37: 0 | J37: 0 | K37: 2 | L37: 1 | M37: 1 | N37: 0 | O37: Marli | P37: 0 | Q37: =DA37 -> #N/A | R37: FALSE | U37: 40 | V37: 616065.jpg | W37: 0 | X37: FALSE | Y37: Salmon | Z37: 0 | AA37: FALSE | AC37: a | AD37: 1 | AE37: 3 | AF37: 0 | AG37: 1910 | AH37: 0 | AI37: 1535 | AJ37: 0 | AK37: 0 | AL37: 0 | AM37: Salmon | AO37: 241 | AP37: 45860 | AQ37: 40054 | AR37: FALSE | AS37: p616065 | AT37: 0 | AU37: 0 | AV37: 0 | AW37: 0 | AX37: 0 | AY37: 0 | AZ37: 0 | BA37: 0 | BB37: 0 | BC37: 0 | BD37: 0 | BE37: 0 | BF37: 0 | BG37: 0 | BH37: 0 | BI37: 0 | BJ37: 0 | BK37: 0 | BL37: 0 | BM37: 0 | BN37: 0 | BO37: 0 | BP37: 0 | BQ37: 0 | BR37: 0 | BS37: 0 | CA37: 636 | CB37: 245 | CC37: 628 | CD37: 244 | CE37: 598 | CF37: 241 | CG37: 639 | CH37: 245 | CI37: 0 | CJ37: 0 | CK37: 0 | CL37: 0 | CM37: 0 | CN37: 0 | CO37: 746 | CP37: 205 | CQ37: 529 | CR37: 212 | CS37: 646 | CT37: 244 | CU37: 664 | CV37: 235 | CW37: 0 | CX37: 0 | CY37: 0 | CZ37: =O37&" "&Y37 -> Marli Salmon | DA37: =VLOOKUP(CZ37,[1]FINAL!$A$1:$AP$1000,MATCH("Element No.",[1]FINAL!$A$1:$AP$1,0),0) -> #N/A
A38: TRUE | B38: FALSE | C38: 100 | D38: 100 | E38: 98980 | F38: 0 | G38: 0 | H38: 0 | I38: 0 | J38: 3 | K38: 1 | L38: 2.7 | M38: 2 | N38: 0 | O38: Emiliano | P38: 2.5 | Q38: =DA38 -> 28 | R38: FALSE | T38: 2026-04-12T21:30:08.032006Z | U38: 50 | V38: 98980.jpg | W38: 3.8 | X38: FALSE | Y38: Martínez Romero | Z38: 4.4 | AA38: FALSE | AC38: a | AD38: 2 | AE38: 7 | AF38: 120 | AG38: 1133258 | AH38: 0 | AI38: 844392 | AJ38: 0 | AK38: 0.5 | AL38: 24 | AM38: Martinez | AO38: 10 | AP38: 44090 | AQ38: 33849 | AR38: FALSE | AS38: p98980 | AT38: 2835 | AU38: 0 | AV38: 1 | AW38: 7 | AX38: 39 | AY38: 0 | AZ38: 1 | BA38: 0 | BB38: 2 | BC38: 0 | BD38: 95 | BE38: 11 | BF38: 530 | BG38: 769.8 | BH38: 23.2 | BI38: 0 | BJ38: 79.2 | BK38: 27 | BL38: 272 | BM38: 0 | BN38: 0 | BO38: 32 | BP38: 0 | BQ38: 0.08 | BR38: 0.08 | BS38: 42.92 | CA38: 38 | CB38: 10 | CC38: 408 | CD38: 4 | CE38: 800 | CF38: 93 | CG38: 206 | CH38: 10 | CI38: 0 | CJ38: 3.02 | CK38: 0 | CL38: 0 | CM38: 1.36 | CN38: 1.24 | CO38: 245 | CP38: 10 | CQ38: 150 | CR38: 14 | CS38: 80 | CT38: 8 | CU38: 86 | CV38: 16 | CW38: 1.02 | CX38: 0.22 | CY38: 0 | CZ38: =O38&" "&Y38 -> Emiliano Martínez Romero | DA38: =VLOOKUP(CZ38,[1]FINAL!$A$1:$AP$1000,MATCH("Element No.",[1]FINAL!$A$1:$AP$1,0),0) -> 28
A39: TRUE | B39: FALSE | C39: 100 | D39: 100 | E39: 72147 | F39: 0 | G39: 0 | H39: -3 | I39: 3 | J39: 0 | K39: 1 | L39: -0.5 | M39: 0 | N39: 2 | O39: Marco | P39: 0.5 | Q39: =DA39 -> 29 | R39: FALSE | T39: 2026-02-15T00:30:06.693638Z | U39: 42 | V39: 72147.jpg | W39: 2.3 | X39: FALSE | Y39: Bizot | Z39: 0.4 | AA39: FALSE | AC39: a | AD39: 2 | AE39: 7 | AF39: 16 | AG39: 85879 | AH39: 0 | AI39: 117979 | AJ39: 0 | AK39: 0.1 | AL39: 3.8 | AM39: M.Bizot | AO39: 152 | AP39: 45853 | AQ39: 33307 | AR39: FALSE | AS39: p72147 | AT39: 585 | AU39: 0 | AV39: 0 | AW39: 1 | AX39: 10 | AY39: 0 | AZ39: 0 | BA39: 0 | BB39: 2 | BC39: 0 | BD39: 19 | BE39: 0 | BF39: 75 | BG39: 139.2 | BH39: 0 | BI39: 0 | BJ39: 13.9 | BK39: 10 | BL39: 53 | BM39: 0 | BN39: 0 | BO39: 6 | BP39: 0 | BQ39: 0 | BR39: 0 | BS39: 11.02 | CA39: 358 | CB39: 26 | CC39: 642 | CD39: 83 | CE39: 614 | CF39: 68 | CG39: 415 | CH39: 26 | CI39: 0 | CJ39: 2.92 | CK39: 0 | CL39: 0 | CM39: 1.7 | CN39: 1.54 | CO39: 635 | CP39: 29 | CQ39: 328 | CR39: 26 | CS39: 302 | CT39: 29 | CU39: 295 | CV39: 38 | CW39: 0.92 | CX39: 0.15 | CY39: 0 | CZ39: =O39&" "&Y39 -> Marco Bizot | DA39: =VLOOKUP(CZ39,[1]FINAL!$A$1:$AP$1000,MATCH("Element No.",[1]FINAL!$A$1:$AP$1,0),0) -> 29
A40: TRUE | B40: FALSE | C40: 0 | D40: 0 | E40: 462492 | F40: 0 | G40: 0 | H40: 0 | I40: 0 | J40: 0 | K40: 1 | L40: 0 | M40: 0 | N40: 0 | O40: Joe | P40: 0 | Q40: =DA40 -> #N/A | R40: FALSE | S40: Has joined Port Vale on loan for the rest of the season. | T40: 2025-08-12T07:40:37.843391Z | U40: 40 | V40: 462492.jpg | W40: 0 | X40: FALSE | Y40: Gauci | Z40: 0.1 | AA40: FALSE | AC40: u | AD40: 2 | AE40: 7 | AF40: 0 | AG40: 0 | AH40: 0 | AI40: 17885 | AJ40: 0 | AK40: 0 | AL40: 0 | AM40: Gauci | AO40: 13 | AP40: 45323 | AQ40: 36711 | AR40: FALSE | AS40: p462492 | AT40: 0 | AU40: 0 | AV40: 0 | AW40: 0 | AX40: 0 | AY40: 0 | AZ40: 0 | BA40: 0 | BB40: 0 | BC40: 0 | BD40: 0 | BE40: 0 | BF40: 0 | BG40: 0 | BH40: 0 | BI40: 0 | BJ40: 0 | BK40: 0 | BL40: 0 | BM40: 0 | BN40: 0 | BO40: 0 | BP40: 0 | BQ40: 0 | BR40: 0 | BS40: 0 | CA40: 598 | CB40: 75 | CC40: 589 | CD40: 64 | CE40: 558 | CF40: 49 | CG40: 601 | CH40: 75 | CI40: 0 | CJ40: 0 | CK40: 0 | CL40: 0 | CM40: 0 | CN40: 0 | CO40: 700 | CP40: 53 | CQ40: 487 | CR40: 67 | CS40: 609 | CT40: 75 | CU40: 511 | CV40: 74 | CW40: 0 | CX40: 0 | CY40: 0 | CZ40: =O40&" "&Y40 -> Joe Gauci | DA40: =VLOOKUP(CZ40,[1]FINAL!$A$1:$AP$1000,MATCH("Element No.",[1]FINAL!$A$1:$AP$1,0),0) -> #N/A
A41: TRUE | B41: FALSE | C41: 0 | D41: 0 | E41: 462381 | F41: 0 | G41: 0 | H41: 0 | I41: 0 | J41: 0 | K41: 1 | L41: 0 | M41: 0 | N41: 0 | O41: Filip | P41: 0 | Q41: =DA41 -> #N/A | R41: FALSE | S41: Has joined Stevenage permanently. | T41: 2025-07-30T14:08:21.698398Z | U41: 40 | V41: 462381.jpg | W41: 0 | X41: FALSE | Y41: Marschall | Z41: 0 | AA41: FALSE | AC41: u | AD41: 2 | AE41: 7 | AF41: 0 | AG41: 0 | AH41: 0 | AI41: 1303 | AJ41: 0 | AK41: 0 | AL41: 0 | AM41: Marschall | AO41: 241 | AP41: 44543 | AQ41: 37735 | AR41: FALSE | AS41: p462381 | AT41: 0 | AU41: 0 | AV41: 0 | AW41: 0 | AX41: 0 | AY41: 0 | AZ41: 0 | BA41: 0 | BB41: 0 | BC41: 0 | BD41: 0 | BE41: 0 | BF41: 0 | BG41: 0 | BH41: 0 | BI41: 0 | BJ41: 0 | BK41: 0 | BL41: 0 | BM41: 0 | BN41: 0 | BO41: 0 | BP41: 0 | BQ41: 0 | BR41: 0 | BS41: 0 | CA41: 597 | CB41: 74 | CC41: 588 | CD41: 63 | CE41: 557 | CF41: 48 | CG41: 600 | CH41: 74 | CI41: 0 | CJ41: 0 | CK41: 0 | CL41: 0 | CM41: 0 | CN41: 0 | CO41: 699 | CP41: 52 | CQ41: 486 | CR41: 66 | CS41: 608 | CT41: 74 | CU41: 761 | CV41: 88 | CW41: 0 | CX41: 0 | CY41: 0 | CZ41: =O41&" "&Y41 -> Filip Marschall | DA41: =VLOOKUP(CZ41,[1]FINAL!$A$1:$AP$1000,MATCH("Element No.",[1]FINAL!$A$1:$AP$1,0),0) -> #N/A
A42: TRUE | B42: FALSE | C42: 100 | D42: 100 | E42: 199796 | F42: 0 | G42: 0 | H42: 1 | I42: -1 | J42: 2 | K42: 2 | L42: 1.5 | M42: 1.3 | N42: 1 | O42: Matty | P42: 1.8 | Q42: =DA42 -> 32 | R42: FALSE | T42: 2026-03-05T00:00:08.205820Z | U42: 46 | V42: 199796.jpg | W42: 3.3 | X42: FALSE | Y42: Cash | Z42: 7.4 | AA42: FALSE | AC42: a | AD42: 2 | AE42: 7 | AF42: 117 | AG42: 2994809 | AH42: 0 | AI42: 2459799 | AJ42: 0 | AK42: 0.4 | AL42: 25.4 | AM42: Cash | AO42: 172 | AP42: 44077 | AQ42: 35649 | AR42: FALSE | AS42: p199796 | AT42: 3016 | AU42: 3 | AV42: 3 | AW42: 8 | AX42: 38 | AY42: 0 | AZ42: 0 | BA42: 0 | BB42: 9 | BC42: 0 | BD42: 0 | BE42: 7 | BF42: 450 | BG42: 643 | BH42: 510.7 | BI42: 221 | BJ42: 137.5 | BK42: 120 | BL42: 88 | BM42: 66 | BN42: 186 | BO42: 34 | BP42: 1.14 | BQ42: 2.94 | BR42: 4.08 | BS42: 45.45 | BT42: 3 | CA42: 70 | CB42: 32 | CC42: 57 | CD42: 8 | CE42: 163 | CF42: 35 | CG42: 77 | CH42: 15 | CI42: 0.03 | CJ42: 0 | CK42: 0.09 | CL42: 0.12 | CM42: 1.36 | CN42: 1.13 | CO42: 397 | CP42: 67 | CQ42: 199 | CR42: 68 | CS42: 145 | CT42: 52 | CU42: 59 | CV42: 17 | CW42: 1.01 | CX42: 0.24 | CY42: 5.55 | CZ42: =O42&" "&Y42 -> Matty Cash | DA42: =VLOOKUP(CZ42,[1]FINAL!$A$1:$AP$1000,MATCH("Element No.",[1]FINAL!$A$1:$AP$1,0),0) -> 32
A43: TRUE | B43: FALSE | C43: 100 | D43: 100 | E43: 101188 | F43: 0 | G43: 0 | H43: 0 | I43: 0 | J43: 1 | K43: 2 | L43: 1.3 | M43: 0.7 | N43: 0 | O43: Lucas | P43: 1.2 | Q43: =DA43 -> 30 | R43: FALSE | T43: 2025-10-23T13:30:07.954318Z | U43: 45 | V43: 101188.jpg | W43: 3.1 | X43: FALSE | Y43: Digne | Z43: 1.5 | AA43: FALSE | AC43: a | AD43: 2 | AE43: 7 | AF43: 97 | AG43: 355694 | AH43: 0 | AI43: 398719 | AJ43: 0 | AK43: 0.3 | AL43: 21.6 | AM43: Digne | AO43: 73 | AP43: 44574 | AQ43: 34170 | AR43: FALSE | AS43: p101188 | AT43: 1842 | AU43: 0 | AV43: 7 | AW43: 7 | AX43: 23 | AY43: 0 | AZ43: 0 | BA43: 0 | BB43: 3 | BC43: 0 | BD43: 0 | BE43: 5 | BF43: 381 | BG43: 400.2 | BH43: 455.5 | BI43: 130 | BJ43: 98.5 | BK43: 77 | BL43: 63 | BM43: 36 | BN43: 113 | BO43: 21 | BP43: 0.67 | BQ43: 3.28 | BR43: 3.95 | BS43: 27.79 | BT43: 2 | BV43: 2 | CA43: 183 | CB43: 75 | CC43: 72 | CD43: 15 | CE43: 251 | CF43: 65 | CG43: 154 | CH43: 51 | CI43: 0.03 | CJ43: 0 | CK43: 0.16 | CL43: 0.19 | CM43: 1.36 | CN43: 1.12 | CO43: 411 | CP43: 74 | CQ43: 249 | CR43: 92 | CS43: 178 | CT43: 68 | CU43: 165 | CV43: 65 | CW43: 1.03 | CX43: 0.34 | CY43: 5.52 | CZ43: =O43&" "&Y43 -> Lucas Digne | DA43: =VLOOKUP(CZ43,[1]FINAL!$A$1:$AP$1000,MATCH("Element No.",[1]FINAL!$A$1:$AP$1,0),0) -> 30
A44: TRUE | B44: FALSE | C44: 100 | D44: 100 | E44: 199798 | F44: 0 | G44: 0 | H44: -1 | I44: 1 | J44: 0 | K44: 2 | L44: 0.5 | M44: 0 | N44: 0 | O44: Ezri | P44: 0.5 | Q44: =DA44 -> 31 | R44: FALSE | T44: 2025-11-18T09:30:07.536725Z | U44: 44 | V44: 199798.jpg | W44: 2.9 | X44: FALSE | Y44: Konsa Ngoyo | Z44: 7 | AA44: FALSE | AC44: a | AD44: 2 | AE44: 7 | AF44: 100 | AG44: 836516 | AH44: 0 | AI44: 2247010 | AJ44: 0 | AK44: 0.1 | AL44: 22.7 | AM44: Konsa | AO44: 241 | AP44: 43657 | AQ44: 35726 | AR44: FALSE | AS44: p199798 | AT44: 3035 | AU44: 0 | AV44: 1 | AW44: 9 | AX44: 44 | AY44: 0 | AZ44: 0 | BA44: 0 | BB44: 0 | BC44: 1 | BD44: 0 | BE44: 3 | BF44: 497 | BG44: 601.4 | BH44: 108.3 | BI44: 124 | BJ44: 84 | BK44: 174 | BL44: 108 | BM44: 22 | BN44: 196 | BO44: 34 | BP44: 1.27 | BQ44: 0.59 | BR44: 1.86 | BS44: 48.93 | CA44: 83 | CB44: 35 | CC44: 293 | CD44: 91 | CE44: 258 | CF44: 68 | CG44: 193 | CH44: 67 | CI44: 0.04 | CJ44: 0 | CK44: 0.02 | CL44: 0.06 | CM44: 1.45 | CN44: 1.3 | CO44: 538 | CP44: 106 | CQ44: 330 | CR44: 117 | CS44: 205 | CT44: 81 | CU44: 62 | CV44: 19 | CW44: 1.01 | CX44: 0.27 | CY44: 5.81 | CZ44: =O44&" "&Y44 -> Ezri Konsa Ngoyo | DA44: =VLOOKUP(CZ44,[1]FINAL!$A$1:$AP$1000,MATCH("Element No.",[1]FINAL!$A$1:$AP$1,0),0) -> 31
A45: TRUE | B45: FALSE | E45: 441302 | F45: 0 | G45: 0 | H45: -3 | I45: 3 | J45: 0 | K45: 2 | L45: 0.3 | M45: 1.5 | N45: 5 | O45: Ian | P45: 2 | Q45: =DA45 -> 36 | R45: FALSE | U45: 42 | V45: 441302.jpg | W45: 1.8 | X45: FALSE | Y45: Maatsen | Z45: 0.5 | AA45: FALSE | AC45: a | AD45: 2 | AE45: 7 | AF45: 54 | AG45: 89595 | AH45: 0 | AI45: 125987 | AJ45: 0 | AK45: 0.5 | AL45: 12.9 | AM45: Maatsen | AO45: 152 | AP45: 45471 | AQ45: 37325 | AR45: FALSE | AS45: p441302 | AT45: 1590 | AU45: 0 | AV45: 1 | AW45: 2 | AX45: 27 | AY45: 0 | AZ45: 0 | BA45: 0 | BB45: 2 | BC45: 0 | BD45: 0 | BE45: 1 | BF45: 242 | BG45: 336.6 | BH45: 373.4 | BI45: 231 | BJ45: 94.3 | BK45: 85 | BL45: 82 | BM45: 43 | BN45: 128 | BO45: 17 | BP45: 1.26 | BQ45: 2.39 | BR45: 3.65 | BS45: 26.64 | CA45: 219 | CB45: 89 | CC45: 105 | CD45: 26 | CE45: 155 | CF45: 32 | CG45: 165 | CH45: 55 | CI45: 0.07 | CJ45: 0 | CK45: 0.14 | CL45: 0.21 | CM45: 1.51 | CN45: 1.53 | CO45: 645 | CP45: 145 | CQ45: 176 | CR45: 55 | CS45: 377 | CT45: 140 | CU45: 262 | CV45: 97 | CW45: 0.96 | CX45: 0.11 | CY45: 7.25 | CZ45: =O45&" "&Y45 -> Ian Maatsen | DA45: =VLOOKUP(CZ45,[1]FINAL!$A$1:$AP$1000,MATCH("Element No.",[1]FINAL!$A$1:$AP$1,0),0) -> 36
A46: TRUE | B46: FALSE | C46: 100 | D46: 100 | E46: 149484 | F46: 0 | G46: 0 | H46: -2 | I46: 2 | J46: 1 | K46: 2 | L46: -0.3 | M46: 0.7 | N46: 4 | O46: Tyrone | P46: 1.2 | Q46: =DA46 -> 33 | R46: FALSE | T46: 2026-04-12T21:30:08.045496Z | U46: 43 | V46: 149484.jpg | W46: 2.9 | X46: FALSE | Y46: Mings | Z46: 0.6 | AA46: FALSE | AC46: a | AD46: 2 | AE46: 7 | AF46: 50 | AG46: 161621 | AH46: 0 | AI46: 216139 | AJ46: 0 | AK46: 0.3 | AL46: 11.6 | AM46: Mings | AO46: 241 | AP46: 43654 | AQ46: 34041 | AR46: FALSE | AS46: p149484 | AT46: 1322 | AU46: 0 | AV46: 1 | AW46: 3 | AX46: 23 | AY46: 0 | AZ46: 0 | BA46: 0 | BB46: 1 | BC46: 0 | BD46: 0 | BE46: 4 | BF46: 169 | BG46: 282.6 | BH46: 80.5 | BI46: 105 | BJ46: 46.8 | BK46: 102 | BL46: 47 | BM46: 5 | BN46: 107 | BO46: 15 | BP46: 1.3 | BQ46: 0.42 | BR46: 1.72 | BS46: 23.37 | CA46: 258 | CB46: 102 | CC46: 327 | CD46: 110 | CE46: 278 | CF46: 80 | CG46: 319 | CH46: 105 | CI46: 0.09 | CJ46: 0 | CK46: 0.03 | CL46: 0.12 | CM46: 1.59 | CN46: 1.57 | CO46: 587 | CP46: 125 | CQ46: 244 | CR46: 88 | CS46: 204 | CT46: 80 | CU46: 246 | CV46: 92 | CW46: 1.02 | CX46: 0.2 | CY46: 7.28 | CZ46: =O46&" "&Y46 -> Tyrone Mings | DA46: =VLOOKUP(CZ46,[1]FINAL!$A$1:$AP$1000,MATCH("Element No.",[1]FINAL!$A$1:$AP$1,0),0) -> 33
A47: TRUE | B47: FALSE | C47: 100 | D47: 100 | E47: 244954 | F47: 0 | G47: 0 | H47: -2 | I47: 2 | J47: 0 | K47: 2 | L47: 0.7 | M47: 0.7 | N47: 1 | O47: Pau | P47: 1.2 | Q47: =DA47 -> 34 | R47: FALSE | T47: 2025-12-12T00:00:09.857457Z | U47: 43 | V47: 244954.jpg | W47: 3 | X47: FALSE | Y47: Torres | Z47: 0.3 | AA47: FALSE | AC47: a | AD47: 2 | AE47: 7 | AF47: 64 | AG47: 75312 | AH47: 0 | AI47: 101789 | AJ47: 0 | AK47: 0.3 | AL47: 14.9 | AM47: Pau | AO47: 200 | AP47: 45119 | AQ47: 35446 | AR47: FALSE | AS47: p244954 | AT47: 1673 | AU47: 0 | AV47: 2 | AW47: 5 | AX47: 19 | AY47: 1 | AZ47: 0 | BA47: 0 | BB47: 1 | BC47: 0 | BD47: 0 | BE47: 2 | BF47: 280 | BG47: 321.8 | BH47: 47.1 | BI47: 79 | BJ47: 45.1 | BK47: 90 | BL47: 79 | BM47: 22 | BN47: 112 | BO47: 18 | BP47: 1.33 | BQ47: 0.39 | BR47: 1.72 | BS47: 22.81 | CA47: 233 | CB47: 92 | CC47: 376 | CD47: 135 | CE47: 311 | CF47: 97 | CG47: 325 | CH47: 110 | CI47: 0.07 | CJ47: 0 | CK47: 0.02 | CL47: 0.09 | CM47: 1.23 | CN47: 1.02 | CO47: 594 | CP47: 130 | CQ47: 245 | CR47: 89 | CS47: 191 | CT47: 75 | CU47: 327 | CV47: 120 | CW47: 0.97 | CX47: 0.27 | CY47: 6.03 | CZ47: =O47&" "&Y47 -> Pau Torres | DA47: =VLOOKUP(CZ47,[1]FINAL!$A$1:$AP$1000,MATCH("Element No.",[1]FINAL!$A$1:$AP$1,0),0) -> 34
A48: TRUE | B48: FALSE | C48: 100 | D48: 100 | E48: 606798 | F48: 0 | G48: 0 | H48: -1 | I48: 1 | J48: 0 | K48: 2 | L48: -0.5 | M48: -0.3 | N48: 1 | O48: Andrés | P48: 0.2 | Q48: =DA48 -> 38 | R48: FALSE | T48: 2026-01-29T12:00:08.835746Z | U48: 39 | V48: 606798.jpg | W48: 0.8 | X48: FALSE | Y48: García | Z48: 0.2 | AA48: FALSE | AC48: a | AD48: 2 | AE48: 7 | AF48: 5 | AG48: 30457 | AH48: 0 | AI48: 43192 | AJ48: 0 | AK48: 0.1 | AL48: 1.3 | AM48: A.García | AO48: 200 | AP48: 45678 | AQ48: 37659 | AR48: FALSE | AS48: p606798 | AT48: 83 | AU48: 0 | AV48: 0 | AW48: 0 | AX48: 3 | AY48: 0 | AZ48: 0 | BA48: 0 | BB48: 0 | BC48: 0 | BD48: 0 | BE48: 0 | BF48: 12 | BG48: 17.8 | BH48: 3.2 | BI48: 2 | BJ48: 2.3 | BK48: 5 | BL48: 4 | BM48: 5 | BN48: 10 | BO48: 1 | BP48: 0 | BQ48: 0.01 | BR48: 0.01 | BS48: 2.74 | CA48: 468 | CB48: 170 | CC48: 470 | CD48: 169 | CE48: 456 | CF48: 171 | CG48: 486 | CH48: 173 | CI48: 0 | CJ48: 0 | CK48: 0.01 | CL48: 0.01 | CM48: 2.97 | CN48: 3.25 | CO48: 799 | CP48: 233 | CQ48: 358 | CR48: 126 | CS48: 529 | CT48: 179 | CU48: 378 | CV48: 136 | CW48: 1.08 | CX48: 0 | CY48: 10.84 | CZ48: =O48&" "&Y48 -> Andrés García | DA48: =VLOOKUP(CZ48,[1]FINAL!$A$1:$AP$1000,MATCH("Element No.",[1]FINAL!$A$1:$AP$1,0),0) -> 38
A49: TRUE | B49: FALSE | C49: 0 | D49: 0 | E49: 106468 | F49: 0 | G49: 0 | H49: 0 | I49: 0 | J49: 0 | K49: 2 | L49: 0 | M49: 0 | N49: 0 | O49: Álex | P49: 0 | Q49: =DA49 -> #N/A | R49: FALSE | S49: Has joined Girona permanently. | T49: 2025-08-26T13:45:03.013808Z | U49: 40 | V49: 106468.jpg | W49: 0 | X49: FALSE | Y49: Moreno Lopera | Z49: 1.5 | AA49: FALSE | AC49: u | AD49: 2 | AE49: 7 | AF49: 0 | AG49: 44476 | AH49: 0 | AI49: 893174 | AJ49: 0 | AK49: 0 | AL49: 0 | AM49: Alex Moreno | AO49: 200 | AP49: 44937 | AQ49: 34128 | AR49: FALSE | AS49: p106468 | AT49: 0 | AU49: 0 | AV49: 0 | AW49: 0 | AX49: 0 | AY49: 0 | AZ49: 0 | BA49: 0 | BB49: 0 | BC49: 0 | BD49: 0 | BE49: 0 | BF49: 0 | BG49: 0 | BH49: 0 | BI49: 0 | BJ49: 0 | BK49: 0 | BL49: 0 | BM49: 0 | BN49: 0 | BO49: 0 | BP49: 0 | BQ49: 0 | BR49: 0 | BS49: 0 | CA49: 582 | CB49: 212 | CC49: 570 | CD49: 211 | CE49: 539 | CF49: 207 | CG49: 585 | CH49: 212 | CI49: 0 | CJ49: 0 | CK49: 0 | CL49: 0 | CM49: 0 | CN49: 0 | CO49: 676 | CP49: 161 | CQ49: 466 | CR49: 174 | CS49: 593 | CT49: 212 | CU49: 164 | CV49: 64 | CW49: 0 | CX49: 0 | CY49: 0 | CZ49: =O49&" "&Y49 -> Álex Moreno Lopera | DA49: =VLOOKUP(CZ49,[1]FINAL!$A$1:$AP$1000,MATCH("Element No.",[1]FINAL!$A$1:$AP$1,0),0) -> #N/A
A50: TRUE | B50: FALSE | C50: 100 | D50: 100 | E50: 515597 | F50: 0 | G50: 0 | H50: 0 | I50: 0 | J50: 0 | K50: 2 | L50: 0.5 | M50: 0.5 | N50: 2 | O50: Lamare | P50: 1 | Q50: =DA50 -> 35 | R50: FALSE | T50: 2025-11-20T10:30:09.224047Z | U50: 40 | V50: 515597.jpg | W50: 1.4 | X50: FALSE | Y50: Bogarde | Z50: 0.5 | AA50: FALSE | AC50: a | AD50: 2 | AE50: 7 | AF50: 40 | AG50: 114072 | AH50: 0 | AI50: 100401 | AJ50: 0 | AK50: 0.2 | AL50: 10 | AM50: Bogarde | AO50: 152 | AP50: 44203 | AQ50: 37991 | AR50: FALSE | AS50: p515597 | AT50: 1042 | AU50: 0 | AV50: 0 | AW50: 2 | AX50: 17 | AY50: 0 | AZ50: 0 | BA50: 0 | BB50: 5 | BC50: 0 | BD50: 0 | BE50: 4 | BF50: 121 | BG50: 133 | BH50: 59.4 | BI50: 14 | BJ50: 20.6 | BK50: 34 | BL50: 43 | BM50: 26 | BN50: 60 | BO50: 11 | BP50: 0 | BQ50: 0.2 | BR50: 0.2 | BS50: 15.38 | CA50: 365 | CB50: 135 | CC50: 356 | CD50: 124 | CE50: 416 | CF50: 153 | CG50: 393 | CH50: 138 | CI50: 0 | CJ50: 0 | CK50: 0.02 | CL50: 0.02 | CM50: 1.33 | CN50: 1.47 | CO50: 720 | CP50: 184 | CQ50: 273 | CR50: 96 | CS50: 430 | CT50: 155 | CU50: 263 | CV50: 98 | CW50: 0.95 | CX50: 0.17 | CY50: 5.18 | CZ50: =O50&" "&Y50 -> Lamare Bogarde | DA50: =VLOOKUP(CZ50,[1]FINAL!$A$1:$AP$1000,MATCH("Element No.",[1]FINAL!$A$1:$AP$1,0),0) -> 35
A51: TRUE | B51: FALSE | C51: 0 | D51: 0 | E51: 514315 | F51: 0 | G51: 0 | H51: -2 | I51: 2 | J51: 0 | K51: 2 | L51: 0 | M51: 0 | N51: 0 | O51: Lino | P51: 0 | Q51: =DA51 -> #N/A | R51: FALSE | S51: has joined Rotherham on loan for the rest of the season. | T51: 2026-02-06T22:51:55.055374Z | U51: 38 | V51: 514315.jpg | W51: 0 | X51: FALSE | Y51: da Cruz Sousa | Z51: 0.2 | AA51: FALSE | AC51: u | AD51: 2 | AE51: 7 | AF51: 0 | AG51: 22076 | AH51: 0 | AI51: 40217 | AJ51: 0 | AK51: 0 | AL51: 0 | AM51: Sousa | AR51: FALSE | AS51: p514315 | AT51: 0 | AU51: 0 | AV51: 0 | AW51: 0 | AX51: 0 | AY51: 0 | AZ51: 0 | BA51: 0 | BB51: 0 | BC51: 0 | BD51: 0 | BE51: 0 | BF51: 0 | BG51: 0 | BH51: 0 | BI51: 0 | BJ51: 0 | BK51: 0 | BL51: 0 | BM51: 0 | BN51: 0 | BO51: 0 | BP51: 0 | BQ51: 0 | BR51: 0 | BS51: 0 | CA51: 540 | CB51: 194 | CC51: 522 | CD51: 193 | CE51: 490 | CF51: 188 | CG51: 543 | CH51: 194 | CI51: 0 | CJ51: 0 | CK51: 0 | CL51: 0 | CM51: 0 | CN51: 0 | CO51: 819 | CP51: 249 | CQ51: 419 | CR51: 152 | CS51: 551 | CT51: 194 | CU51: 361 | CV51: 131 | CW51: 0 | CX51: 0 | CY51: 0 | CZ51: =O51&" "&Y51 -> Lino da Cruz Sousa | DA51: =VLOOKUP(CZ51,[1]FINAL!$A$1:$AP$1000,MATCH("Element No.",[1]FINAL!$A$1:$AP$1,0),0) -> #N/A
A52: TRUE | B52: FALSE | C52: 0 | D52: 0 | E52: 587178 | F52: 0 | G52: 0 | H52: 0 | I52: 0 | J52: 0 | K52: 2 | L52: 0 | M52: 0 | N52: 0 | O52: Yasin | P52: 0 | Q52: =DA52 -> #N/A | R52: FALSE | S52: has joined Anderlecht on loan for the rest of the season. | T52: 2025-09-22T21:15:59.805053Z | U52: 40 | V52: 587178.jpg | W52: 0 | X52: FALSE | Y52: Özcan | Z52: 0.1 | AA52: FALSE | AC52: u | AD52: 2 | AE52: 7 | AF52: 0 | AG52: 4656 | AH52: 0 | AI52: 21237 | AJ52: 0 | AK52: 0 | AL52: 0 | AM52: Yasin | AO52: 219 | AP52: 45809 | AQ52: 38827 | AR52: FALSE | AS52: p587178 | AT52: 0 | AU52: 0 | AV52: 0 | AW52: 0 | AX52: 0 | AY52: 0 | AZ52: 0 | BA52: 0 | BB52: 0 | BC52: 0 | BD52: 0 | BE52: 0 | BF52: 0 | BG52: 0 | BH52: 0 | BI52: 0 | BJ52: 0 | BK52: 0 | BL52: 0 | BM52: 0 | BN52: 0 | BO52: 0 | BP52: 0 | BQ52: 0 | BR52: 0 | BS52: 0 | CA52: 627 | CB52: 237 | CC52: 619 | CD52: 236 | CE52: 589 | CF52: 233 | CG52: 630 | CH52: 237 | CI52: 0 | CJ52: 0 | CK52: 0 | CL52: 0 | CM52: 0 | CN52: 0 | CO52: 736 | CP52: 196 | CQ52: 519 | CR52: 203 | CS52: 637 | CT52: 236 | CU52: 469 | CV52: 174 | CW52: 0 | CX52: 0 | CY52: 0 | CZ52: =O52&" "&Y52 -> Yasin Özcan | DA52: =VLOOKUP(CZ52,[1]FINAL!$A$1:$AP$1000,MATCH("Element No.",[1]FINAL!$A$1:$AP$1,0),0) -> #N/A
A53: TRUE | B53: FALSE | C53: 100 | D53: 100 | E53: 244850 | F53: 0 | G53: 0 | H53: 3 | I53: -3 | J53: 4 | K53: 3 | L53: 3.7 | M53: 3.3 | N53: 0 | O53: Morgan | P53: 3.8 | Q53: =DA53 -> 40 | R53: FALSE | T53: 2025-08-10T22:00:04.458365Z | U53: 73 | V53: 244850.jpg | W53: 4.6 | X53: FALSE | Y53: Rogers | Z53: 20.2 | AA53: FALSE | AC53: a | AD53: 2 | AE53: 7 | AF53: 169 | AG53: 6873325 | AH53: 0 | AI53: 5463430 | AJ53: 0 | AK53: 0.5 | AL53: 23.2 | AM53: Rogers | AO53: 241 | AP53: 45323 | AQ53: 37463 | AR53: FALSE | AS53: p244850 | AT53: 3280 | AU53: 10 | AV53: 8 | AW53: 9 | AX53: 48 | AY53: 0 | AZ53: 0 | BA53: 0 | BB53: 7 | BC53: 0 | BD53: 0 | BE53: 17 | BF53: 605 | BG53: 746.2 | BH53: 706.2 | BI53: 871 | BJ53: 232 | BK53: 49 | BL53: 139 | BM53: 42 | BN53: 230 | BO53: 37 | BP53: 6.84 | BQ53: 4.32 | BR53: 11.16 | BS53: 51.55 | BV53: 1 | CA53: 41 | CB53: 11 | CC53: 26 | CD53: 25 | CE53: 8 | CF53: 3 | CG53: 9 | CH53: 6 | CI53: 0.19 | CJ53: 0 | CK53: 0.12 | CL53: 0.31 | CM53: 1.41 | CN53: 1.32 | CO53: 28 | CP53: 17 | CQ53: 87 | CR53: 38 | CS53: 27 | CT53: 12 | CU53: 13 | CV53: 4 | CW53: 1.02 | CX53: 0.25 | CY53: 6.31 | CZ53: =O53&" "&Y53 -> Morgan Rogers | DA53: =VLOOKUP(CZ53,[1]FINAL!$A$1:$AP$1000,MATCH("Element No.",[1]FINAL!$A$1:$AP$1,0),0) -> 40
A54: TRUE | B54: FALSE | C54: 100 | D54: 100 | E54: 166989 | F54: 0 | G54: 0 | H54: -1 | I54: 1 | J54: 0 | K54: 3 | L54: 2 | M54: 1.7 | N54: 1 | O54: Youri | P54: 2.2 | Q54: =DA54 -> 43 | R54: FALSE | T54: 2026-01-26T04:00:07.415161Z | U54: 59 | V54: 166989.jpg | W54: 2.7 | X54: FALSE | Y54: Tielemans | Z54: 0.7 | AA54: FALSE | AC54: a | AD54: 2 | AE54: 7 | AF54: 68 | AG54: 171924 | AH54: 0 | AI54: 356117 | AJ54: 0 | AK54: 0.4 | AL54: 11.5 | AM54: Tielemans | AO54: 21 | AP54: 45091 | AQ54: 35557 | AR54: FALSE | AS54: p166989 | AT54: 1857 | AU54: 0 | AV54: 4 | AW54: 4 | AX54: 27 | AY54: 0 | AZ54: 0 | BA54: 0 | BB54: 0 | BC54: 0 | BD54: 0 | BE54: 3 | BF54: 417 | BG54: 432 | BH54: 513.6 | BI54: 184 | BJ54: 113.1 | BK54: 51 | BL54: 94 | BM54: 58 | BN54: 203 | BO54: 21 | BP54: 1.14 | BQ54: 3.26 | BR54: 4.4 | BS54: 31.34 | BT54: 5 | CA54: 166 | CB54: 61 | CC54: 56 | CD54: 48 | CE54: 206 | CF54: 107 | CG54: 117 | CH54: 66 | CI54: 0.06 | CJ54: 0 | CK54: 0.16 | CL54: 0.22 | CM54: 1.52 | CN54: 1.31 | CO54: 89 | CP54: 57 | CQ54: 171 | CR54: 78 | CS54: 248 | CT54: 101 | CU54: 242 | CV54: 84 | CW54: 1.02 | CX54: 0.19 | CY54: 9.84 | CZ54: =O54&" "&Y54 -> Youri Tielemans | DA54: =VLOOKUP(CZ54,[1]FINAL!$A$1:$AP$1000,MATCH("Element No.",[1]FINAL!$A$1:$AP$1,0),0) -> 43
A55: TRUE | B55: FALSE | C55: 100 | D55: 100 | E55: 215711 | F55: 0 | G55: 0 | H55: 0 | I55: 0 | J55: 0 | K55: 3 | L55: 0.3 | M55: 1.3 | N55: 5 | O55: Leon | P55: 1.8 | Q55: =DA55 -> 44 | R55: FALSE | T55: 2025-08-20T13:31:56.843157Z | U55: 55 | V55: 215711.jpg | W55: 1.6 | X55: FALSE | Y55: Bailey | Z55: 0.1 | AA55: FALSE | AC55: a | AD55: 2 | AE55: 7 | AF55: 21 | AG55: 10030 | AH55: 0 | AI55: 52941 | AJ55: 0 | AK55: 0.3 | AL55: 3.8 | AM55: Bailey | AO55: 107 | AP55: 44412 | AQ55: 35651 | AR55: FALSE | AS55: p215711 | AT55: 450 | AU55: 0 | AV55: 2 | AW55: 0 | AX55: 9 | AY55: 0 | AZ55: 0 | BA55: 0 | BB55: 1 | BC55: 0 | BD55: 0 | BE55: 0 | BF55: 69 | BG55: 71.2 | BH55: 160.4 | BI55: 69 | BJ55: 30.1 | BK55: 7 | BL55: 31 | BM55: 10 | BN55: 48 | BO55: 3 | BP55: 0.5 | BQ55: 1.46 | BR55: 1.96 | BS55: 7.03 | BT55: 4 | CA55: 411 | CB55: 179 | CC55: 237 | CD55: 152 | CE55: 328 | CF55: 169 | CG55: 369 | CH55: 174 | CI55: 0.1 | CJ55: 0 | CK55: 0.29 | CL55: 0.39 | CM55: 1.41 | CN55: 1.8 | CO55: 138 | CP55: 86 | CQ55: 209 | CR55: 93 | CS55: 417 | CT55: 179 | CU55: 467 | CV55: 161 | CW55: 0.6 | CX55: 0 | CY55: 9.6 | CZ55: =O55&" "&Y55 -> Leon Bailey | DA55: =VLOOKUP(CZ55,[1]FINAL!$A$1:$AP$1000,MATCH("Element No.",[1]FINAL!$A$1:$AP$1,0),0) -> 44
A56: TRUE | B56: FALSE | C56: 100 | D56: 100 | E56: 195546 | F56: 0 | G56: 0 | H56: -2 | I56: 2 | J56: 3 | K56: 3 | L56: 2.3 | M56: 3.3 | N56: 6 | O56: Emiliano | P56: 3.8 | Q56: =DA56 -> 41 | R56: FALSE | T56: 2026-03-16T00:00:09.650848Z | U56: 53 | V56: 195546.jpg | W56: 2.8 | X56: FALSE | Y56: Buendía Stati | Z56: 0.4 | AA56: FALSE | AC56: a | AD56: 2 | AE56: 7 | AF56: 102 | AG56: 238478 | AH56: 0 | AI56: 218449 | AJ56: 0 | AK56: 0.7 | AL56: 19.2 | AM56: Buendía | AO56: 10 | AP56: 44357 | AQ56: 35424 | AR56: FALSE | AS56: p195546 | AT56: 1753 | AU56: 6 | AV56: 2 | AW56: 3 | AX56: 24 | AY56: 0 | AZ56: 0 | BA56: 0 | BB56: 6 | BC56: 0 | BD56: 0 | BE56: 10 | BF56: 382 | BG56: 427 | BH56: 402.1 | BI56: 398 | BJ56: 121.4 | BK56: 39 | BL56: 109 | BM56: 49 | BN56: 197 | BO56: 21 | BP56: 3.38 | BQ56: 2.23 | BR56: 5.61 | BS56: 28.03 | BV56: 6 | BX56: 2 | CA56: 167 | CB56: 62 | CC56: 90 | CD56: 65 | CE56: 80 | CF56: 47 | CG56: 98 | CH56: 57 | CI56: 0.17 | CJ56: 0 | CK56: 0.11 | CL56: 0.28 | CM56: 1.44 | CN56: 1.23 | CO56: 182 | CP56: 115 | CQ56: 82 | CR56: 35 | CS56: 228 | CT56: 88 | CU56: 294 | CV56: 102 | CW56: 1.08 | CX56: 0.15 | CY56: 10.11 | CZ56: =O56&" "&Y56 -> Emiliano Buendía Stati | DA56: =VLOOKUP(CZ56,[1]FINAL!$A$1:$AP$1000,MATCH("Element No.",[1]FINAL!$A$1:$AP$1,0),0) -> 41
A57: TRUE | B57: FALSE | C57: 0 | D57: 0 | E57: 469247 | F57: 0 | G57: 0 | H57: 0 | I57: 0 | J57: 0 | K57: 3 | L57: 0 | M57: 0 | N57: 0 | O57: Samuel | P57: 0 | Q57: =DA57 -> 49 | R57: FALSE | S57: has joined Pisa on loan for the rest of the season. | T57: 2025-09-22T21:15:59.838578Z | U57: 55 | V57: 469247.jpg | W57: 0 | X57: FALSE | Y57: Iling-Junior | Z57: 0 | AA57: FALSE | AC57: u | AD57: 2 | AE57: 7 | AF57: 0 | AG57: 1383 | AH57: 0 | AI57: 3814 | AJ57: 0 | AK57: 0 | AL57: 0 | AM57: Iling Jr | AO57: 241 | AP57: 45474 | AQ57: 37898 | AR57: FALSE | AS57: p469247 | AT57: 0 | AU57: 0 | AV57: 0 | AW57: 0 | AX57: 0 | AY57: 0 | AZ57: 0 | BA57: 0 | BB57: 0 | BC57: 0 | BD57: 0 | BE57: 0 | BF57: 0 | BG57: 0 | BH57: 0 | BI57: 0 | BJ57: 0 | BK57: 0 | BL57: 0 | BM57: 0 | BN57: 0 | BO57: 0 | BP57: 0 | BQ57: 0 | BR57: 0 | BS57: 0 | CA57: 830 | CB57: 372 | CC57: 830 | CD57: 372 | CE57: 829 | CF57: 372 | CG57: 830 | CH57: 372 | CI57: 0 | CJ57: 0 | CK57: 0 | CL57: 0 | CM57: 0 | CN57: 0 | CO57: 144 | CP57: 91 | CQ57: 814 | CR57: 363 | CS57: 830 | CT57: 372 | CU57: 700 | CV57: 281 | CW57: 0 | CX57: 0 | CY57: 0 | CZ57: =O57&" "&Y57 -> Samuel Iling-Junior | DA57: =VLOOKUP(CZ57,[1]FINAL!$A$1:$AP$1000,MATCH("Element No.",[1]FINAL!$A$1:$AP$1,0),0) -> 49
A58: TRUE | B58: FALSE | C58: 0 | D58: 0 | E58: 204646 | F58: 0 | G58: 0 | H58: -4 | I58: 4 | J58: 1 | K58: 3 | L58: 0 | M58: 0 | N58: 0 | O58: Donyell | P58: 0 | Q58: =DA58 -> #N/A | R58: FALSE | S58: has joined Roma on loan for the rest of the season. | T58: 2026-01-16T15:17:04.828016Z | U58: 51 | V58: 204646.jpg | W58: 2.6 | X58: FALSE | Y58: Malen | Z58: 0.4 | AA58: FALSE | AC58: u | AD58: 2 | AE58: 7 | AF58: 55 | AG58: 172896 | AH58: 0 | AI58: 340842 | AJ58: 0 | AK58: 0 | AL58: 10.8 | AM58: Malen | AO58: 152 | AP58: 45671 | AQ58: 36179 | AR58: FALSE | AS58: p204646 | AT58: 640 | AU58: 4 | AV58: 2 | AW58: 1 | AX58: 10 | AY58: 0 | AZ58: 0 | BA58: 0 | BB58: 0 | BC58: 0 | BD58: 0 | BE58: 3 | BF58: 161 | BG58: 183.4 | BH58: 99.7 | BI58: 290 | BJ58: 56.3 | BK58: 2 | BL58: 10 | BM58: 4 | BN58: 16 | BO58: 5 | BP58: 4.03 | BQ58: 0.35 | BR58: 4.38 | BS58: 10.59 | CA58: 321 | CB58: 141 | CC58: 299 | CD58: 172 | CE58: 120 | CF58: 71 | CG58: 282 | CH58: 143 | CI58: 0.57 | CJ58: 0 | CK58: 0.05 | CL58: 0.62 | CM58: 1.49 | CN58: 1.41 | CO58: 227 | CP58: 139 | CQ58: 782 | CR58: 339 | CS58: 265 | CT58: 108 | CU58: 292 | CV58: 100 | CW58: 0.7 | CX58: 0.14 | CY58: 2.25 | CZ58: =O58&" "&Y58 -> Donyell Malen | DA58: =VLOOKUP(CZ58,[1]FINAL!$A$1:$AP$1000,MATCH("Element No.",[1]FINAL!$A$1:$AP$1,0),0) -> #N/A
A59: TRUE | B59: FALSE | C59: 100 | D59: 100 | E59: 122806 | F59: 0 | G59: 0 | H59: -2 | I59: 2 | J59: 2 | K59: 3 | L59: 2.7 | M59: 2.5 | N59: 1 | O59: John | P59: 3 | Q59: =DA59 -> 45 | R59: FALSE | T59: 2026-05-03T23:00:09.124947Z | U59: 53 | V59: 122806.jpg | W59: 3.4 | X59: FALSE | Y59: McGinn | Z59: 0.7 | AA59: FALSE | AC59: a | AD59: 2 | AE59: 7 | AF59: 103 | AG59: 266912 | AH59: 0 | AI59: 274130 | AJ59: 0 | AK59: 0.6 | AL59: 19.4 | AM59: McGinn | AO59: 243 | AP59: 43320 | AQ59: 34625 | AR59: FALSE | AS59: p122806 | AT59: 2136 | AU59: 5 | AV59: 4 | AW59: 8 | AX59: 28 | AY59: 0 | AZ59: 0 | BA59: 0 | BB59: 5 | BC59: 0 | BD59: 0 | BE59: 6 | BF59: 443 | BG59: 459.8 | BH59: 605.3 | BI59: 309 | BJ59: 137.3 | BK59: 32 | BL59: 89 | BM59: 29 | BN59: 150 | BO59: 28 | BP59: 3 | BQ59: 4.11 | BR59: 7.11 | BS59: 33.08 | CA59: 148 | CB59: 52 | CC59: 37 | CD59: 34 | CE59: 110 | CF59: 67 | CG59: 78 | CH59: 48 | CI59: 0.13 | CJ59: 0 | CK59: 0.17 | CL59: 0.3 | CM59: 1.39 | CN59: 1.18 | CO59: 179 | CP59: 112 | CQ59: 117 | CR59: 53 | CS59: 134 | CT59: 57 | CU59: 233 | CV59: 81 | CW59: 1.18 | CX59: 0.34 | CY59: 6.32 | CZ59: =O59&" "&Y59 -> John McGinn | DA59: =VLOOKUP(CZ59,[1]FINAL!$A$1:$AP$1000,MATCH("Element No.",[1]FINAL!$A$1:$AP$1,0),0) -> 45
A60: TRUE | B60: FALSE | C60: 100 | D60: 100 | E60: 88894 | F60: 0 | G60: 0 | H60: -2 | I60: 2 | J60: 1 | K60: 3 | L60: 2.5 | M60: 3.5 | N60: 5 | O60: Ross | P60: 4 | Q60: =DA60 -> 46 | R60: FALSE | T60: 2025-11-30T22:30:09.043798Z | U60: 48 | V60: 88894.jpg | W60: 2.7 | X60: FALSE | Y60: Barkley | Z60: 0.1 | AA60: FALSE | AC60: a | AD60: 2 | AE60: 7 | AF60: 56 | AG60: 17174 | AH60: 0 | AI60: 18618 | AJ60: 0 | AK60: 0.8 | AL60: 11.7 | AM60: Barkley | AO60: 241 | AP60: 45474 | AQ60: 34308 | AR60: FALSE | AS60: p88894 | AT60: 844 | AU60: 3 | AV60: 2 | AW60: 1 | AX60: 15 | AY60: 0 | AZ60: 0 | BA60: 0 | BB60: 1 | BC60: 0 | BD60: 0 | BE60: 5 | BF60: 221 | BG60: 227.8 | BH60: 162.3 | BI60: 191 | BJ60: 58.1 | BK60: 15 | BL60: 45 | BM60: 14 | BN60: 74 | BO60: 7 | BP60: 1.58 | BQ60: 1.26 | BR60: 2.84 | BS60: 13.2 | CA60: 289 | CB60: 122 | CC60: 231 | CD60: 150 | CE60: 193 | CF60: 103 | CG60: 275 | CH60: 139 | CI60: 0.17 | CJ60: 0 | CK60: 0.13 | CL60: 0.3 | CM60: 1.41 | CN60: 1.6 | CO60: 345 | CP60: 216 | CQ60: 68 | CR60: 28 | CS60: 241 | CT60: 94 | CU60: 510 | CV60: 187 | CW60: 0.75 | CX60: 0.11 | CY60: 7.89 | CZ60: =O60&" "&Y60 -> Ross Barkley | DA60: =VLOOKUP(CZ60,[1]FINAL!$A$1:$AP$1000,MATCH("Element No.",[1]FINAL!$A$1:$AP$1,0),0) -> 46
A61: TRUE | B61: FALSE | C61: 0 | D61: 0 | E61: 491287 | F61: 0 | G61: 0 | H61: 0 | I61: 0 | J61: 0 | K61: 3 | L61: 0 | M61: 0 | N61: 0 | O61: Enzo | P61: 0 | Q61: =DA61 -> #N/A | R61: FALSE | S61: Season-long loan to Benfica | T61: 2025-07-22T13:50:13.193555Z | U61: 50 | V61: 491287.jpg | W61: 0 | X61: FALSE | Y61: Barrenechea | Z61: 0 | AA61: FALSE | AC61: u | AD61: 2 | AE61: 7 | AF61: 0 | AG61: 0 | AH61: 0 | AI61: 36 | AJ61: 0 | AK61: 0 | AL61: 0 | AM61: Barrenechea | AR61: FALSE | AS61: p491287 | AT61: 0 | AU61: 0 | AV61: 0 | AW61: 0 | AX61: 0 | AY61: 0 | AZ61: 0 | BA61: 0 | BB61: 0 | BC61: 0 | BD61: 0 | BE61: 0 | BF61: 0 | BG61: 0 | BH61: 0 | BI61: 0 | BJ61: 0 | BK61: 0 | BL61: 0 | BM61: 0 | BN61: 0 | BO61: 0 | BP61: 0 | BQ61: 0 | BR61: 0 | BS61: 0 | CA61: 812 | CB61: 359 | CC61: 811 | CD61: 359 | CE61: 808 | CF61: 358 | CG61: 812 | CH61: 359 | CI61: 0 | CJ61: 0 | CK61: 0 | CL61: 0 | CM61: 0 | CN61: 0 | CO61: 266 | CP61: 161 | CQ61: 773 | CR61: 332 | CS61: 812 | CT61: 359 | CU61: 840 | CV61: 379 | CW61: 0 | CX61: 0 | CY61: 0 | CZ61: =O61&" "&Y61 -> Enzo Barrenechea | DA61: =VLOOKUP(CZ61,[1]FINAL!$A$1:$AP$1000,MATCH("Element No.",[1]FINAL!$A$1:$AP$1,0),0) -> #N/A
A62: TRUE | B62: FALSE | C62: 0 | D62: 0 | E62: 461421 | F62: 0 | G62: 0 | H62: 0 | I62: 0 | J62: 0 | K62: 3 | L62: 0 | M62: 0 | N62: 0 | O62: Lewis | P62: 0 | Q62: =DA62 -> #N/A | R62: FALSE | S62: Has joined Preston North End on loan for the rest of the season. | T62: 2025-08-26T13:44:19.058961Z | U62: 50 | V62: 461421.jpg | W62: 0 | X62: FALSE | Y62: Dobbin | Z62: 0 | AA62: FALSE | AC62: u | AD62: 2 | AE62: 7 | AF62: 0 | AG62: 889 | AH62: 0 | AI62: 5455 | AJ62: 0 | AK62: 0 | AL62: 0 | AM62: Dobbin | AO62: 241 | AP62: 45466 | AQ62: 37624 | AR62: FALSE | AS62: p461421 | AT62: 0 | AU62: 0 | AV62: 0 | AW62: 0 | AX62: 0 | AY62: 0 | AZ62: 0 | BA62: 0 | BB62: 0 | BC62: 0 | BD62: 0 | BE62: 0 | BF62: 0 | BG62: 0 | BH62: 0 | BI62: 0 | BJ62: 0 | BK62: 0 | BL62: 0 | BM62: 0 | BN62: 0 | BO62: 0 | BP62: 0 | BQ62: 0 | BR62: 0 | BS62: 0 | CA62: 808 | CB62: 356 | CC62: 807 | CD62: 356 | CE62: 804 | CF62: 355 | CG62: 808 | CH62: 356 | CI62: 0 | CJ62: 0 | CK62: 0 | CL62: 0 | CM62: 0 | CN62: 0 | CO62: 262 | CP62: 158 | CQ62: 769 | CR62: 329 | CS62: 808 | CT62: 356 | CU62: 675 | CV62: 271 | CW62: 0 | CX62: 0 | CY62: 0 | CZ62: =O62&" "&Y62 -> Lewis Dobbin | DA62: =VLOOKUP(CZ62,[1]FINAL!$A$1:$AP$1000,MATCH("Element No.",[1]FINAL!$A$1:$AP$1,0),0) -> #N/A
A63: TRUE | B63: FALSE | C63: 0 | D63: 0 | E63: 226944 | F63: 0 | G63: 0 | H63: -1 | I63: 1 | J63: 0 | K63: 3 | L63: 0 | M63: 0 | N63: 0 | O63: Boubacar | P63: 0 | Q63: =DA63 -> 47 | R63: FALSE | S63: Knee injury - Expected back 01 Jun | T63: 2026-05-08T15:30:09.019486Z | U63: 49 | V63: 226944.jpg | W63: 3.4 | X63: FALSE | Y63: Kamara | Z63: 0.2 | AA63: FALSE | AC63: i | AD63: 2 | AE63: 7 | AF63: 61 | AG63: 111587 | AH63: 0 | AI63: 121485 | AJ63: 0 | AK63: 0 | AL63: 12.4 | AM63: Kamara | AO63: 73 | AP63: 44723 | AQ63: 36487 | AR63: FALSE | AS63: p226944 | AT63: 1410 | AU63: 1 | AV63: 3 | AW63: 5 | AX63: 15 | AY63: 0 | AZ63: 0 | BA63: 0 | BB63: 5 | BC63: 0 | BD63: 0 | BE63: 7 | BF63: 282 | BG63: 325 | BH63: 241.3 | BI63: 75 | BJ63: 64.2 | BK63: 46 | BL63: 65 | BM63: 38 | BN63: 149 | BO63: 17 | BP63: 0.53 | BQ63: 0.84 | BR63: 1.36 | BS63: 20.8 | CA63: 230 | CB63: 96 | CC63: 170 | CD63: 112 | CE63: 315 | CF63: 164 | CG63: 254 | CH63: 127 | CI63: 0.03 | CJ63: 0 | CK63: 0.05 | CL63: 0.08 | CM63: 1.33 | CN63: 0.96 | CO63: 308 | CP63: 191 | CQ63: 743 | CR63: 311 | CS63: 129 | CT63: 54 | CU63: 408 | CV63: 140 | CW63: 1.09 | CX63: 0.32 | CY63: 9.51 | CZ63: =O63&" "&Y63 -> Boubacar Kamara | DA63: =VLOOKUP(CZ63,[1]FINAL!$A$1:$AP$1000,MATCH("Element No.",[1]FINAL!$A$1:$AP$1,0),0) -> 47
A64: TRUE | B64: FALSE | C64: 100 | D64: 100 | E64: 449871 | F64: 0 | G64: 0 | H64: -2 | I64: 2 | J64: 0 | K64: 3 | L64: -0.5 | M64: -0.3 | N64: 1 | O64: Amadou | P64: 0.2 | Q64: =DA64 -> 48 | R64: FALSE | T64: 2026-04-26T22:30:07.719459Z | U64: 48 | V64: 449871.jpg | W64: 3 | X64: FALSE | Y64: Onana | Z64: 0.6 | AA64: FALSE | AC64: a | AD64: 2 | AE64: 7 | AF64: 76 | AG64: 168465 | AH64: 0 | AI64: 295144 | AJ64: 0 | AK64: 0 | AL64: 15.8 | AM64: Onana | AO64: 21 | AP64: 45495 | AQ64: 37119 | AR64: FALSE | AS64: p449871 | AT64: 1755 | AU64: 2 | AV64: 0 | AW64: 6 | AX64: 26 | AY64: 0 | AZ64: 0 | BA64: 0 | BB64: 3 | BC64: 0 | BD64: 0 | BE64: 4 | BF64: 353 | BG64: 413.2 | BH64: 152.6 | BI64: 178 | BJ64: 74.4 | BK64: 99 | BL64: 72 | BM64: 48 | BN64: 219 | BO64: 21 | BP64: 1.68 | BQ64: 0.69 | BR64: 2.37 | BS64: 28.53 | CA64: 176 | CB64: 66 | CC64: 249 | CD64: 158 | CE64: 211 | CF64: 112 | CG64: 219 | CH64: 106 | CI64: 0.09 | CJ64: 0 | CK64: 0.04 | CL64: 0.13 | CM64: 1.46 | CN64: 1.33 | CO64: 361 | CP64: 224 | CQ64: 377 | CR64: 169 | CS64: 194 | CT64: 74 | CU64: 248 | CV64: 88 | CW64: 1.08 | CX64: 0.31 | CY64: 11.23 | CZ64: =O64&" "&Y64 -> Amadou Onana | DA64: =VLOOKUP(CZ64,[1]FINAL!$A$1:$AP$1000,MATCH("Element No.",[1]FINAL!$A$1:$AP$1,0),0) -> 48
A65: TRUE | B65: FALSE | C65: 0 | D65: 0 | E65: 577731 | F65: 0 | G65: 0 | H65: -1 | I65: 1 | J65: 0 | K65: 3 | L65: 0 | M65: 0 | N65: 0 | O65: Ben | P65: 0 | Q65: =DA65 -> #N/A | R65: FALSE | S65: has joined Falkirk on loan for the rest of the season. | T65: 2026-02-06T22:47:15.874946Z | U65: 44 | V65: 577731.jpg | W65: 0 | X65: FALSE | Y65: Broggio | Z65: 0.2 | AA65: FALSE | AC65: u | AD65: 2 | AE65: 7 | AF65: 0 | AG65: 38290 | AH65: 0 | AI65: 52801 | AJ65: 0 | AK65: 0 | AL65: 0 | AM65: Broggio | AO65: 241 | AP65: 45558 | AQ65: 39111 | AR65: FALSE | AS65: p577731 | AT65: 0 | AU65: 0 | AV65: 0 | AW65: 0 | AX65: 0 | AY65: 0 | AZ65: 0 | BA65: 0 | BB65: 0 | BC65: 0 | BD65: 0 | BE65: 0 | BF65: 0 | BG65: 0 | BH65: 0 | BI65: 0 | BJ65: 0 | BK65: 0 | BL65: 0 | BM65: 0 | BN65: 0 | BO65: 0 | BP65: 0 | BQ65: 0 | BR65: 0 | BS65: 0 | CA65: 694 | CB65: 267 | CC65: 689 | CD65: 269 | CE65: 670 | CF65: 262 | CG65: 696 | CH65: 269 | CI65: 0 | CJ65: 0 | CK65: 0 | CL65: 0 | CM65: 0 | CN65: 0 | CO65: 575 | CP65: 347 | CQ65: 615 | CR65: 217 | CS65: 700 | CT65: 272 | CU65: 363 | CV65: 124 | CW65: 0 | CX65: 0 | CY65: 0 | CZ65: =O65&" "&Y65 -> Ben Broggio | DA65: =VLOOKUP(CZ65,[1]FINAL!$A$1:$AP$1000,MATCH("Element No.",[1]FINAL!$A$1:$AP$1,0),0) -> #N/A
A66: TRUE | B66: FALSE | C66: 0 | D66: 0 | E66: 151589 | F66: 0 | G66: 0 | H66: 0 | I66: 0 | J66: 0 | K66: 3 | L66: 0 | M66: 0 | N66: 0 | O66: Leander | P66: 0 | Q66: =DA66 -> #N/A | R66: FALSE | S66: Has joined Real Oviedo permanently. | T66: 2025-08-20T13:31:56.822248Z | U66: 45 | V66: 151589.jpg | W66: 0 | X66: FALSE | Y66: Dendoncker | Z66: 0.1 | AA66: FALSE | AC66: u | AD66: 2 | AE66: 7 | AF66: 0 | AG66: 2169 | AH66: 0 | AI66: 33857 | AJ66: 0 | AK66: 0 | AL66: 0 | AM66: Dendoncker | AO66: 21 | AP66: 44805 | AQ66: 34804 | AR66: FALSE | AS66: p151589 | AT66: 0 | AU66: 0 | AV66: 0 | AW66: 0 | AX66: 0 | AY66: 0 | AZ66: 0 | BA66: 0 | BB66: 0 | BC66: 0 | BD66: 0 | BE66: 0 | BF66: 0 | BG66: 0 | BH66: 0 | BI66: 0 | BJ66: 0 | BK66: 0 | BL66: 0 | BM66: 0 | BN66: 0 | BO66: 0 | BP66: 0 | BQ66: 0 | BR66: 0 | BS66: 0 | CA66: 700 | CB66: 269 | CC66: 695 | CD66: 271 | CE66: 676 | CF66: 264 | CG66: 702 | CH66: 271 | CI66: 0 | CJ66: 0 | CK66: 0 | CL66: 0 | CM66: 0 | CN66: 0 | CO66: 414 | CP66: 250 | CQ66: 624 | CR66: 221 | CS66: 706 | CT66: 274 | CU66: 543 | CV66: 200 | CW66: 0 | CX66: 0 | CY66: 0 | CZ66: =O66&" "&Y66 -> Leander Dendoncker | DA66: =VLOOKUP(CZ66,[1]FINAL!$A$1:$AP$1000,MATCH("Element No.",[1]FINAL!$A$1:$AP$1,0),0) -> #N/A
A67: TRUE | B67: FALSE | C67: 0 | D67: 0 | E67: 559962 | F67: 0 | G67: 0 | H67: 0 | I67: 0 | J67: 0 | K67: 3 | L67: 0 | M67: 0 | N67: 0 | O67: Jamaldeen | P67: 0 | Q67: =DA67 -> #N/A | R67: FALSE | S67: has joined West Brom on loan for the rest of the season. | T67: 2026-02-06T22:47:15.891521Z | U67: 45 | V67: 559962.jpg | W67: 1 | X67: FALSE | Y67: Jimoh-Aloba | Z67: 0.1 | AA67: FALSE | AC67: u | AD67: 2 | AE67: 7 | AF67: 1 | AG67: 8790 | AH67: 0 | AI67: 11047 | AJ67: 0 | AK67: 0 | AL67: 0.2 | AM67: Jimoh-Aloba | AO67: 241 | AP67: 45558 | AQ67: 38992 | AR67: FALSE | AS67: p559962 | AT67: 8 | AU67: 0 | AV67: 0 | AW67: 0 | AX67: 0 | AY67: 0 | AZ67: 0 | BA67: 0 | BB67: 0 | BC67: 0 | BD67: 0 | BE67: 0 | BF67: 3 | BG67: 0.2 | BH67: 0.3 | BI67: 0 | BJ67: 0.1 | BK67: 0 | BL67: 1 | BM67: 0 | BN67: 1 | BO67: 0 | BP67: 0 | BQ67: 0 | BR67: 0 | BS67: 0.61 | CA67: 525 | CB67: 239 | CC67: 498 | CD67: 242 | CE67: 717 | CF67: 298 | CG67: 528 | CH67: 241 | CI67: 0 | CJ67: 0 | CK67: 0 | CL67: 0 | CM67: 6.86 | CN67: 0 | CO67: 471 | CP67: 287 | CQ67: 667 | CR67: 256 | CS67: 493 | CT67: 221 | CU67: 574 | CV67: 215 | CW67: 0 | CX67: 0 | CY67: 11.25 | CZ67: =O67&" "&Y67 -> Jamaldeen Jimoh-Aloba | DA67: =VLOOKUP(CZ67,[1]FINAL!$A$1:$AP$1000,MATCH("Element No.",[1]FINAL!$A$1:$AP$1,0),0) -> #N/A
A68: TRUE | B68: FALSE | C68: 0 | D68: 0 | E68: 537403 | F68: 0 | G68: 0 | H68: -2 | I68: 2 | J68: 0 | K68: 3 | L68: 0 | M68: 0 | N68: 0 | O68: Kadan | P68: 0 | Q68: =DA68 -> #N/A | R68: FALSE | S68: has joined Reading on loan for the rest of the season. | T68: 2026-02-06T22:47:15.909676Z | U68: 43 | V68: 537403.jpg | W68: 0 | X68: FALSE | Y68: Young | Z68: 0.5 | AA68: FALSE | AC68: u | AD68: 2 | AE68: 7 | AF68: 0 | AG68: 102090 | AH68: 0 | AI68: 135893 | AJ68: 0 | AK68: 0 | AL68: 0 | AM68: Young | AO68: 241 | AP68: 44905 | AQ68: 38736 | AR68: FALSE | AS68: p537403 | AT68: 0 | AU68: 0 | AV68: 0 | AW68: 0 | AX68: 0 | AY68: 0 | AZ68: 0 | BA68: 0 | BB68: 0 | BC68: 0 | BD68: 0 | BE68: 0 | BF68: 0 | BG68: 0 | BH68: 0 | BI68: 0 | BJ68: 0 | BK68: 0 | BL68: 0 | BM68: 0 | BN68: 0 | BO68: 0 | BP68: 0 | BQ68: 0 | BR68: 0 | BS68: 0 | CA68: 661 | CB68: 244 | CC68: 657 | CD68: 248 | CE68: 635 | CF68: 238 | CG68: 664 | CH68: 246 | CI68: 0 | CJ68: 0 | CK68: 0 | CL68: 0 | CM68: 0 | CN68: 0 | CO68: 615 | CP68: 363 | CQ68: 575 | CR68: 193 | CS68: 672 | CT68: 253 | CU68: 278 | CV68: 95 | CW68: 0 | CX68: 0 | CY68: 0 | CZ68: =O68&" "&Y68 -> Kadan Young | DA68: =VLOOKUP(CZ68,[1]FINAL!$A$1:$AP$1000,MATCH("Element No.",[1]FINAL!$A$1:$AP$1,0),0) -> #N/A
A69: TRUE | B69: FALSE | C69: 100 | D69: 100 | E69: 178301 | F69: 0 | G69: 0 | H69: -3 | I69: 3 | J69: 5 | K69: 4 | L69: 6.3 | M69: 9 | N69: 13 | O69: Ollie | P69: 9.5 | Q69: =DA69 -> 55 | R69: FALSE | T69: 2026-01-29T23:00:09.533353Z | U69: 87 | V69: 178301.jpg | W69: 4.5 | X69: FALSE | Y69: Watkins | Z69: 13 | AA69: FALSE | AC69: a | AD69: 2 | AE69: 7 | AF69: 167 | AG69: 3761213 | AH69: 0 | AI69: 5154207 | AJ69: 0 | AK69: 1.1 | AL69: 19.2 | AM69: Watkins | AO69: 241 | AP69: 44083 | AQ69: 35063 | AR69: FALSE | AS69: p178301 | AT69: 2833 | AU69: 16 | AV69: 4 | AW69: 9 | AX69: 38 | AY69: 0 | AZ69: 0 | BA69: 0 | BB69: 4 | BC69: 0 | BD69: 0 | BE69: 26 | BF69: 623 | BG69: 720.2 | BH69: 330.9 | BI69: 1206 | BJ69: 225.2 | BK69: 23 | BL69: 49 | BM69: 22 | BN69: 94 | BO69: 33 | BP69: 15.4 | BQ69: 1.18 | BR69: 16.58 | BS69: 43.39 | BX69: 3 | CA69: 47 | CB69: 5 | CC69: 126 | CD69: 7 | CE69: 2 | CF69: 2 | CG69: 12 | CH69: 4 | CI69: 0.49 | CJ69: 0 | CK69: 0.04 | CL69: 0.53 | CM69: 1.38 | CN69: 1.21 | CO69: 9 | CP69: 5 | CQ69: 1 | CR69: 1 | CS69: 32 | CT69: 5 | CU69: 28 | CV69: 8 | CW69: 1.05 | CX69: 0.29 | CY69: 2.99 | CZ69: =O69&" "&Y69 -> Ollie Watkins | DA69: =VLOOKUP(CZ69,[1]FINAL!$A$1:$AP$1000,MATCH("Element No.",[1]FINAL!$A$1:$AP$1,0),0) -> 55
A70: TRUE | B70: FALSE | C70: 0 | D70: 0 | E70: 576756 | F70: 0 | G70: 0 | H70: 0 | I70: 0 | J70: 0 | K70: 4 | L70: 0 | M70: 0 | N70: 0 | O70: Zépiqueno | P70: 0 | Q70: =DA70 -> #N/A | R70: FALSE | S70: has joined Huddersfield Town on loan for the rest of the season. | T70: 2025-09-02T13:26:36.441136Z | U70: 45 | V70: 576756.jpg | W70: 0 | X70: FALSE | Y70: Redmond | Z70: 0.3 | AA70: FALSE | AC70: u | AD70: 2 | AE70: 7 | AF70: 0 | AG70: 17574 | AH70: 0 | AI70: 85482 | AJ70: 0 | AK70: 0 | AL70: 0 | AM70: Redmond | AR70: FALSE | AS70: p576756 | AT70: 0 | AU70: 0 | AV70: 0 | AW70: 0 | AX70: 0 | AY70: 0 | AZ70: 0 | BA70: 0 | BB70: 0 | BC70: 0 | BD70: 0 | BE70: 0 | BF70: 0 | BG70: 0 | BH70: 0 | BI70: 0 | BJ70: 0 | BK70: 0 | BL70: 0 | BM70: 0 | BN70: 0 | BO70: 0 | BP70: 0 | BQ70: 0 | BR70: 0 | BS70: 0 | CA70: 749 | CB70: 80 | CC70: 743 | CD70: 79 | CE70: 730 | CF70: 79 | CG70: 750 | CH70: 80 | CI70: 0 | CJ70: 0 | CK70: 0 | CL70: 0 | CM70: 0 | CN70: 0 | CO70: 486 | CP70: 69 | CQ70: 679 | CR70: 72 | CS70: 752 | CT70: 81 | CU70: 337 | CV70: 55 | CW70: 0 | CX70: 0 | CY70: 0 | CZ70: =O70&" "&Y70 -> Zépiqueno Redmond | DA70: =VLOOKUP(CZ70,[1]FINAL!$A$1:$AP$1000,MATCH("Element No.",[1]FINAL!$A$1:$AP$1,0),0) -> #N/A
A71: TRUE | B71: FALSE | C71: 100 | D71: 100 | E71: 444884 | F71: 0 | G71: 0 | H71: -4 | I71: 4 | J71: 0 | K71: 3 | L71: -0.5 | M71: -0.5 | N71: 0 | O71: Harvey | P71: 0 | Q71: =DA71 -> 383 | R71: FALSE | T71: 2026-05-09T21:00:09.892280Z | U71: 51 | V71: 444884.jpg | W71: 1 | X71: FALSE | Y71: Elliott | Z71: 0.2 | AA71: FALSE | AC71: a | AD71: 2 | AE71: 7 | AF71: 5 | AG71: 95040 | AH71: 0 | AI71: 104382 | AJ71: 0 | AK71: 0 | AL71: 1 | AM71: Elliott | AO71: 241 | AP71: 45901 | AQ71: 37715 | AR71: FALSE | AS71: p444884 | AT71: 110 | AU71: 0 | AV71: 0 | AW71: 0 | AX71: 2 | AY71: 0 | AZ71: 0 | BA71: 0 | BB71: 0 | BC71: 0 | BD71: 0 | BE71: 0 | BF71: 17 | BG71: 11.8 | BH71: 31.7 | BI71: 31 | BJ71: 7.4 | BK71: 2 | BL71: 4 | BM71: 0 | BN71: 6 | BO71: 1 | BP71: 0.29 | BQ71: 0.08 | BR71: 0.37 | BS71: 1.74 | CA71: 476 | CB71: 210 | CC71: 396 | CD71: 199 | CE71: 378 | CF71: 191 | CG71: 453 | CH71: 203 | CI71: 0.24 | CJ71: 0 | CK71: 0.07 | CL71: 0.31 | CM71: 1.42 | CN71: 1.64 | CO71: 232 | CP71: 142 | CQ71: 784 | CR71: 341 | CS71: 516 | CT71: 238 | CU71: 409 | CV71: 141 | CW71: 0.82 | CX71: 0 | CY71: 4.91 | CZ71: =O71&" "&Y71 -> Harvey Elliott | DA71: =VLOOKUP(CZ71,[1]FINAL!$A$1:$AP$1000,MATCH("Element No.",[1]FINAL!$A$1:$AP$1,0),0) -> 383
A72: TRUE | B72: FALSE | C72: 100 | D72: 100 | E72: 209243 | F72: 0 | G72: 0 | H72: -2 | I72: 2 | J72: 0 | K72: 3 | L72: 0.5 | M72: 0.3 | N72: 0 | O72: Jadon | P72: 0.8 | Q72: =DA72 -> #N/A | R72: FALSE | T72: 2026-03-27T21:00:10.454595Z | U72: 58 | V72: 209243.jpg | W72: 1.6 | X72: FALSE | Y72: Sancho | Z72: 0.2 | AA72: FALSE | AC72: a | AD72: 2 | AE72: 7 | AF72: 37 | AG72: 53465 | AH72: 0 | AI72: 56572 | AJ72: 0 | AK72: 0.1 | AL72: 6.4 | AM72: Sancho | AO72: 241 | AP72: 45901 | AQ72: 36610 | AR72: FALSE | AS72: p209243 | AT72: 863 | AU72: 0 | AV72: 2 | AW72: 2 | AX72: 10 | AY72: 0 | AZ72: 0 | BA72: 0 | BB72: 0 | BC72: 0 | BD72: 0 | BE72: 0 | BF72: 141 | BG72: 130.2 | BH72: 290.6 | BI72: 193 | BJ72: 61.6 | BK72: 11 | BL72: 26 | BM72: 7 | BN72: 44 | BO72: 9 | BP72: 0.61 | BQ72: 1.87 | BR72: 2.48 | BS72: 14.11 | BT72: 6 | CA72: 371 | CB72: 166 | CC72: 152 | CD72: 100 | CE72: 192 | CF72: 102 | CG72: 263 | CH72: 130 | CI72: 0.06 | CJ72: 0 | CK72: 0.2 | CL72: 0.26 | CM72: 1.47 | CN72: 1.04 | CO72: 106 | CP72: 69 | CQ72: 317 | CR72: 142 | CS72: 418 | CT72: 180 | CU72: 368 | CV72: 126 | CW72: 0.94 | CX72: 0.21 | CY72: 4.59 | CZ72: =O72&" "&Y72 -> Jadon Sancho | DA72: =VLOOKUP(CZ72,[1]FINAL!$A$1:$AP$1000,MATCH("Element No.",[1]FINAL!$A$1:$AP$1,0),0) -> #N/A
A73: TRUE | B73: FALSE | E73: 481283 | F73: 0 | G73: 0 | H73: -1 | I73: 1 | J73: 0 | K73: 1 | L73: -0.5 | M73: -0.5 | N73: 0 | O73: James | P73: 0 | Q73: =DA73 -> #N/A | R73: FALSE | U73: 39 | V73: 481283.jpg | W73: 0 | X73: FALSE | Y73: Wright | Z73: 0.6 | AA73: FALSE | AC73: a | AD73: 2 | AE73: 7 | AF73: 0 | AG73: 62596 | AH73: 0 | AI73: 48936 | AJ73: 0 | AK73: 0 | AL73: 0 | AM73: Wright | AO73: 241 | AP73: 45016 | AQ73: 38323 | AR73: FALSE | AS73: p481283 | AT73: 0 | AU73: 0 | AV73: 0 | AW73: 0 | AX73: 0 | AY73: 0 | AZ73: 0 | BA73: 0 | BB73: 0 | BC73: 0 | BD73: 0 | BE73: 0 | BF73: 0 | BG73: 0 | BH73: 0 | BI73: 0 | BJ73: 0 | BK73: 0 | BL73: 0 | BM73: 0 | BN73: 0 | BO73: 0 | BP73: 0 | BQ73: 0 | BR73: 0 | BS73: 0 | CA73: 564 | CB73: 57 | CC73: 549 | CD73: 40 | CE73: 518 | CF73: 25 | CG73: 567 | CH73: 57 | CI73: 0 | CJ73: 0 | CK73: 0 | CL73: 0 | CM73: 0 | CN73: 0 | CO73: 782 | CP73: 84 | CQ73: 446 | CR73: 47 | CS73: 575 | CT73: 57 | CU73: 256 | CV73: 34 | CW73: 0 | CX73: 0 | CY73: 0 | CZ73: =O73&" "&Y73 -> James Wright | DA73: =VLOOKUP(CZ73,[1]FINAL!$A$1:$AP$1000,MATCH("Element No.",[1]FINAL!$A$1:$AP$1,0),0) -> #N/A
A74: TRUE | B74: FALSE | C74: 100 | D74: 100 | E74: 230046 | F74: 0 | G74: 0 | H74: -1 | I74: 1 | J74: 0 | K74: 3 | L74: 0 | M74: 0.5 | N74: 2 | O74: Douglas Luiz | P74: 1 | Q74: =DA74 -> #N/A | R74: FALSE | T74: 2025-11-01T18:30:08.443766Z | U74: 49 | V74: 230046.jpg | W74: 1.7 | X74: FALSE | Y74: Soares de Paulo | Z74: 0.1 | AA74: FALSE | AC74: a | AD74: 2 | AE74: 7 | AF74: 35 | AG74: 29269 | AH74: 0 | AI74: 25967 | AJ74: 0 | AK74: 0.2 | AL74: 7.1 | AM74: Douglas Luiz | AN74: Douglas Luiz | AO74: 30 | AP74: 46050 | AQ74: 35924 | AR74: FALSE | AS74: p230046 | AT74: 913 | AU74: 1 | AV74: 1 | AW74: 1 | AX74: 15 | AY74: 0 | AZ74: 0 | BA74: 0 | BB74: 3 | BC74: 0 | BD74: 0 | BE74: 0 | BF74: 220 | BG74: 201.6 | BH74: 294.3 | BI74: 94 | BJ74: 59.1 | BK74: 31 | BL74: 52 | BM74: 22 | BN74: 105 | BO74: 12 | BP74: 0.53 | BQ74: 1.42 | BR74: 1.95 | BS74: 13.24 | BT74: 1 | CA74: 310 | CB74: 133 | CC74: 149 | CD74: 98 | CE74: 297 | CF74: 157 | CG74: 271 | CH74: 136 | CI74: 0.05 | CJ74: 0 | CK74: 0.14 | CL74: 0.19 | CM74: 1.31 | CN74: 1.48 | CO74: 310 | CP74: 192 | CQ74: 285 | CR74: 126 | CS74: 404 | CT74: 174 | CU74: 529 | CV74: 193 | CW74: 1.18 | CX74: 0.1 | CY74: 10.35 | CZ74: =O74&" "&Y74 -> Douglas Luiz Soares de Paulo | DA74: =VLOOKUP(CZ74,[1]FINAL!$A$1:$AP$1000,MATCH("Element No.",[1]FINAL!$A$1:$AP$1,0),0) -> #N/A
A75: TRUE | B75: FALSE | C75: 0 | D75: 0 | E75: 569577 | F75: 0 | G75: 0 | H75: 0 | I75: 0 | J75: 0 | K75: 2 | L75: 0 | M75: 0 | N75: 0 | O75: Triston | P75: 0 | Q75: =DA75 -> #N/A | R75: FALSE | S75: has joined Annecy on loan for the rest of the season. | T75: 2025-09-22T21:15:59.825051Z | U75: 40 | V75: 569577.jpg | W75: 0 | X75: FALSE | Y75: Rowe | Z75: 0.1 | AA75: FALSE | AC75: u | AD75: 2 | AE75: 7 | AF75: 0 | AG75: 8943 | AH75: 0 | AI75: 10853 | AJ75: 0 | AK75: 0 | AL75: 0 | AM75: Rowe | AO75: 241 | AP75: 45558 | AQ75: 38992 | AR75: FALSE | AS75: p569577 | AT75: 0 | AU75: 0 | AV75: 0 | AW75: 0 | AX75: 0 | AY75: 0 | AZ75: 0 | BA75: 0 | BB75: 0 | BC75: 0 | BD75: 0 | BE75: 0 | BF75: 0 | BG75: 0 | BH75: 0 | BI75: 0 | BJ75: 0 | BK75: 0 | BL75: 0 | BM75: 0 | BN75: 0 | BO75: 0 | BP75: 0 | BQ75: 0 | BR75: 0 | BS75: 0 | CA75: 624 | CB75: 234 | CC75: 616 | CD75: 233 | CE75: 586 | CF75: 230 | CG75: 627 | CH75: 234 | CI75: 0 | CJ75: 0 | CK75: 0 | CL75: 0 | CM75: 0 | CN75: 0 | CO75: 733 | CP75: 193 | CQ75: 516 | CR75: 200 | CS75: 634 | CT75: 233 | CU75: 544 | CV75: 193 | CW75: 0 | CX75: 0 | CY75: 0 | CZ75: =O75&" "&Y75 -> Triston Rowe | DA75: =VLOOKUP(CZ75,[1]FINAL!$A$1:$AP$1000,MATCH("Element No.",[1]FINAL!$A$1:$AP$1,0),0) -> #N/A
A76: TRUE | B76: FALSE | E76: 645618 | F76: 0 | G76: 0 | H76: -2 | I76: 2 | J76: 0 | K76: 3 | L76: -0.5 | M76: -0.5 | N76: 0 | O76: Bradley | P76: 0 | Q76: =DA76 -> 50 | R76: FALSE | U76: 43 | V76: 645618.jpg | W76: 1 | X76: FALSE | Y76: Burrowes | Z76: 0.1 | AA76: FALSE | AC76: a | AD76: 2 | AE76: 7 | AF76: 1 | AG76: 20893 | AH76: 0 | AI76: 12404 | AJ76: 0 | AK76: 0 | AL76: 0.2 | AM76: Burrowes | AO76: 241 | AP76: 45666 | AQ76: 39511 | AR76: FALSE | AS76: p645618 | AT76: 16 | AU76: 0 | AV76: 0 | AW76: 0 | AX76: 1 | AY76: 0 | AZ76: 0 | BA76: 0 | BB76: 0 | BC76: 0 | BD76: 0 | BE76: 0 | BF76: 3 | BG76: 0 | BH76: 0.3 | BI76: 0 | BJ76: 0 | BK76: 0 | BL76: 1 | BM76: 0 | BN76: 1 | BO76: 0 | BP76: 0 | BQ76: 0 | BR76: 0 | BS76: 0.9 | CA76: 672 | CB76: 254 | CC76: 497 | CD76: 241 | CE76: 645 | CF76: 248 | CG76: 674 | CH76: 256 | CI76: 0 | CJ76: 0 | CK76: 0 | CL76: 0 | CM76: 5.06 | CN76: 5.62 | CO76: 631 | CP76: 377 | CQ76: 587 | CR76: 204 | CS76: 483 | CT76: 211 | CU76: 443 | CV76: 152 | CW76: 0 | CX76: 0 | CY76: 5.62 | CZ76: =O76&" "&Y76 -> Bradley Burrowes | DA76: =VLOOKUP(CZ76,[1]FINAL!$A$1:$AP$1000,MATCH("Element No.",[1]FINAL!$A$1:$AP$1,0),0) -> 50
A77: TRUE | B77: FALSE | E77: 564505 | F77: 0 | G77: 0 | H77: -1 | I77: 1 | J77: 0 | K77: 1 | L77: -0.5 | M77: -0.5 | N77: 0 | O77: Sam | P77: 0 | Q77: =DA77 -> #N/A | R77: FALSE | U77: 39 | V77: 564505.jpg | W77: 0 | X77: FALSE | Y77: Proctor | Z77: 0.6 | AA77: FALSE | AC77: a | AD77: 2 | AE77: 7 | AF77: 0 | AG77: 95367 | AH77: 0 | AI77: 52276 | AJ77: 0 | AK77: 0 | AL77: 0 | AM77: Proctor | AO77: 241 | AP77: 45276 | AQ77: 39072 | AR77: FALSE | AS77: p564505 | AT77: 0 | AU77: 0 | AV77: 0 | AW77: 0 | AX77: 0 | AY77: 0 | AZ77: 0 | BA77: 0 | BB77: 0 | BC77: 0 | BD77: 0 | BE77: 0 | BF77: 0 | BG77: 0 | BH77: 0 | BI77: 0 | BJ77: 0 | BK77: 0 | BL77: 0 | BM77: 0 | BN77: 0 | BO77: 0 | BP77: 0 | BQ77: 0 | BR77: 0 | BS77: 0 | CA77: 573 | CB77: 63 | CC77: 559 | CD77: 47 | CE77: 528 | CF77: 32 | CG77: 576 | CH77: 63 | CI77: 0 | CJ77: 0 | CK77: 0 | CL77: 0 | CM77: 0 | CN77: 0 | CO77: 793 | CP77: 91 | CQ77: 456 | CR77: 53 | CS77: 584 | CT77: 63 | CU77: 257 | CV77: 35 | CW77: 0 | CX77: 0 | CY77: 0 | CZ77: =O77&" "&Y77 -> Sam Proctor | DA77: =VLOOKUP(CZ77,[1]FINAL!$A$1:$AP$1000,MATCH("Element No.",[1]FINAL!$A$1:$AP$1,0),0) -> #N/A
A78: TRUE | B78: FALSE | E78: 534836 | F78: 0 | G78: 0 | H78: -1 | I78: 1 | J78: 0 | K78: 2 | L78: -0.5 | M78: -0.5 | N78: 0 | O78: Travis | P78: 0 | Q78: =DA78 -> #N/A | R78: FALSE | U78: 39 | V78: 534836.jpg | W78: 0 | X78: FALSE | Y78: Patterson | Z78: 0.2 | AA78: FALSE | AC78: a | AD78: 2 | AE78: 7 | AF78: 0 | AG78: 34014 | AH78: 0 | AI78: 24439 | AJ78: 0 | AK78: 0 | AL78: 0 | AM78: Patterson | AO78: 241 | AP78: 45899 | AQ78: 38631 | AR78: FALSE | AS78: p534836 | AT78: 0 | AU78: 0 | AV78: 0 | AW78: 0 | AX78: 0 | AY78: 0 | AZ78: 0 | BA78: 0 | BB78: 0 | BC78: 0 | BD78: 0 | BE78: 0 | BF78: 0 | BG78: 0 | BH78: 0 | BI78: 0 | BJ78: 0 | BK78: 0 | BL78: 0 | BM78: 0 | BN78: 0 | BO78: 0 | BP78: 0 | BQ78: 0 | BR78: 0 | BS78: 0 | CA78: 570 | CB78: 207 | CC78: 556 | CD78: 206 | CE78: 525 | CF78: 202 | CG78: 573 | CH78: 207 | CI78: 0 | CJ78: 0 | CK78: 0 | CL78: 0 | CM78: 0 | CN78: 0 | CO78: 790 | CP78: 228 | CQ78: 453 | CR78: 168 | CS78: 581 | CT78: 207 | CU78: 389 | CV78: 142 | CW78: 0 | CX78: 0 | CY78: 0 | CZ78: =O78&" "&Y78 -> Travis Patterson | DA78: =VLOOKUP(CZ78,[1]FINAL!$A$1:$AP$1000,MATCH("Element No.",[1]FINAL!$A$1:$AP$1,0),0) -> #N/A
A79: TRUE | B79: FALSE | C79: 100 | D79: 100 | E79: 184667 | F79: 0 | G79: 0 | H79: 0 | I79: 0 | J79: 0 | K79: 2 | L79: 0.3 | M79: 0.7 | N79: 2 | O79: Victor | P79: 1.2 | Q79: =DA79 -> 37 | R79: FALSE | T79: 2025-09-18T04:00:08.433120Z | U79: 45 | V79: 184667.jpg | W79: 1.7 | X79: FALSE | Y79: Lindelöf | Z79: 0.1 | AA79: FALSE | AC79: a | AD79: 2 | AE79: 7 | AF79: 29 | AG79: 22854 | AH79: 0 | AI79: 16638 | AJ79: 0 | AK79: 0.3 | AL79: 6.4 | AM79: Lindelöf | AO79: 206 | AP79: 45901 | AQ79: 34532 | AR79: FALSE | AS79: p184667 | AT79: 942 | AU79: 0 | AV79: 1 | AW79: 1 | AX79: 15 | AY79: 0 | AZ79: 0 | BA79: 0 | BB79: 0 | BC79: 0 | BD79: 0 | BE79: 0 | BF79: 124 | BG79: 167.8 | BH79: 36.6 | BI79: 22 | BJ79: 22.7 | BK79: 47 | BL79: 19 | BM79: 7 | BN79: 54 | BO79: 11 | BP79: 0.28 | BQ79: 0.1 | BR79: 0.38 | BS79: 15.93 | CA79: 331 | CB79: 127 | CC79: 388 | CD79: 139 | CE79: 398 | CF79: 142 | CG79: 390 | CH79: 137 | CI79: 0.03 | CJ79: 0 | CK79: 0.01 | CL79: 0.04 | CM79: 1.52 | CN79: 1.43 | CO79: 418 | CP79: 78 | CQ79: 250 | CR79: 93 | CS79: 397 | CT79: 145 | CU79: 484 | CV79: 176 | CW79: 1.05 | CX79: 0.1 | CY79: 5.16 | CZ79: =O79&" "&Y79 -> Victor Lindelöf | DA79: =VLOOKUP(CZ79,[1]FINAL!$A$1:$AP$1000,MATCH("Element No.",[1]FINAL!$A$1:$AP$1,0),0) -> 37
